Workbook

Sheet Cover
A5: K-Beauty & Medical Premium Tour Package for Muslim VIP Clients
A21: 2026.02.13
B27: Package Highlights (Trust + Religious Reassurance + Premium Value)
C31: ✔ Halal & Muslim-Friendly Services (Verified Partners)
C32: ✔ Privacy & Gender-Sensitive Care
C33: ✔ Female Doctor & Therapist Options
C34: ✔ Alcohol-Free Medical & Beauty Products (on request)
C35: ✔ Luxury Hotel Accommodation
C36: ✔ Private Vehicle Service
C37: – Optional Halal-Certified Limousine (Prayer Space Available)
C38: ✔ Fully Private Schedule
C39: ✔ Halal Dining Arrangements & Muslim-Friendly Options
C40: ✔ Arabic / English Coordination Support
C41: ✔ Prayer Times Considered in Daily Schedule
C42: ✔ Transparent Pricing
B47: Travel & Service Overview
B48: (Basic Information for Service Coordination)
B51: 1. | C51: Concept | D51: : K-Beauty + Medical + Wellness (Tour / Leisure / K-Pop Experience) + Luxury
B53: 2. | C53: Destination & Travelers
B54: ● | C54: Destination | D54: : Republic of Korea
B55: ● | C55: Total Travelers | D55: : [ ] Persons (Family / Companion / Others: [ ] )
B57: 3. | C57: Flight Schedule
B58: ● | C58: OUT(Outbound) | D58: : Departure - Mar. 10. 2026. 03:30 (Dubai) / Arrival - Mar. 10. 2026. 16:50 (Incheon)
B59: ● | C59: IN(Inbound) | D59: : Departure - Mar. 19. 2026. 23:40 (Incheon) / Arrival - Mar. 20. 2026. 05:05 (Dubai)
B61: 4. | C61: Prepared by
B62: ● | C62: Agent Name / Company | D62: :
B63: ● | C63: Meeting Date | D63: :
B66: VIP Essentials & Preferences
B68: 1. | C68: VIP Information
B69: ● | C69: Full name | D69: : Michael Hong
B70: ● | C70: Gender | D70: [ ] Male / [ ] Female
B71: ● | C71: Date of Birth | D71: : Feb. OO, 197X(Age: 5X)
B72: ● | C72: Nationality | D72: : Korean
B73: ● | C73: Passport No | D73: : DMC 0000000000
B75: 2. | C75: Contact Information
B76: ● | C76: Phone Number | D76: : +971-00-00-000
B77: ● | C77: Email Address | D77: : example@example.com
B78: ● | C78: Emergency Contact | D78: : Name: [ ] / Relation: [ ] / Phone: [ ]
B80: 3. | C80: Medical & Special Information
B81: ● | C81: Health Conditions | D81: : | E81: ● | F81: Medical Restrictions | G81: :
B82: ● | C82: Blood Type | D82: : | E82: ● | F82: Allergies & Adverse Drug Reactions | G82: :
B83: ● | C83: Current Medications | D83: : | E83: ● | F83: Special Requests | G83: :
B84: ● | C84: Others | D84: :
B86: 4. | C86: Service Preferences & Religious Considerations
B87: 1) | C87: Prayer Preferences
B88: ● | C88: Prayer Frequency | D88: ☐ All 5 daily prayers ☐ Flexible depending on travel schedule
B89: ● | C89: Prayer Location Preference | D89: ☐ Hotel ☐ Vehicle (halal-certified limousine, if convenient)
D90: ☐ External Prayer Room (if available) ☐ Mosque (if schedule permits)
B92: 2) | C92: Dietary
B93: ● | C93: Dietary requirements & preferences | D93: :
B95: 3) | C95: Medical & Care Preferences
B96: ● | C96: Same-gender doctor | D96: ☐ Required ☐ Preferred ☐ No preference
B97: ● | C97: Same-gender therapist | D97: ☐ Required ☐ Preferred ☐ No preference
B99: 4) | C99: Schedule & Companion Preferences
B100: ● | C100: Mixed-gender activities | D100: ☐ Comfortable ☐ Prefer to limit ☐ Not comfortable
B102: 5) | C102: Additional Preferences or Notes
B103: ● | C103: Cultural, religious, or personal requests | D103: :

Sheet (1) Selection_K-Medical
A1: K-Medical Selection Sheet for Schedule
B3: Name (M or F) : | C3: =Cover!$D$69 -> : Michael Hong | F3: Passport No. : | G3: =Cover!$D$73 -> : DMC 0000000000
B4: Birth Date : | C4: =Cover!$D$71 -> : Feb. OO, 197X(Age: 5X) | F4: Arrival Flight Schedule (Local Time): | G4: =Cover!$D$58 -> : Departure - Mar. 10. 2026. 03:30 (Dubai) / Arrival - Mar. 10. 2026. 16:50 (Incheon)
B5: VIPs Contact. : | C5: =_xlfn.TEXTJOIN(" / ", TRUE, Cover!$D$76:$D$77) -> : +971-00-00-000 / : example@example.com | F5: Departure Flight Schedule (Local Time) : | G5: =Cover!$D$59 -> : Departure - Mar. 19. 2026. 23:40 (Incheon) / Arrival - Mar. 20. 2026. 05:05 (Dubai)
A7: Premium Package Category | F7: Check (ex.) | G7: Remarks | H7: Customer Requirement
A8: Package | C8: Package detail | D8: Duration | E8: Estimated Price (USD)
A9: K-Medical | B9: Silver | C9: Purpose * Quick overview of current health status * Early detection of basic health risks * Entry-level screening with minimal time and burden Core Inclusions * Physical measurements (height, weight, BMI, blood pressure) * Basic blood tests (liver, kidney, glucose, lipid profile) * Urinalysis * Chest X-ray * Basic consultation | D9: 1day | E9: M: 990 - 1,200 F: 1,110 - 1733.33 | G9: Surgery excluded After the medical check-up, please indicate whether you would prefer to rest at the hospital or at your hotel.
B10: Gold | C10: Purpose * Early detection of common diseases * In-depth evaluation of major organs * Most common comprehensive check-up level in Korea Core Inclusions * All BASIC items * Abdominal ultrasound * Gastroscopy / Colonoscopy (or alternatives) * Cardiovascular tests (ECG, arteriosclerosis) * Cancer screening (age & gender-based) * Specialist consultation | D10: 1day | E10: M: 3,506.53 - 12,376 F: 3,900 - 12,000
A11: Premium Package Category | F11: Check (ex.) | G11: Remarks | H11: Customer Requirement
A12: Package | C12: Package detail | D12: Duration | E12: Estimated Price (USD)
A13: K-Medical | B13: Diamond (Premium) | C13: Purpose * High-precision diagnostics and personalized risk assessment * Prediction and prevention of future health issues * VIP-level medical experience Core Inclusions * All STANDARD items * Advanced imaging (CT, MRI, heart/brain scans) * Advanced cancer screening panels * Hormone, immune, metabolic analysis * Optional genetic testing * One-on-one expert consultation * Personalized health report | D13: Min.2day | E13: M: 11,519.20 - 16,818.67 F: 12,518.80 - 17,294.67 | F13: ✔ | G13: Surgery excluded After the medical check-up, please indicate whether you would prefer to rest at the hospital or at your hotel.

Sheet (2) Selection_K-Beauty_Medical
A1: K-Medical Selection Sheet for Schedule
C3: Name (M or F) : | D3: =Cover!$D$69 -> : Michael Hong | G3: Passport No. : | H3: =Cover!$D$73 -> : DMC 0000000000
C4: Birth Date : | D4: =Cover!$D$71 -> : Feb. OO, 197X(Age: 5X) | G4: Arrival Flight Schedule (Local Time): | H4: =Cover!$D$58 -> : Departure - Mar. 10. 2026. 03:30 (Dubai) / Arrival - Mar. 10. 2026. 16:50 (Incheon)
C5: VIPs Contact. : | D5: =_xlfn.TEXTJOIN(" / ", TRUE, Cover!$D$76:$D$77) -> : +971-00-00-000 / : example@example.com | G5: Departure Flight Schedule (Local Time) : | H5: =Cover!$D$59 -> : Departure - Mar. 19. 2026. 23:40 (Incheon) / Arrival - Mar. 20. 2026. 05:05 (Dubai)
A8: Premium Package Category | G8: Check (ex.) | H8: Remarks | I8: Customer Requirement
A9: Package | D9: Package detail | E9: Duration | F9: Estimated Price (USD)
A10: K-Beauty (Medical) | B10: A Clinic | C10: Juvénile | D10: "A Clinic" is the VVIP stem cell center at "A Clinic", offering an exclusive private regenerative program that rejuvenates not only the skin but your entire body. Moving beyond simple treatments, our program is built on precise stem-cell-based solutions that address the root causes of aging, helping you preserve firm, radiant skin and enhance your overall wellness.
C11: All-Layer | D11: All-Layer is our specialized lifting and tightening center, dedicated to refining your natural beauty by precisely treating every layer of the skin — from the surface to the deep muscle tissue. Beyond superficial improvements, we perform a comprehensive, multi-layer analysis of your skin’s structure to deliver a fully personalized solution. This approach restores harmonious balance to your facial volume, elasticity, and texture.
C12: Sportif | D12: "A Clinic" is a specialized total body conditioning center for professional athletes needing pre/post-game care, and for individuals seeking recovery after physical activities such as tennis and golf. We provide personalized care designed to maximize athletic performance, including rapid post-workout recovery, muscle fatigue relief, and body contour refinement. Our tailored solutions encompass everything from pre- and post-competition care for athletes, diet management, postpartum recovery, to body contouring.
C13: Glow Package | D13: Ultherapy 400 shots + Sofwave 300 pulses + Eye Thermage 450 shots + Premium Rejuran Glow Toxin + Premium Skin Care Treatment | E13: 120m | F13: 6666.67
C14: Premium Anti-Aging Package | D14: Stem Cell IV Therapy + Ultherapy 400 shots + Sofwave 300 pulses + Eye Thermage 450 shots + Titanium or BBL Hero + Premium Rejuran Glow Toxin + Premium Skin Care Treatment | E14: 180m | F14: 13333.33
C15: Premium Stem Cell Anti-Aging Package | D15: Activated Stem Cell IV Therapy + Stem Cell Facial Treatment + Ultherapy 600 shots + Sofwave 300 pulses + Titanium or BBL Hero + Premium Skin Care Treatment | E15: 180m | F15: 20000
C16: Premiun Body Package | D16: Ultherapy Prime 3,000 shots (Abdomen, Arms, Thighs) + Sofwave 1,500 pulses (Abdomen, Arms, Thighs) + Full Body BBL HERO + Manual Body Treatment + Hyperbaric Oxygen Therapy + Stem Cell IV Therapy + Premium Skin Care Treatment | E16: 480m | F16: 33333.33 | G16: ✔
A19: Premium Package Category | G19: Check (ex.) | H19: Remarks | I19: Customer Requirement
A20: Package | D20: Package detail | E20: Duration | F20: Estimated Price (USD)
A21: K-Beauty (Medical) | B21: B Clinic | C21: Special (Stem Cell) | D21: Blood Stem Cell Full Face + Stem cell intravenous injection + Premium SkinCeuticals Antioxidant Care | E21: 120m
C22: Basic | D22: S-1 or S-2 + Basic : 1 vial Sculptra or Juvederm Filler 3cc (No restrictions on body part) + Premium SkinCeuticals Antioxidant Care | E22: 120m | F22: 15,866.67 - 23,800
C23: Gold | D23: S-1 or S-2 + Gold : Rejuran HB 4cc + Full Face Skin Botox + Thermage FLX 900 Shot(Face+Neck)+ 1 vial Sculptra (No restrictions on body part) + Premium SkinCeuticals Antioxidant Care | E23: 120m | F23: 23,800 - 31,733.33
C24: Platinum | D24: S-1 or S-2 + Platinum : Rejuran HB 4cc + Full Face Skin Botox + Ultherapy HIFU Prime 600 shot + Thermage FLX 900 Shot(Face+Neck) + Premium SkinCeuticals Antioxidant Care + Premium SkinCeuticals(55ml) Ampoule giveaway | E24: 180m | F24: 31,733.33 - 39,666.67 | G24: ✔
B25: C Clinic | C25: Royal Refresh Day (Face only, no injection) | D25: Ultherapy Prime 600 shots, Thermage 600 shots, Eye Thermage 225 shots, LDM therapy (12 minutes), Radio-Frequency facial care, 24K Gold Therapy, Regenerative LED treatment | E25: 180m | F25: 7933.33
C26: Royal Signature Lifting (Including neck & fatigue recovery) | D26: Ultherapy Prime 600 shots, Ultherapy Prime 200 shots (Neck), Eye Ultherapy Prime 200 shots Thermage 600 shots, Volumer 200 shots (Neck), Eye Thermage 225 shots, Titanium 100 kJ Pico Toning, Rejuran Healer 4cc, Rejuran Eye 2cc, Juvelook Skin 4cc, Mega Complex Vitamin IV Therapy, Premium Nutrition IV Therapy, RejuDM Premium Care(24K Gold therapy+Cryo therapy+LDM Rejuran Skin Booster(2 vials)+LED light therapy+Modeling pack) Radio-Frequency facial & neck care | E26: 240m | F26: 15866.67
C27: Royal Face & Body Refinement (Royal Hospital Takeover) | D27: Ultherapy Prime 600 shots, Ultherapy Prime 200 shots (Neck), Eye Ultherapy Prime 200 shots Thermage 600 shots, Volumer 200 shots (Neck), Eye Thermage 225 shots, Titanium 100 kJ Pico Dual Toning, Rejuran Healer 4cc, Rejuran Eye 2cc, Juvelook Skin 4cc Mega Complex Vitamin IV Therapy, Premium Nutrition IV Therapy RejuDM Premium Care(24K Gold therapy+Cryo therapy+LDM Rejuran Skin Booster(2 vials)+LED light therapy+Modeling pack) Radio-Frequency facial & neck care, Ultrasound facial & neck care | E27: 540m | F27: 23800 | G27: ✔

Sheet Information_K-Beauty_Medical
A1: K-Beauty_Medical Information for Schedule
A5: K-Beauty Dermatology Clinic Category
A6: Package | D6: Treatment Objective | E6: Signature Treatments | F6: Key Ingredients & Medications & Injectable Products | G6: Medical Devices | H6: A CLINIC | I6: B CLINIC | J6: C CLINIC
A7: K-Beauty (Medical) | B7: ① | C7: Brightening & Skin Tone Correction | D7: • Improve uneven skin tone • Reduce pigmentation, melasma, and sun damage • Achieve luminous and clear complexion | E7: • Pico Laser Toning • Laser Whitening Program • Glutathione IV Therapy • Medical Brightening Ampoule Infusion | F7: • Glutathione • Vitamin C Complex • Tranexamic Acid • Niacinamide | G7: • PicoSure / PicoWay Laser • Nd:YAG Laser • IPL (Lumenis M22) | I7: Full Face Skin Botox Blood Stem Cell Full Face Stem cell intravenous injection | J7: Pico Dual Toning RejuDM Premium Care(24K Gold therapy+Cryo therapy+LDM Rejuran Skin Booster(2 vials)+LED light Rejuran Healer 4cc, Rejuran Eye 2cc, | K7: Brightening & Skin Tone Correction (미백 & 피부톤개선)
B8: ② | C8: Anti-Aging & Skin Rejuvenation | D8: • Restore youthful skin quality • Stimulate collagen and cellular regeneration • mprove fine lines and skin elasticity | E8: • Skin Booster Therapy • PRP (Platelet-Rich Plasma) • Exosome Rejuvenation • Regenerative Laser Therapy | F8: • PDRN (Salmon DNA) • Hyaluronic Acid • Growth Factors • Medical-grade Exosomes | G8: • RF Microneedling Systems • Fractional Rejuvenation Lasers • LED Regenerative Therapy | I8: Blood Stem Cell Full Face Stem cell intravenous injection | J8: Radio-Frequency facial & neck care Juvelook Skin 4cc RejuDM Premium Care(24K Gold therapy+Cryo therapy+LDM Rejuran Skin Booster(2 vials)+LED light Rejuran Healer 4cc, Rejuran Eye 2cc, | K8: Anti-Aging & Skin Rejuvenation (안티에이징&피부재생)
B9: ③ | C9: Lifting & Facial Contouring | D9: • Improve skin sagging and facial laxity • Enhance jawline and facial contour • Non-surgical lifting solutions | E9: • HIFU Lifting • Radiofrequency Skin Tightening • Premium Thread Lifting | F9: • PDO / PLLA Threads • Collagen Stimulating Agents | G9: • Ultherapy (HIFU) • Shurink Universe • InMode (Forma / FX) • Density RF System | I9: Thermage FLX 900 Shot(Face+Neck) 1 vial Sculptra (No restrictions on body part) Blood Stem Cell Full Face Ultherapy HIFU Prime 600 shot Stem cell intravenous injection | J9: Ultherapy Prime 600 shots, Ultherapy Prime 600 shots(Neck), Ultherapy Prime 600 shots(Eye) Thermage 600 shots, Thermage 225 shots(Eye) Rejuran Healer 4cc, Rejuran Eye 2cc, Volumer 200 shots (Neck). Titanium 100 kJ Ultrasound facial & neck care | K9: Lifting & Facial Contouring (리프팅&윤곽개선)
B10: ④ | C10: Wrinkle Reduction & Volume Restoration | D10: • Smooth deep wrinkles • Restore facial volume naturally • Maintain elegant and refined facial harmony | E10: • Premium Dermal Fillers • Collagen Stimulating Injections • Precision Botulinum Therapy | F10: • Juvederm / Restylane (Hyaluronic Acid Fillers) • Sculptra (PLLA) • Botulinum Toxin (Allergan / Nabota) | G10: • Cannula-based Injection • Ultrasound-Guided Precision Injection | I10: 1 vial Sculptra or Juvederm Filler 3cc (No restrictions on body part) Full Face Skin Botox Thermage FLX 900 Shot(Face+Neck) Blood Stem Cell Full Face | J10: Juvelook Skin 4cc RejuDM Premium Care(24K Gold therapy+Cryo therapy+LDM Rejuran Skin Booster(2 vials)+LED light therapy+Modeling pack) Ultrasound facial & neck care | K10: Wrinkle Reduction & Volume Restoration (주름개선&볼륨복원)
B11: ⑤ | C11: Skin Texture, Pores & Scar Repair | D11: • Improve acne scars and enlarged pores • Refine skin texture • Enhance overall skin smoothness | E11: • Fractional Laser Therapy • RF Microneedling • Subcision Therapy • Medical MTS | F11: • PRP • Exosomes • PDRN • Hyaluronic Acid | G11: • Fraxel Laser • Potenza RF Microneedling • CO₂ Laser Systems | I11: Blood Stem Cell Full Face Stem cell intravenous injection Rejuran HB 4cc | J11: Pico Dual Toning Rejuran Healer 4cc, Rejuran Eye 2cc, | K11: Skin Texture, Pores & Scar Repair (피부결,모공,흉터개선)
B12: ⑥ | C12: Regenerative & Recovery Therapy | D12: • Stem-Cell Derived Therapy • Intensive Skin Recovery Program • Post-Procedure Regeneration Care | E12: • Stem-Cell Derived Therapy • Intensive Skin Recovery Program • Post-Procedure Regeneration Care | F12: • Stem Cell Conditioned Media • Exosomes • Centella-based Regenerative Compounds | G12: • LED Healing Therapy • Oxygen Therapy Systems | I12: Blood Stem Cell Full Face Stem cell intravenous injection | K12: Regenerative & Recovery Therapy (재생&회복치료)
B13: ⑦ | C13: Wellness & Aesthetic Medicine | D13: • Holistic beauty and wellness • Anti-aging from within • Physical and mental rejuvenation | E13: • IV Vitamin & Antioxidant Therapy • Detox & Anti-Inflammatory Programs • Body Contouring & Tightening | F13: • Vitamin Complex • Antioxidants • L-Carnitine | G13: • InMode Body • EMS Sculpting Systems • RF Body Tightening Devices | I13: Premium SkinCeuticals Antioxidant Care Rejuran HB 4cc Premium SkinCeuticals(55ml) Ampoule giveaway Stem cell intravenous injection | J13: Rejuran Healer 4cc, Rejuran Eye 2cc, Mega Complex Vitamin IV Therapy Premium Nutrition IV Therapy | K13: Wellness & Aesthetic Medicine (웰니스&메디컬에스테틱)

Sheet (3) Selection_K-Beauty_NonMedi
A1: K-Beauty_Non-Medical Selection Sheet for Schedule
C3: Name (M or F) : | D3: =Cover!$D$69 -> : Michael Hong | G3: Passport No. : | H3: =Cover!$D$73 -> : DMC 0000000000
C4: Birth Date : | D4: =Cover!$D$71 -> : Feb. OO, 197X(Age: 5X) | G4: Arrival Flight Schedule (Local Time): | H4: =Cover!$D$58 -> : Departure - Mar. 10. 2026. 03:30 (Dubai) / Arrival - Mar. 10. 2026. 16:50 (Incheon)
C5: VIPs Contact. : | D5: =_xlfn.TEXTJOIN(" / ", TRUE, Cover!$D$76:$D$77) -> : +971-00-00-000 / : example@example.com | G5: Departure Flight Schedule (Local Time) : | H5: =Cover!$D$59 -> : Departure - Mar. 19. 2026. 23:40 (Incheon) / Arrival - Mar. 20. 2026. 05:05 (Dubai)
A8: Premium Package Category | G8: Check (ex.) | H8: Remarks | I8: Customer Requirement
A9: Package | D9: Package detail | E9: Duration (activity + transfer) | F9: Estimated Price (USD)
A10: K-Beauty (Non-Medical) | B10: Body Therapy | C10: Silver | D10: Purpose * Daily fatigue relief and muscle relaxation * Light recovery without strong stimulation or devices * Entry-level body therapy for first-time spa users Core Inclusions * Manual massage–based body therapy * Medium or light pressure * Partial or basic full-body coverage * No advanced devices or functional slimming technology | E10: 60-120min | F10: 412.53 - 575.96
C11: Gold | D11: Purpose * Deeper muscle recovery and circulation improvement * Body balance, lymphatic flow, and line refinement * Noticeable physical effect beyond relaxation Core Inclusions * Full-body treatment * Medium to deep pressure * Thermal elements, lymphatic techniques, or spa-specific technology * Optional detox or body line–focused care | E11: 90-150min | F11: 539.47 - 1,078.93
C12: Diamond | D12: Purpose * Targeted body transformation or premium sensory experience * Slimming, deep detox, or rare luxury ingredients * Destination-level body therapy Core Inclusions * Full-body ritual or intensive device-based care * Advanced technology (ultrasound, pressure & temperature control) * Long-duration or highly specialized programs | E12: 120-240min | F12: 674.33 - 2,380 | G12: ✔
A15: Premium Package Category | G15: Check (ex.) | H15: Remarks | I15: Customer Requirement
A16: Package | D16: Package detail | E16: Duration (activity + transfer) | F16: Estimated Price (USD)
A17: K-Beauty (Non-Medical) | B17: Signature treatments | C17: Silver | D17: Purpose Recovery-focused signature experience Body therapy + simple facial combination Core Inclusions Warm stone or calming body therapy Short ritual structure Stress & jet lag recovery focus | E17: 120min | F17: 840.93
C18: Gold | D18: Purpose * Emotional relaxation and shared experience * Sensory immersion rather than medical effect Core Inclusions * Multi-step ritual * Body scrub + body therapy * Couple or private suite experience | E18: 150min | F18: 840.93
C19: Diamond | D19: Purpose * Brand-defining spa journey * Cultural storytelling + full ritual experience Core Inclusions * Scrub + detox + body therapy + facial * Long duration * Most comprehensive Signature treatment | E19: 150min | F19: 840.93 | G19: ✔
B20: Facial collection | C20: Silver | D20: Purpose * Skin recovery and rejuvenation * Practical, no-downtime facial care Core Inclusions * Device-based facial technology * Cleansing, hydration, circulation improvement | E20: 90min | F20: 650.53
C21: Gold | D21: Purpose * Personalized skin improvement * Texture, contour, and radiance enhancement Core Inclusions * Skin analysis * Bespoke treatment protocol * Reshaping and hydration care | E21: 90min | F21: 714
C22: Diamond | D22: Purpose * Instant visible results with premium cosmeceutical technology * Flagship facial experience Core Inclusions * Exclusive treatment method (Second Skin) * High-concentration active ingredients * No-downtime, high-impact result | E22: 75min | F22: 888.53 | G22: ✔
A25: Premium Package Category | G25: Check (ex.) | H25: Remarks | I25: Customer Requirement
A26: Package | D26: Package detail | E26: Duration (activity + transfer) | F26: Estimated Price (USD)
A27: K-Beauty (Non-Medical) | B27: Henna | C27: Henna at Seoul | D27: Traditional Indian henna art created using natural henna dye. The design remains on the skin temporarily and fades naturally over time. #Henna #Art #Temporary #Seoul
C28: Henna at Busan | D28: Traditional Indian henna art created using natural henna dye. The design remains on the skin temporarily and fades naturally over time. #Henna #Art #Temporary #Busan | H28: For locations outside Seoul, Incheon, and Gyeonggi-do, travel time may be longer, so we recommend combining this experience with other activities in Busan or Ulsan.
B29: Scalp treatment | D29: A premium scalp care program at Eco Jardin, providing deep cleansing and revitalization of the scalp through delicate care by experienced professionals. The program includes consultation, diagnosis, scalp treatment, and styling. #Premium Scalp Care #Consultation & Diagnosis #Treatment #Styling #Seoul | F29: 396.67 | G29: ✔

Sheet (4-1) Selection_K-Wellness_GEN
A1: K-Wellness_General Selection Sheet for Schedule
D2: Name (M or F) : | E2: =Cover!$D$69 -> : Michael Hong | H2: Passport No. : | I2: =Cover!$D$73 -> : DMC 0000000000
D3: Birth Date : | E3: =Cover!$D$71 -> : Feb. OO, 197X(Age: 5X) | H3: Arrival Flight Schedule (Local Time): | I3: =Cover!$D$58 -> : Departure - Mar. 10. 2026. 03:30 (Dubai) / Arrival - Mar. 10. 2026. 16:50 (Incheon)
D4: VIPs Contact. : | E4: =_xlfn.TEXTJOIN(" / ", TRUE, Cover!$D$76:$D$77) -> : +971-00-00-000 / : example@example.com | H4: Departure Flight Schedule (Local Time) : | I4: =Cover!$D$59 -> : Departure - Mar. 19. 2026. 23:40 (Incheon) / Arrival - Mar. 20. 2026. 05:05 (Dubai)
A7: Premium Package Category | H7: Check (ex.) | I7: Remarks | J7: Customer Requirement
A8: Package | E8: Package detail | F8: Duration (activity + transfer) | G8: Estimated Price (USD)
A9: K-Wellness | B9: Free Time | E9: Personal rest options available (4 hours or full day)
B10: Shopping | C10: Cosmetics & Beauty Products | E10: Korea’s first health and beauty store and the country’s largest H&B retail chain, offering a curated selection of cosmetics, health supplements, beauty products, and popular domestic and international brands in one place. #Cosmetics #Health #Beauty #Olive Young | H10: ✔ | I10: Final purchases are entirely at the customer’s own discretion.
C11: K-GLASSES | E11: A premium optical store founded in 1942, trusted by Korean presidents and VIPs, and Korea’s largest Lindberg dealer, offering advanced eye examinations and high-precision digital lenses with state-of-the-art technology. #Premium Optical Store #Lindberg #Advanced Technology #State-of-the-Art Equipment #KUMKANG OPTICAL | H11: ✔ | I11: Final purchases are entirely at the customer’s own discretion.
C12: Stationery | E12: Korea’s first design-focused stationery brand that redefined stationery as a lifestyle category, offering stylish stationery and everyday lifestyle goods with a strong design identity. #Fancy Goods #Stationery #Lifestyle Products #ARTBOX | I12: Final purchases are entirely at the customer’s own discretion.
B13: K-Pop | C13: Tour | D13: K-POP Demon Hunters | E13: An immersive mission-based adventure across Seoul’s iconic landmarks using cutting-edge XR/AR technology, where participants step into the world of K-POP Demon Hunters. #Private van tour #mission tour #XR/AR #Seoul | F13: 1day | G13: 1,364.53 / 1Group | H13: ✔
D14: K-POP Concert | E14: Attend a live taping of SBS Inkigayo and enjoy a walking tour around the SBS Public Hall area, with itineraries that change monthly. #SBS Inkigayo #K-POP Walking Tour #Seoul Jongro | F14: 1day | G14: 571.2 | I14: Held Every Sunday Passport Required Due to limited ticket availability, participation may not be possible even if this option is selected.
D15: K-Drama Tour (Descendants of the Sun, Guardian: The Lonely and Great God, My Love From the Star) | E15: Visit iconic filming locations from three legendary K-dramas and enjoy everyday Korean life through local cafés and chicken restaurants. #Private Tour #K-Drama Tour #Descendants of the Sun #Guardian: The Lonely and Great God #My Love From the Star #Seoul, Incheon | F15: 1day | G15: 245.14 - 554.54
D16: K-Drama Tour (Welcome to Samdal-ri, Extraordinary Attorney Woo, When Life Gives You Tangerines) | E16: Explore K-drama filming locations across Jeju Island and experience the scenery and stories that brought these dramas to life. #Private Tour #K-Drama Tour #Welcome to Samdal-ri #Extraordinary Attorney Woo #When Life Gives You Tangerines #Jeju island | F16: 2day | G16: 603 | I16: For locations outside Seoul, Incheon, and Gyeonggi-do, travel time may be longer, so we recommend combining this experience with other activities in Jeju.
D17: K-Drama Tour (Squid Game) | E17: Visit real Squid Game filming locations and participate in on-screen missions including dalgona carving, retro lunchbox dining, and themed activities across Incheon. #Mission tour #Squid Game #Incheon | F17: 1day | G17: 366.52
D18: Award Ceremony | E18: Experience the atmosphere of a Korean award ceremony and witness K-POP stars and artists celebrate their achievements live.
A21: Premium Package Category | H21: Check (ex.) | I21: Remarks | J21: Customer Requirement
A22: Package | E22: Package detail | F22: Duration (activity + transfer) | G22: Estimated Price (USD)
A23: K-Wellness | B23: K-Pop | C23: Experience | D23: K-POP Experience | E23: A VIP-only private K-POP program limited to four participants per day, offering dance and vocal training, idol makeup, and concept photo shoots inspired by real debut preparation. #Dance lesson #Vocal lesson #Idol Makeup #Idol Concept Photo Shoot #Seoul | F23: 1day | G23: 855.21
C24: Dance | D24: K-POP Dance Lesson | E24: Fully customized private dance lessons tailored to individual goals, available at your preferred time and location, covering any genre or choreography. #Private lesson #Dance lesson #Choreography Master #Seoul | F24: 180min | G24: 158.67 | I24: Photos and videos may be used for promotional purposes. Led by a professional trainer, with difficulty tailored to participants’ levels.
C25: Beauty | D25: K-POP Fashion | E25: A one-on-one styling experience with a Korean stylist who curates 6–7 outfit recommendations per hour from popular Korean fashion brands, with full freedom to choose final purchases. #Private group #Korean Stylist #Shopping tour #Seoul Gangnam | F25: 180min | G25: 317.33 - 337.96 | H25: ✔
D26: K-POP Styling | E26: Professional K-Beauty styling experience at studios where Korean stars prepare for performances, including makeup, hair styling, and photoshoots. #K-POP Styling #Makeup #Hair Styling #Photoshoot #Seoul | F26: 240min | G26: 1071 | H26: ✔ | I26: Pre-interview required(Google Form)
D27: Style Consulting | E27: Personalized offline consulting to find the most suitable hair, makeup, and fashion style based on individual concerns and desired image. #Private Offline Service #Hair Consulting #Makeup Consulting #Fashion Consulting #Seoul | F27: 300min | G27: 714 | H27: ✔
D28: Personal Color Diagnosis | E28: In-depth personal color and image consulting that defines optimal colors, styling direction, and overall branding for each individual. #Private Consulting #Personal Color #Body Structure Consulting #Image Perfume & Aroma #Seoul | F28: 210min | G28: 952 - 13,962.67 | H28: ✔
B29: Tour | C29: KTX Experience | E29: Experience Korea’s high-speed rail system that connects most regions within two hours, representing the country’s fastest and most efficient mode of travel. | I29: If selected, inter-regional travel will be by train rather than by private vehicle.
C30: Seoul Tour | D30: Seoul City Tour | E30: A full-day premium tour capturing Seoul’s history, culture, nature, and modern cityscape, from royal palaces and traditional streets to urban landmarks and a scenic Han River night view. #VIP Private Tour #Royal Guard change ceremony #Gyeongbokgung Palace #National folk museum of korea #N seoul tower #Changdeokgung palace #Insadong #Han River Cruise #Seoul | F30: 1day | G30: 349.07 | I30: Mondays: Changdeokgung Palace closed -> replace with Bukchon Hanok Village Tuesdays: Gyeongbokgung closed -> replaced with Deoksugung Below -10°C or in case of rain/snow: Royal Guard Changing Ceremony may be canceled In case of strong winds, heavy rain or snow: N Seoul Tower schedule may be canceled
D31: Seoul City Night Tour | E31: Discover Seoul after dark through a scenic drive and relaxed evening walks showcasing illuminated landmarks and vibrant city nightlife. #Gwanghwamun #Cheonggyecheon River #Dongdaemun Design Plaza #N Seoul Tower #Han River #Banpo Grand Bridge Fountain #Itaewon #Seoul | F31: 300min | G31: 142.8 | I31: Passport Required If traffic is restricted due to rallies or demonstrations near Gwanghwamun Square, an alternative itinerary will be arranged.
D32: ISLAMIC Seoul City Tour | E32: A Muslim-only private Seoul tour with halal meals and prayer time arrangements, covering key historical, cultural, and modern landmarks. #Muslim Private Tour #Royal Guard change ceremony #Gyeongbokgung Palace #N seoul tower #Itaewon Mosque #Bukchon Village #Dongdaemun Design Plaza #Gwangjang Market #Myeongdong #Seoul | F32: 1day | G32: 134.87
A35: Premium Package Category | H35: Check (ex.) | I35: Remarks | J35: Customer Requirement
A36: Package | E36: Package detail | F36: Duration (activity + transfer) | G36: Estimated Price (USD)
A37: K-Wellness | B37: Tour | C37: Local Tour | D37: DMZ + NLL Tour | E37: Explore the realities of the Korean Peninsula’s division through visits to the DMZ and NLL, including the Third Tunnel, observatory views of North Korea, and a meeting with a North Korean defector. #DMZ Tour #NLL Tour #North Korea #DMZ,NLL | F37: 1day | G37: 253.87 | H37: ✔ | I37: Mondays & Public Holidays: Closed / Passport required Military situation or severe weather: Alternative route operated (no refunds) Military area rules must be strictly followed / Only authorized buses and military shuttles permitted No independent movement allowed / Photography and video recording prohibited in restricted areas (Military Protection Act)
D38: ISLAMIC NAMI ISLAND TOUR | E38: A Muslim-only private tour to Nami Island with halal meals and prayer time arrangements in a peaceful natural setting. #Muslim Private Tour #Nami island #Gangwon-do | F38: 1day | G38: 190.4 | H38: ✔
D39: Jeju Island Private Tour | E39: A fully customizable luxury Jeju tour with a stay at Grand Hyatt Jeju, combining sightseeing, relaxation, fine dining, yacht cruising, massage, and immersive art experiences. #Private Tour #Yacht #Massage #Jeju Island | F39: 3day | G39: 1,088.45 - 1,848.47 | I39: Round-trip airfare, private vehicle, and driver included. For locations outside Seoul, Incheon, and Gyeonggi-do, travel time may be longer.
D40: Jeju island Golf Tour | E40: A premium golf getaway featuring a private Blackstone Villa Suite stay and multiple rounds at Jeju’s top-tier golf courses, Blackstone CC and Elysian CC. #Golf Tour #Blackstone CC #Elysian CC #Jeju Island | F40: 3day | G40: 1,407.37 - 1,975.40 | I40: Green fees for three 18-hole rounds – 1 round at Elysian, 2 rounds at Blackstone For locations outside Seoul, Incheon, and Gyeonggi-do, travel time may be longer.
D41: Gyeongbuk Tourpass | E41: A convenient all-in-one free-pass granting access to major paid attractions across Gyeongsangbuk-do for 24, 48, or 72 hours with a single barcode. #FreePass #TourismPass #Gyeongju #Pohang #Ulleungdo #More #Gyeongsangbuk-do | F41: 3day | G41: 26.97 | I41: A free-pass style ticket offering complimentary access to selected attractions and partner cafés. No guide, no fixed route For locations outside Seoul, Incheon, and Gyeonggi-do, travel time may be longer
C42: Cruise Tour | D42: Busan Cruise Tour | E42: An unforgettable overnight luxury cruise departing from Busan Port, featuring premium dining, live performances, onboard fireworks, and exclusive duty-free shopping along the Korea Strait. #One-night Cruise #Onboard buffet #Onboard fireworks #Busan | F42: 2day | G42: 1,047.20 - 1,031.33 | I42: Operates every Saturday 1st, 2nd, 4th, and 5th Saturdays: Taejongdae, Molundae, Dongbaekseom, Gwangalli 3rd Saturday: Tsushima Hitakatsu Port – Gwangalli Passport required For locations outside Seoul, Incheon, and Gyeonggi-do, travel time may be longer, so we recommend combining this experience with other activities in Busan or Ulsan.
C43: Rail Cruise Tour | D43: Grand Tour of Korea by Train | E43: A unique overnight sightseeing train journey that combines rail travel and cruise-style comfort, traveling across Korea’s major regions before returning to Seoul. #GrandTour #OvernightTrain #Suncheon #Yeosu #Busan #Gyeongju #Donghae #whole country #Departing from Seoul #Returning to Seoul | F43: 3day | G43: 5,616.80 - 5,886.53 | I43: Train fare, connecting bus fees, onboard accommodation, meals, snacks, beverages, entrance fees, activity fees, and onboard events included.
A46: Premium Package Category | H46: Check (ex.) | I46: Remarks | J46: Customer Requirement
A47: Package | E47: Package detail | F47: Duration (activity + transfer) | G47: Estimated Price (USD)
A48: K-Wellness | B48: Leisure | C48: Snow Park | D48: Ski | E48: Enjoy winter skiing at major resorts in Gangwon-do and Gyeonggi-do, offering slopes for all skill levels with well-equipped facilities. #Winter Sports #Ski rental #Suit rental #Lift #MonaYongPyong #High1 #VivaldiPark #Konjiam #Gangwon-do #Gyeonggi-do | F48: 1-2day | G48: 176.12 - 252.28 | I48: Limited to season If you have a preferred ski resort, please specify it here (e.g., MONA Yongpyong Resort, High1 Resort, Vivaldi Park Resort, KONJIAM Resort). If left blank, we will recommend the best available option for you. For locations outside Seoul, Incheon, and Gyeonggi-do, travel time may be longer.
D49: Board | E49: Experience snowboarding at top winter resorts with diverse slopes and convenient facilities suitable for beginners to advanced riders. #Winter Sports #Board rental #Suit rental #Lift #MonaYongPyong #High1 #VivaldiPark #Konjiam #Gangwon-do #Gyeonggi-do | F49: 1-2day | G49: 238 - 634.67
D50: Lesson | E50: Professional ski and snowboard lessons led by experienced instructors, designed for safe and effective skill development. #Winter Sports #Ski Lesson #Board Lesson #MonaYongPyong #High1 #VivaldiPark #Konjiam #Gangwon-do #Gyeonggi-do | F50: 1-2day | G50: 79.33 - 142.80
C51: Water Park | E51: A large-scale water theme park featuring slides, wave pools, adventure zones, and spa areas for all ages. #Water Park #Water slide #Wave pool #Adventure pool #Spa area #Caribbean Bay #Ocean World #Cimer #Gangwon-do #Gyeonggi-do #Incheon | F51: 1-2day | G51: 93.61 - 119 | I51: Limited to season If you have a preferred ski resort, please specify it here(e.g., Caribbean Bay, Ocean World, Cimer). If left blank, we will recommend the best available option for you. For locations outside Seoul, Incheon, and Gyeonggi-do, travel time may be longer
C52: Barge | E52: River-based water leisure activities including water skiing, towable rides, jet boats, and water slides for dynamic outdoor fun. #Barge #Water Leisure #Water Ski #Towable rides #Jet Boat #Water Slide #Gyeonggi-do Gapyeong | F52: 1-2day | G52: 117.41 - 122.17 | I52: Limited to season
C53: Sprorts | D53: Baseball | E53: Watch professional baseball games from a private skybox with food and beverages included, offering a relaxed and exclusive viewing experience. #BaseballGame #Skybox #KiwoomHeroes #SSGLanders #GocheokSkyDome #SSGLandersField #Seoul #Incheon | F53: 240min | G53: 112.65 - 122.17 | I53: Match viewing may not be available depending on the game schedule. If you have a preferred team or venue, please specify it here (e.g., Kiwoom Heroes at Gocheok Sky Dome, SSG Landers at Incheon SSG Landers Field). If left blank, we will recommend the best available option for you.
D54: Soccer | E54: Enjoy top-tier soccer matches from a private skybox with in-seat dining, combining comfort and premium stadium views. #SoccerGame #Skybox #FC Seoul #Seoul World Cup Stadium #Seoul | F54: 180min | G54: 4,712.40(1 Group) | I54: Match viewing may not be available depending on the game schedule. If you have a preferred team or venue, please specify it here(e.g., FC Seoul at (Seoul World Cup Stadium). If left blank, we will recommend the best available option for you.
C55: Theme Park | E55: A full-scale amusement park experience with thrilling rides, family attractions, games, and live entertainment. #Theme Park #Amusement Park #Everland Dream Tour #Lotte World Magic Pass #Seoul Land #Gyeonggi-do #Seoul | F55: 1day | G55: 82.51 - 555.33 | H55: ✔ | I55: If you have a preferred theme park, please specify it here(e.g., Everland, Lotte World, Seoul Land). If left blank, we will recommend the best available option for you. Everland: Dream Tour may be available, which includes priority entry, guided park tour, and priority access to major attractions Lotte World: Magic Pass Ticket may be available, which includes priority access to attractions

Sheet (4-2) Selection_K-Wellness_SCH
A1: K-Wellness_School Trip Selection Sheet for Schedule
D2: Name (M or F) : | E2: =Cover!$D$69 -> : Michael Hong | H2: Passport No. : | I2: =Cover!$D$73 -> : DMC 0000000000
D3: Birth Date : | E3: =Cover!$D$71 -> : Feb. OO, 197X(Age: 5X) | H3: Arrival Flight Schedule (Local Time): | I3: =Cover!$D$58 -> : Departure - Mar. 10. 2026. 03:30 (Dubai) / Arrival - Mar. 10. 2026. 16:50 (Incheon)
D4: VIPs Contact. : | E4: =_xlfn.TEXTJOIN(" / ", TRUE, Cover!$D$76:$D$77) -> : +971-00-00-000 / : example@example.com | H4: Departure Flight Schedule (Local Time) : | I4: =Cover!$D$59 -> : Departure - Mar. 19. 2026. 23:40 (Incheon) / Arrival - Mar. 20. 2026. 05:05 (Dubai)
A7: Premium Package Category | H7: Check (ex.) | I7: Remarks | J7: Customer Requirement
A8: Package | E8: Package detail | F8: Duration (activity + transfer) | G8: Estimated Price (USD)
A9: K-Wellness | B9: Free Time | E9: Personal rest options available (4 hours or full day)
B10: Shopping | C10: Cosmetics & Beauty Products | E10: Korea’s first health and beauty store and the country’s largest H&B retail chain, offering a curated selection of cosmetics, health supplements, beauty products, and popular domestic and international brands in one place. #Cosmetics #Health #Beauty #Olive Young | H10: ✔ | I10: Final purchases are entirely at the customer’s own discretion.
C11: K-GLASSES | E11: A premium optical store founded in 1942, trusted by Korean presidents and VIPs, and Korea’s largest Lindberg dealer, offering advanced eye examinations and high-precision digital lenses with state-of-the-art technology. #Premium Optical Store #Lindberg #Advanced Technology #State-of-the-Art Equipment #KUMKANG OPTICAL | H11: ✔ | I11: Final purchases are entirely at the customer’s own discretion.
C12: Stationery | E12: Korea’s first design-focused stationery brand that redefined stationery as a lifestyle category, offering stylish stationery and everyday lifestyle goods with a strong design identity. #Fancy Goods #Stationery #Lifestyle Products #ARTBOX | I12: Final purchases are entirely at the customer’s own discretion.
B13: K-Pop | C13: Tour | D13: K-POP Demon Hunters | E13: An immersive mission-based adventure across Seoul’s iconic landmarks using cutting-edge XR/AR technology, where participants step into the world of K-POP Demon Hunters. #Private van tour #mission tour #XR/AR #Seoul | F13: 1day | G13: 1,364.53 / 1Group | H13: ✔
D14: K-POP Concert | E14: Attend a live taping of SBS Inkigayo and enjoy a walking tour around the SBS Public Hall area, with itineraries that change monthly. #SBS Inkigayo #K-POP Walking Tour #Seoul Jongro | F14: 1day | G14: 571.2 | I14: Held Every Sunday Passport Required Due to limited ticket availability, participation may not be possible even if this option is selected.
D15: K-Drama Tour (Descendants of the Sun, Guardian: The Lonely and Great God, My Love From the Star) | E15: Visit iconic filming locations from three legendary K-dramas and enjoy everyday Korean life through local cafés and chicken restaurants. #Private Tour #K-Drama Tour #Descendants of the Sun #Guardian: The Lonely and Great God #My Love From the Star #Seoul, Incheon | F15: 1day | G15: 245.14 - 554.54
D16: K-Drama Tour (Welcome to Samdal-ri, Extraordinary Attorney Woo, When Life Gives You Tangerines) | E16: Explore K-drama filming locations across Jeju Island and experience the scenery and stories that brought these dramas to life. #Private Tour #K-Drama Tour #Welcome to Samdal-ri #Extraordinary Attorney Woo #When Life Gives You Tangerines #Jeju island | F16: 2day | G16: 603 | I16: For locations outside Seoul, Incheon, and Gyeonggi-do, travel time may be longer, so we recommend combining this experience with other activities in Jeju.
D17: K-Drama Tour (Squid Game) | E17: Visit real Squid Game filming locations and participate in on-screen missions including dalgona carving, retro lunchbox dining, and themed activities across Incheon. #Mission tour #Squid Game #Incheon | F17: 1day | G17: 366.52
D18: Award Ceremony | E18: Experience the atmosphere of a Korean award ceremony and witness K-POP stars and artists celebrate their achievements live.
A21: Premium Package Category | H21: Check (ex.) | I21: Remarks | J21: Customer Requirement
A22: Package | E22: Package detail | F22: Duration (activity + transfer) | G22: Estimated Price (USD)
A23: K-Wellness | B23: K-Pop | C23: Experience | D23: K-POP Experience | E23: A VIP-only private K-POP program limited to four participants per day, offering dance and vocal training, idol makeup, and concept photo shoots inspired by real debut preparation. #Dance lesson #Vocal lesson #Idol Makeup #Idol Concept Photo Shoot #Seoul | F23: 1day | G23: 855.21
C24: Dance | D24: K-POP Dance Lesson | E24: Fully customized private dance lessons tailored to individual goals, available at your preferred time and location, covering any genre or choreography. #Private lesson #Dance lesson #Choreography Master #Seoul | F24: 180min | G24: 158.67 | I24: Photos and videos may be used for promotional purposes. Led by a professional trainer, with difficulty tailored to participants’ levels.
C25: Beauty | D25: K-POP Fashion | E25: A one-on-one styling experience with a Korean stylist who curates 6–7 outfit recommendations per hour from popular Korean fashion brands, with full freedom to choose final purchases. #Private group #Korean Stylist #Shopping tour #Seoul Gangnam | F25: 180min | G25: 317.33 - 337.96 | H25: ✔
D26: K-POP Styling | E26: Professional K-Beauty styling experience at studios where Korean stars prepare for performances, including makeup, hair styling, and photoshoots. #K-POP Styling #Makeup #Hair Styling #Photoshoot #Seoul | F26: 240min | G26: 1071 | H26: ✔ | I26: Pre-interview required(Google Form)
D27: Style Consulting | E27: Personalized offline consulting to find the most suitable hair, makeup, and fashion style based on individual concerns and desired image. #Private Offline Service #Hair Consulting #Makeup Consulting #Fashion Consulting #Seoul | F27: 300min | G27: 714 | H27: ✔
D28: Personal Color Diagnosis | E28: In-depth personal color and image consulting that defines optimal colors, styling direction, and overall branding for each individual. #Private Consulting #Personal Color #Body Structure Consulting #Image Perfume & Aroma #Seoul | F28: 210min | G28: 952 - 13,962.67 | H28: ✔
B29: Tour | C29: KTX Experience | E29: Experience Korea’s high-speed rail system that connects most regions within two hours, representing the country’s fastest and most efficient mode of travel. | I29: If selected, inter-regional travel will be by train rather than by private vehicle.
C30: Seoul Tour | D30: Seoul City Tour | E30: A full-day premium tour capturing Seoul’s history, culture, nature, and modern cityscape, from royal palaces and traditional streets to urban landmarks and a scenic Han River night view. #VIP Private Tour #Royal Guard change ceremony #Gyeongbokgung Palace #National folk museum of korea #N seoul tower #Changdeokgung palace #Insadong #Han River Cruise #Seoul | F30: 1day | G30: 349.07 | I30: Mondays: Changdeokgung Palace closed -> replace with Bukchon Hanok Village Tuesdays: Gyeongbokgung closed -> replaced with Deoksugung Below -10°C or in case of rain/snow: Royal Guard Changing Ceremony may be canceled In case of strong winds, heavy rain or snow: N Seoul Tower schedule may be canceled
D31: Seoul City Night Tour | E31: Discover Seoul after dark through a scenic drive and relaxed evening walks showcasing illuminated landmarks and vibrant city nightlife. #Gwanghwamun #Cheonggyecheon River #Dongdaemun Design Plaza #N Seoul Tower #Han River #Banpo Grand Bridge Fountain #Itaewon #Seoul | F31: 300min | G31: 142.8 | I31: Passport Required If traffic is restricted due to rallies or demonstrations near Gwanghwamun Square, an alternative itinerary will be arranged.
D32: ISLAMIC Seoul City Tour | E32: A Muslim-only private Seoul tour with halal meals and prayer time arrangements, covering key historical, cultural, and modern landmarks. #Muslim Private Tour #Royal Guard change ceremony #Gyeongbokgung Palace #N seoul tower #Itaewon Mosque #Bukchon Village #Dongdaemun Design Plaza #Gwangjang Market #Myeongdong #Seoul | F32: 1day | G32: 134.87
A35: Premium Package Category | H35: Check (ex.) | I35: Remarks | J35: Customer Requirement
A36: Package | E36: Package detail | F36: Duration (activity + transfer) | G36: Estimated Price (USD)
A37: K-Wellness | B37: Tour | C37: Local Tour | D37: DMZ + NLL Tour | E37: Explore the realities of the Korean Peninsula’s division through visits to the DMZ and NLL, including the Third Tunnel, observatory views of North Korea, and a meeting with a North Korean defector. #DMZ Tour #NLL Tour #North Korea #DMZ,NLL | F37: 1day | G37: 253.87 | H37: ✔ | I37: Mondays & Public Holidays: Closed / Passport required Military situation or severe weather: Alternative route operated (no refunds) Military area rules must be strictly followed / Only authorized buses and military shuttles permitted No independent movement allowed / Photography and video recording prohibited in restricted areas (Military Protection Act)
D38: ISLAMIC NAMI ISLAND TOUR | E38: A Muslim-only private tour to Nami Island with halal meals and prayer time arrangements in a peaceful natural setting. #Muslim Private Tour #Nami island #Gangwon-do | F38: 1day | G38: 190.4 | H38: ✔
D39: Jeju Island Private Tour | E39: A fully customizable luxury Jeju tour with a stay at Grand Hyatt Jeju, combining sightseeing, relaxation, fine dining, yacht cruising, massage, and immersive art experiences. #Private Tour #Yacht #Massage #Jeju Island | F39: 3day | G39: 1,088.45 - 1,848.47 | I39: Round-trip airfare, private vehicle, and driver included. For locations outside Seoul, Incheon, and Gyeonggi-do, travel time may be longer.
D40: Jeju island Golf Tour | E40: A premium golf getaway featuring a private Blackstone Villa Suite stay and multiple rounds at Jeju’s top-tier golf courses, Blackstone CC and Elysian CC. #Golf Tour #Blackstone CC #Elysian CC #Jeju Island | F40: 3day | G40: 1,407.37 - 1,975.40 | I40: Green fees for three 18-hole rounds – 1 round at Elysian, 2 rounds at Blackstone For locations outside Seoul, Incheon, and Gyeonggi-do, travel time may be longer.
D41: Gyeongbuk Tourpass | E41: A convenient all-in-one free-pass granting access to major paid attractions across Gyeongsangbuk-do for 24, 48, or 72 hours with a single barcode. #FreePass #TourismPass #Gyeongju #Pohang #Ulleungdo #More #Gyeongsangbuk-do | F41: 3day | G41: 26.97 | I41: A free-pass style ticket offering complimentary access to selected attractions and partner cafés. No guide, no fixed route For locations outside Seoul, Incheon, and Gyeonggi-do, travel time may be longer
C42: Cruise Tour | D42: Busan Cruise Tour | E42: An unforgettable overnight luxury cruise departing from Busan Port, featuring premium dining, live performances, onboard fireworks, and exclusive duty-free shopping along the Korea Strait. #One-night Cruise #Onboard buffet #Onboard fireworks #Busan | F42: 2day | G42: 1,047.20 - 1,031.33 | I42: Operates every Saturday 1st, 2nd, 4th, and 5th Saturdays: Taejongdae, Molundae, Dongbaekseom, Gwangalli 3rd Saturday: Tsushima Hitakatsu Port – Gwangalli Passport required For locations outside Seoul, Incheon, and Gyeonggi-do, travel time may be longer, so we recommend combining this experience with other activities in Busan or Ulsan.
C43: Rail Cruise Tour | D43: Grand Tour of Korea by Train | E43: A unique overnight sightseeing train journey that combines rail travel and cruise-style comfort, traveling across Korea’s major regions before returning to Seoul. #GrandTour #OvernightTrain #Suncheon #Yeosu #Busan #Gyeongju #Donghae #whole country #Departing from Seoul #Returning to Seoul | F43: 3day | G43: 5,616.80 - 5,886.53 | I43: Train fare, connecting bus fees, onboard accommodation, meals, snacks, beverages, entrance fees, activity fees, and onboard events included.
A46: Premium Package Category | H46: Check (ex.) | I46: Remarks | J46: Customer Requirement
A47: Package | E47: Package detail | F47: Duration (activity + transfer) | G47: Estimated Price (USD)
A48: K-Wellness | B48: Leisure | C48: Snow Park | D48: Ski | E48: Enjoy winter skiing at major resorts in Gangwon-do and Gyeonggi-do, offering slopes for all skill levels with well-equipped facilities. #Winter Sports #Ski rental #Suit rental #Lift #MonaYongPyong #High1 #VivaldiPark #Konjiam #Gangwon-do #Gyeonggi-do | F48: 1-2day | G48: 176.12 - 252.28 | I48: Limited to season If you have a preferred ski resort, please specify it here (e.g., MONA Yongpyong Resort, High1 Resort, Vivaldi Park Resort, KONJIAM Resort). If left blank, we will recommend the best available option for you. For locations outside Seoul, Incheon, and Gyeonggi-do, travel time may be longer.
D49: Board | E49: Experience snowboarding at top winter resorts with diverse slopes and convenient facilities suitable for beginners to advanced riders. #Winter Sports #Board rental #Suit rental #Lift #MonaYongPyong #High1 #VivaldiPark #Konjiam #Gangwon-do #Gyeonggi-do | F49: 1-2day | G49: 238 - 634.67
D50: Lesson | E50: Professional ski and snowboard lessons led by experienced instructors, designed for safe and effective skill development. #Winter Sports #Ski Lesson #Board Lesson #MonaYongPyong #High1 #VivaldiPark #Konjiam #Gangwon-do #Gyeonggi-do | F50: 1-2day | G50: 79.33 - 142.80
C51: Water Park | E51: A large-scale water theme park featuring slides, wave pools, adventure zones, and spa areas for all ages. #Water Park #Water slide #Wave pool #Adventure pool #Spa area #Caribbean Bay #Ocean World #Cimer #Gangwon-do #Gyeonggi-do #Incheon | F51: 1-2day | G51: 93.61 - 119 | I51: Limited to season If you have a preferred ski resort, please specify it here(e.g., Caribbean Bay, Ocean World, Cimer). If left blank, we will recommend the best available option for you. For locations outside Seoul, Incheon, and Gyeonggi-do, travel time may be longer
C52: Barge | E52: River-based water leisure activities including water skiing, towable rides, jet boats, and water slides for dynamic outdoor fun. #Barge #Water Leisure #Water Ski #Towable rides #Jet Boat #Water Slide #Gyeonggi-do Gapyeong | F52: 1-2day | G52: 117.41 - 122.17 | I52: Limited to season
C53: Sprorts | D53: Baseball | E53: Watch professional baseball games from a private skybox with food and beverages included, offering a relaxed and exclusive viewing experience. #BaseballGame #Skybox #KiwoomHeroes #SSGLanders #GocheokSkyDome #SSGLandersField #Seoul #Incheon | F53: 240min | G53: 112.65 - 122.17 | I53: Match viewing may not be available depending on the game schedule. If you have a preferred team or venue, please specify it here (e.g., Kiwoom Heroes at Gocheok Sky Dome, SSG Landers at Incheon SSG Landers Field). If left blank, we will recommend the best available option for you.
D54: Soccer | E54: Enjoy top-tier soccer matches from a private skybox with in-seat dining, combining comfort and premium stadium views. #SoccerGame #Skybox #FC Seoul #Seoul World Cup Stadium #Seoul | F54: 180min | G54: 4,712.40(1 Group) | I54: Match viewing may not be available depending on the game schedule. If you have a preferred team or venue, please specify it here(e.g., FC Seoul at (Seoul World Cup Stadium). If left blank, we will recommend the best available option for you.
C55: Theme Park | E55: A full-scale amusement park experience with thrilling rides, family attractions, games, and live entertainment. #Theme Park #Amusement Park #Everland Dream Tour #Lotte World Magic Pass #Seoul Land #Gyeonggi-do #Seoul | F55: 1day | G55: 82.51 - 555.33 | H55: ✔ | I55: If you have a preferred theme park, please specify it here(e.g., Everland, Lotte World, Seoul Land). If left blank, we will recommend the best available option for you. Everland: Dream Tour may be available, which includes priority entry, guided park tour, and priority access to major attractions Lotte World: Magic Pass Ticket may be available, which includes priority access to attractions
A58: Premium Package Category | H58: Check (ex.) | I58: Remarks | J58: Customer Requirement
A59: Package | E59: Package detail | F59: Duration (activity + transfer) | G59: Estimated Price (USD)
A60: K-Wellness | B60: Education | C60: Package tour | D60: Experience Future-Oriented Korean Education Spanning School Exchange, AI, Media, and K-POP | E60: Day 1: Incheon Airport → G Valley Industrial Experience Center → Hiker Ground Day 2: School Exchange (AM) → School Exchange (PM) → Namsan Cable Car → N Seoul Tower Day 3: Seoul Robotics & AI Science Center → MMCA Seoul → KBS Station → National Assembly Museum → Han River Cruise Day 4: National Museum of Korea → Myeongdong → Real K-POP Dance Experience → Hongdae Street Day 5: Gyeongbokgung Palace → National Palace Museum → Incheon Airport #School field trip #School Exchange #AI #Media #K-POP #Seoul | F60: 5day | G60: 1746.13 | I60: There is no fixed schedule; the program is customized and arranged according to your preferred dates.
D61: Korean educational tour encompassing university campuses, future technologies, media, and theme parks | E61: Day 1: Incheon Airport → Seodaemun Prison History Museum → War Memorial of Korea Day 2: University Campus Tour → Hongdae Street → MBC World Theme Park → Han River Cruise Day 3: LG Discovery Lab → Seoul Future Lab → National Museum of Korea → Insadong Day 4: Wolmi Sea Train → Wolmi Theme Park → Songdo Central Park → National Museum of World Letters → G-Tower Observatory Day 5: Gimbap Making Experience → National Aviation Museum → Incheon Airport #School field trip #University campus #Future Technology #Media #Theme Park #Seoul #Incheon | F61: 5day | G61: 1616.02
D62: Experience K-POP, Traditional Culture, Theme Parks, and Future Industries All at Once | E62: Day 1: Incheon Airport → Gwangjang Market / Dongdaemun Market Day 2: University Campus Tour → K-POP Dance Experience → Apgujeong K-Star Road Day 3: Korean Folk Village → Everland Day 4: Gyeongbokgung Palace → Hiker Ground → Namsan Cable Car & Seoul Tower → Myeongdong → Painters Show / Musical Chef Day 5: Hyundai Motorstudio Goyang → Heiri Art Village → Incheon Airport #School field trip #K-POP #K-Traditional Culture #Theme Park #Future Industry #Seoul #Gyeonggi-do | F62: 5day | G62: 1869.09
C63: It experience | D63: AI-X Career Exploration Experience Program | E63: An immersive IT and VR-based career exploration program using AI, XR, metaverse platforms, and industrial digital twins. #AI Experience #VR Experience #Career Exploration #Busan | F63: 150min | G63: 634.67 | I63: The experience may not be available due to full bookings, closures, or other scheduling constraints during the travel period. For locations outside Seoul, Incheon, and Gyeonggi-do, travel time may be longer, so we recommend combining this experience with other activities in Busan or Ulsan.
D64: Galaxy AI Class - DigitalCity | E64: Hands-on AI classes and guided tours at Samsung Digital City, exploring AI applications in everyday life and workplaces. #AI Experience #Museum tour #Home AI #Workplace tour #Samsung #Gyeonggi-do Suwon | F64: 150min | G64: free | I64: The experience may not be available due to full bookings, closures, or other scheduling constraints during the travel period.
D65: Galaxy AI Class - Samsong Store | E65: Kid-friendly AI programs at Samsung Stores featuring creative, hands-on activities such as making personalized goods. #AI Experience #Make Goods #Samsung #Seoul | F65: 150min | G65: free | I65: The experience may not be available due to full bookings, closures, or other scheduling constraints during the travel period.
C66: Korean University Visit | E66: Visit top universities in Korea to receive an introduction to the school, enjoy a campus tour, and experience student dining #TopKoreanUniversities #CampusTour #UniversityVisit #StudentCafeteria | F66: 180min | G66: free | I66: If you have a preferred university, please specify it here (e.g., Seoul National University, Korea University, Yonsei University). If left blank, we will recommend the best available option for you.
A69: Premium Package Category | H69: Check (ex.) | I69: Remarks | J69: Customer Requirement
A70: Package | E70: Package detail | F70: Duration (activity + transfer) | G70: Estimated Price (USD)
A71: K-Wellness | B71: Education | C71: Major Coporation Factory Tour | D71: Hyundai Ulsan factory | E71: A guided tour of the world’s largest single automobile manufacturing plant, showcasing vehicle production processes and Korea’s only factory-integrated automobile port. #Factory Tour #Hyndai Motor #Automobile Manufacturing #Automobile Port #Ulsan | F71: 150min | G71: free | I71: The experience may not be available due to full bookings, closures, or other scheduling constraints during the travel period. For locations outside Seoul, Incheon, and Gyeonggi-do, travel time may be longer, so we recommend combining this experience with other activities in Busan or Ulsan.
D72: Amorepacific factory | E72: An experiential tour exploring Amorepacific’s cosmetic manufacturing philosophy, smart production systems, and packaging processes. #Factory Tour #Amorepacific #Cosmetic #Manufacturing Technology #Packaging Process #Gyeonggi-do Osan | F72: 150min | G72: free | I72: The experience may not be available due to full bookings, closures, or other scheduling constraints during the travel period.
D73: Nongshim Busan factory | E73: A factory tour introducing Nongshim’s export-focused noodle and snack production, highlighting Korea’s global food manufacturing expertise. #Factory Tour #Nongshim #Ramen #Snack #Busan | F73: 150min | G73: free | I73: The experience may not be available due to full bookings, closures, or other scheduling constraints during the travel period. For locations outside Seoul, Incheon, and Gyeonggi-do, travel time may be longer, so we recommend combining this experience with other activities in Busan or Ulsan.
C74: Korean Cultural Experience | D74: Hanji Fan-Making | E74: A hands-on workshop creating traditional hanji fans while learning Korean patterns and craft techniques in a relaxed café setting. #Korean Hanji #Fan Making #Traditional Patterns #Craft #Seoul | F74: 180min | G74: 99.96
D75: Taekwondo | E75: A foreigner-only Taekwondo experience covering etiquette, basic movements, and poomsae, ending with a completion ceremony and certificate. #Traditional Korean Martial Art #Taekwondo #Etiquette Training #Basic Movements #Poomsae #Seoul | F75: 270min | G75: 253.87
D76: harmony with history and modernity | E76: Experience Korean heritage through hanbok wearing, traditional dessert making, ginseng tea tasting, and a uniquely Korean art performance. #Royal Palace #Hanbok #Korean Desserts #Korean Ginseng Tea #Art Performance #Seoul | F76: 1day | G76: 218.96
D77: Mother-of-Pearl Craft Experience | E77: A premium one-day craft program in Bukchon Hanok Village using traditional mother-of-pearl techniques guided by master artisans. #Traditional Korean Craft #Mother-of-Pearl #Shell #Seoul | F77: 180min | G77: 47 - 238
C78: Korean Heritage Tour | D78: Korean Heritage Passport Tour | E78: A nationwide cultural journey using the Korean Heritage Visitor’s Passport, covering major heritage routes and national treasures across Korea. #Passport Tour #National Heritage #Nationwide Travel | G78: free | I78: This is not a guided tour product, but a self-guided heritage experience where participants visit national heritage sites listed in the Korean Heritage Visitor’s Passport and collect stamps.The program includes 10 routes and a total of 76 national heritage sites. If selected, the itinerary will be customized according to your preferred travel period.
C79: Museum Tour | D79: National Museum of Korea | E79: Korea’s largest national museum, showcasing artifacts and national treasures from prehistoric times through the Joseon Dynasty. #National Museum #Cultural Heritage #National Treasures #Artifacts #Pensive Bodhisattva #Seoul | G79: free
D80: National Gugak Center | E80: The only museum dedicated exclusively to traditional Korean music, featuring gugak instruments, history, and performances. #National Museum #Korean Traditional Music #Gugak #Seoul | G80: free
D81: Seodaemun Prision History Hall | E81: A historic prison-turned-museum that commemorates Korea’s independence and democracy movements, symbolizing freedom and human rights.#Museum #Japanese Colonial Period #Prison #Democracy Movement #Historical Site #Seoul | G81: 4.76

Sheet (5) Selection_SubPackaging
A1: K-Subpackaging Selection Sheet for Schedule
C3: Name (M or F) : | D3: =Cover!$D$69 -> : Michael Hong | G3: Passport No. : | H3: =Cover!$D$73 -> : DMC 0000000000
C4: Birth Date : | D4: =Cover!$D$71 -> : Feb. OO, 197X(Age: 5X) | G4: Arrival Flight Schedule (Local Time): | H4: =Cover!$D$58 -> : Departure - Mar. 10. 2026. 03:30 (Dubai) / Arrival - Mar. 10. 2026. 16:50 (Incheon)
C5: VIPs Contact. : | D5: =_xlfn.TEXTJOIN(" / ", TRUE, Cover!$D$76:$D$77) -> : +971-00-00-000 / : example@example.com | G5: Departure Flight Schedule (Local Time) : | H5: =Cover!$D$59 -> : Departure - Mar. 19. 2026. 23:40 (Incheon) / Arrival - Mar. 20. 2026. 05:05 (Dubai)
A7: Premium Package Category | F7: Check (ex.) | G7: Remarks | H7: Customer Requirement
A8: Package | D8: Package detail | E8: Estimated Price (USD)
A9: Luxury Hotel | B9: ★5 Hotel | C9: Deluxe | D9: ex) Executive Grand / Premier Double / Premier Family / 2 twin bed premium / 2 double premium / Grand Deluxe Suite | E9: 853.63 - 2,792.53(1night) | G9: If you have a preferred area or hotel, please specify it here. If not specified, a hotel will be arranged based on your itinerary and preferred hotel grade.
C10: Suite | D10: Premier Suite / Park Coner Suite / Coner Suite / Royal Suite / Ambassador Suite | E10: 1,767.55 - 6,632.27(1night) | F10: ✔
C11: Special Suite | D11: Shilla Suite / Presidential Suite / Ambassador Suite / Grand Deluxe / Penthouse | E11: 4,314.15 - 20,626.67(1night)
B12: Hanok | E12: 728.28 - 34,906.67(1night)
A13: Private Vehicle | B13: NOBLE KLASSE SOLATI | C13: NOBLE KLASSE SOLATI S11 | D13: A Muslim-exclusive mobility service using the world’s first halal-certified limousine, featuring an in-vehicle prayer space for seamless Muslim travel in Korea. | G13: If you prefer a private vehicle, please specify the desired vehicle category and the number of vehicles required.
B14: Luxury Sedan | C14: Genesis G90 | E14: 714 - 1,348.67(8hour)
B15: Premium SUV | C15: Benz S580 | E15: 1,269.33 - 1,396.27(8hour) | F15: ✔
B16: Benz Sprinter | E16: 1,269.33 - 2,094.40(8hour)
B17: Limousine Bus
B18: Chauffeur | F18: ✔
A19: Interpreter | B19: General Arabic Interpreter | E19: 1605.71(8hour)
B20: Professional Arabic Interpreter | E20: 3,839.73(8hour) | F20: ✔
A21: Concierge | B21: Personal Concierge | E21: 317.33(1hour) | G21: If you require Concierge services, please specify the dates or schedule for which the service is needed.
A22: Restaurant | B22: Halal-Certified | F22: ✔ | G22: 1 time or 2 time / Day
B23: Acceptable Non-Halal | C23: Seafood
C24: Vegetarian
C25: Others | F25: ✔
B26: Cuisine Type | C26: Korean cuisine
C27: Western / European
C28: Others
B29: Meal preferences | C29: Alcohol-free menu preferred
C30: Hotel breakfast included
C31: Others | F31: ✔
A32: Insurance | E32: 317.33 | F32: ✔
A33: VIP Security | B33: VIP Security | D33: Only Tour & Shopping period | E33: 1,000(10hour) | F33: ✔ | G33: If you require VIP security services, please specify the dates or schedule for which the service is needed.
D34: Tour full days

Sheet Total Quotation Price
A1: Muslim VIP K-BMW Premium Tour ToTal Quotation Price for Schedule
D3: Name (M or F) : | E3: =Cover!$D$69 -> : Michael Hong | G3: Passport No. : | J3: =Cover!$D$73 -> : DMC 0000000000
D4: Birth Date : | E4: =Cover!$D$71 -> : Feb. OO, 197X(Age: 5X) | G4: Arrival Flight Schedule (Local Time): | J4: =Cover!$D$58 -> : Departure - Mar. 10. 2026. 03:30 (Dubai) / Arrival - Mar. 10. 2026. 16:50 (Incheon)
D5: VIPs Contact. : | E5: =_xlfn.TEXTJOIN(" / ", TRUE, Cover!$D$76:$D$77) -> : +971-00-00-000 / : example@example.com | G5: Departure Flight Schedule (Local Time) : | J5: =Cover!$D$59 -> : Departure - Mar. 19. 2026. 23:40 (Incheon) / Arrival - Mar. 20. 2026. 05:05 (Dubai)
I7: Exchange Rate (KRW/USD) | J7: 1500
A9: Premium Package Category
A10: Package | E10: Estimation | G10: Partners Quotation (Cost) | I10: Margin Rate | J10: Agent Fee (Customer Submit)
I11: 0.5 | J11: 0.15 | K11: Comission Fee internal partner
E12: 1,000 KRW | F12: USD | G12: 1,000 KRW | H12: USD | I12: USD | J12: USD
A13: K-Medical | B13: Silver | E13: M: 1,485 - 1,800 F: 1,665 - 2,600 | H13: =G13/$J$7*1000 -> 0 | I13: =H13+H13*$I$11 -> 0 | J13: =I13+I13*$J$77 -> 0
B14: Gold | E14: M: 2,210 - 7,800 F: 2,600 - 8,100 | H14: =G14/$J$7*1000 -> 0 | I14: =H14+H14*$I$77 -> 0 | J14: =I14+I14*$J$77 -> 0
B15: Diamond (Premium) | E15: M: 7,260 - 10,600 F: 7,890- 10,900 | G15: 10900 | H15: =G15/$J$7*1000 -> 7266.6667 | I15: =H15+H15*$I$11 -> 10900 | J15: =I15+I15*$J$77 -> 12535 | K15: =G15*0.15*1000 -> 1635000 | L15: =I15-H15 -> 3633.3333 | M15: =J15-I15 -> 1635
A16: K-Beauty (Medical) | B16: A Clinic | C16: Signiture Program | D16: Salon de Juvénile
D17: Salon de All-Layer
D18: Salon de Sportif
C19: Package | D19: Glow Package | F19: 6666.67 | H19: =G19/$J$7*1000 -> 0 | I19: =H19+H19*$I$77 -> 0 | J19: =I19+I19*$J$77 -> 0
D20: Premium Anti-Aging Package | F20: 13333.33
D21: Premium Stem Cell Anti-Aging Package | F21: 20000 | H21: =G21/$J$7*1000 -> 0 | I21: =H21+H21*$I$77 -> 0 | J21: =I21+I21*$J$77 -> 0
D22: Premiun Body Package | F22: 33333.33 | G22: 15000 | H22: =G22/$J$7*1000 -> 10000 | I22: =H22+H22*$I$77 -> 15000 | J22: =I22+I22*$J$77 -> 17250
B23: B Clinic | C23: Dermatological procedures | D23: Special - 2 | H23: =G23/$J$7*1000 -> 0 | I23: =H23+H23*$I$77 -> 0 | J23: =I23+I23*$J$77 -> 0
D24: Basic | E24: 5,000 / 10,000 / 15,000 | G24: 10000 | H24: =G24/$J$7*1000 -> 6666.6667 | I24: =H24+H24*$I$77 -> 10000 | J24: =I24+I24*$J$77 -> 11500 | K24: =G24*0.15*1000 -> 1500000
D25: Gold | E25: 10,000 / 15,000 / 20,000 | H25: =G25/$J$7*1000 -> 0 | I25: =H25+H25*$I$77 -> 0 | J25: =I25+I25*$J$77 -> 0
D26: Platinum | E26: 15,000 / 20,000 / 25,000 | H26: =G26/$J$7*1000 -> 0 | I26: =H26+H26*$I$77 -> 0 | J26: =I26+I26*$J$77 -> 0
B27: C Clinic | C27: Dermatological procedures | D27: Royal Refresh Day (Face only, no injection) | E27: 5000 | H27: =G27/$J$7*1000 -> 0 | I27: =H27+H27*$I$77 -> 0 | J27: =I27+I27*$J$77 -> 0
D28: Royal Signature Lifting (Including neck & fatigue recovery) | E28: 10000 | H28: =G28/$J$7*1000 -> 0 | I28: =H28+H28*$I$77 -> 0 | J28: =I28+I28*$J$77 -> 0
D29: Royal Face & Body Refinement (Royal Hospital Takeover) | E29: 15000 | G29: 15000 | H29: =G29/$J$7*1000 -> 10000 | I29: =H29+H29*$I$77 -> 15000 | J29: =I29+I29*$J$77 -> 17250
A30: K-Beauty (Non-Medical) | B30: Body Therapy | C30: Silver | E30: 260 - 363 | H30: =G30/$J$7*1000 -> 0 | I30: =H30+H30*$I$77 -> 0 | J30: =I30+I30*$J$77 -> 0
C31: Gold | E31: 340 - 680 | H31: =G31/$J$7*1000 -> 0 | I31: =H31+H31*$I$77 -> 0 | J31: =I31+I31*$J$77 -> 0
C32: Diamond (Premium) | E32: 425 - 1,500 | G32: 1500 | H32: =G32/$J$7*1000 -> 1000 | I32: =H32+H32*$I$77 -> 1500 | J32: =I32+I32*$J$77 -> 1725
B33: Signature treatments | C33: Silver | E33: 530 | H33: =G33/$J$7*1000 -> 0 | I33: =H33+H33*$I$77 -> 0 | J33: =I33+I33*$J$77 -> 0
C34: Gold | E34: 530 | H34: =G34/$J$7*1000 -> 0 | I34: =H34+H34*$I$77 -> 0 | J34: =I34+I34*$J$77 -> 0
C35: Diamond (Premium) | E35: 530 | G35: 530 | H35: =G35/$J$7*1000 -> 353.33333 | I35: =H35+H35*$I$77 -> 530 | J35: =I35+I35*$J$77 -> 609.5
B36: Facial collection | C36: Silver | E36: 410 | H36: =G36/$J$7*1000 -> 0 | I36: =H36+H36*$I$77 -> 0 | J36: =I36+I36*$J$77 -> 0
C37: Gold | E37: 450 | H37: =G37/$J$7*1000 -> 0 | I37: =H37+H37*$I$77 -> 0 | J37: =I37+I37*$J$77 -> 0
C38: Diamond (Premium) | E38: 560 | G38: 560 | H38: =G38/$J$7*1000 -> 373.33333 | I38: =H38+H38*$I$77 -> 560 | J38: =I38+I38*$J$77 -> 644
B39: Henna | H39: =G39/$J$7*1000 -> 0 | I39: =H39+H39*$I$77 -> 0 | J39: =I39+I39*$J$77 -> 0
B40: Scalp treatment | E40: 250 | G40: 250 | H40: =G40/$J$7*1000 -> 166.66667 | I40: =H40+H40*$I$77 -> 250 | J40: =I40+I40*$J$77 -> 287.5
A43: Premium Package Category
A44: Package | E44: Estimation | G44: Partners Quotation (Cost) | I44: Margin Rate | J44: Agent Fee (Customer Submit)
I45: 0.5 | J45: =J11 -> 0.15
E46: 1,000 KRW | F46: USD | G46: 1,000 KRW | H46: USD | I46: USD | J46: USD
A47: K-Wellness | B47: Free Time
B48: Shopping | C48: Cosmetics & Beauty Products | H48: =G48/$J$7*1000 -> 0 | I48: =H48+H48*$I$77 -> 0 | J48: =I48+I48*$J$77 -> 0
C49: K-GLASSES | H49: =G49/$J$7*1000 -> 0 | I49: =H49+H49*$I$77 -> 0 | J49: =I49+I49*$J$77 -> 0
C50: Stationery | H50: =G50/$J$7*1000 -> 0 | I50: =H50+H50*$I$77 -> 0 | J50: =I50+I50*$J$77 -> 0
B51: K-Pop | C51: Tour | D51: K-POP Demon Hunters | E51: 860 / 1Group | G51: 430 | H51: =G51/$J$7*1000 -> 286.66667 | I51: =H51+H51*$I$77 -> 430 | J51: =I51+I51*$J$77 -> 494.5
D52: K-POP Concert | F52: 240 | H52: =G52/$J$7*1000 -> 0 | I52: =H52+H52*$I$77 -> 0 | J52: =I52+I52*$J$77 -> 0
D53: K-Drama Tour (Descendants of the Sun, Guardian: The Lonely and Great God, My Love From the Star) | F53: 103 - 233 | H53: =G53/$J$7*1000 -> 0 | I53: =H53+H53*$I$77 -> 0 | J53: =I53+I53*$J$77 -> 0
D54: K-Drama Tour (Welcome to Samdal-ri, Extraordinary Attorney Woo, When Life Gives You Tangerines) | F54: 402 | H54: =G54/$J$7*1000 -> 0 | I54: =H54+H54*$I$77 -> 0 | J54: =I54+I54*$J$77 -> 0
D55: K-Drama Tour (Squid Game) | E55: 231 | H55: =G55/$J$7*1000 -> 0 | I55: =H55+H55*$I$77 -> 0 | J55: =I55+I55*$J$77 -> 0
D56: Award Ceremony | H56: =G56/$J$7*1000 -> 0 | I56: =H56+H56*$I$77 -> 0 | J56: =I56+I56*$J$77 -> 0
C57: Experience | D57: K-POP Experience | E57: 539 | H57: =G57/$J$7*1000 -> 0 | I57: =H57+H57*$I$77 -> 0 | J57: =I57+I57*$J$77 -> 0
C58: Dance | D58: K-POP Dance Lesson | E58: 100 | H58: =G58/$J$7*1000 -> 0 | I58: =H58+H58*$I$77 -> 0 | J58: =I58+I58*$J$77 -> 0
C59: Beauty | D59: K-POP Fashion | E59: 200 - 213
D60: K-POP Styling | F60: 450
D61: Style Consulting | E61: 450 | G61: 213 | H61: =G61/$J$7*1000 -> 142 | I61: =H61+H61*$I$77 -> 213 | J61: =I61+I61*$J$77 -> 244.95
D62: Personal Color Diagnosis | E62: 600 - 8,800 | G62: 8800 | H62: =G62/$J$7*1000 -> 5866.6667 | I62: =H62+H62*$I$77 -> 8800 | J62: =I62+I62*$J$77 -> 10120
B63: Tour | C63: Seoul Tour | D63: Seoul City Tour | E63: 220 | H63: =G63/$J$7*1000 -> 0 | I63: =H63+H63*$I$77 -> 0 | J63: =I63+I63*$J$77 -> 0
D64: Seoul City Night Tour | E64: 90 | G64: 90 | H64: =G64/$J$7*1000 -> 60 | I64: =H64+H64*$I$77 -> 90 | J64: =I64+I64*$J$77 -> 103.5
D65: ISLAMIC Seoul City Tour | E65: 85 | H65: =G65/$J$7*1000 -> 0 | I65: =H65+H65*$I$77 -> 0 | J65: =I65+I65*$J$77 -> 0
C66: Local Tour | D66: DMZ + NLL Tour | E66: 160 | G66: =160*2 -> 320 | H66: =G66/$J$7*1000 -> 213.33333 | I66: =H66+H66*$I$77 -> 320 | J66: =I66+I66*$J$77 -> 368
D67: ISLAMIC NAMI ISLAND TOUR | E67: 120 | G67: =120*2 -> 240 | H67: =G67/$J$7*1000 -> 160 | I67: =H67+H67*$I$77 -> 240 | J67: =I67+I67*$J$77 -> 276
D68: Jeju Island Private Tour | E68: 686 - 1,165 | H68: =G68/$J$7*1000 -> 0 | I68: =H68+H68*$I$77 -> 0 | J68: =I68+I68*$J$77 -> 0
D69: Jeju island Golf Tour | E69: 887 - 1,245 | H69: =G69/$J$7*1000 -> 0 | I69: =H69+H69*$I$77 -> 0 | J69: =I69+I69*$J$77 -> 0
D70: Gyeongbuk Tourpass | E70: 17 | H70: =G70/$J$7*1000 -> 0 | I70: =H70+H70*$I$77 -> 0 | J70: =I70+I70*$J$77 -> 0
C71: Cruise Tour | D71: Busan Cruise Tour | E71: 600 - 650 | H71: =G71/$J$7*1000 -> 0 | I71: =H71+H71*$I$77 -> 0 | J71: =I71+I71*$J$77 -> 0
C72: Rail Cruise Tour | D72: Grand Tour of Korea by Train | E72: 3,540 - 3,710 | H72: =G72/$J$7*1000 -> 0 | I72: =H72+H72*$I$77 -> 0 | J72: =I72+I72*$J$77 -> 0
A75: Premium Package Category
A76: Package | E76: Estimation | G76: Partners Quotation (Cost) | I76: Margin Rate | J76: Agent Fee (Customer Submit)
I77: 0.5 | J77: =J11 -> 0.15
E78: 1,000 KRW | F78: USD | G78: 1,000 KRW | H78: USD | I78: USD | J78: USD
A79: K-Wellness | B79: Leisure | C79: Snow park | D79: ski | E79: 111 - 159 | H79: =G79/$J$7*1000 -> 0 | I79: =H79+H79*$I$77 -> 0 | J79: =I79+I79*$J$77 -> 0
D80: board | E80: 111 - 159 | H80: =G80/$J$7*1000 -> 0 | I80: =H80+H80*$I$77 -> 0 | J80: =I80+I80*$J$77 -> 0
D81: lesson | E81: 150 - 400 | H81: =G81/$J$7*1000 -> 0 | I81: =H81+H81*$I$77 -> 0 | J81: =I81+I81*$J$77 -> 0
C82: Water Park | E82: 50 - 90 | H82: =G82/$J$7*1000 -> 0 | I82: =H82+H82*$I$77 -> 0 | J82: =I82+I82*$J$77 -> 0
C83: Barge | E83: 59 - 75 | H83: =G83/$J$7*1000 -> 0 | I83: =H83+H83*$I$77 -> 0 | J83: =I83+I83*$J$77 -> 0
C84: Sprorts | D84: Baseball | E84: 71 - 77 | H84: =G84/$J$7*1000 -> 0 | I84: =H84+H84*$I$77 -> 0 | J84: =I84+I84*$J$77 -> 0
D85: Soccer | E85: 2,970 / 1Group | H85: =G85/$J$7*1000 -> 0 | I85: =H85+H85*$I$77 -> 0 | J85: =I85+I85*$J$77 -> 0
C86: Theme Park | E86: 52 - 350 | G86: 350 | H86: =G86/$J$7*1000 -> 233.33333 | I86: =H86+H86*$I$77 -> 350 | J86: =I86+I86*$J$77 -> 402.5
B87: KTX Experience
B88: Education | C88: Package tour | D88: Experience Future-Oriented Korean Education Spanning School Exchange, AI, Media, and K-POP | E88: 1100.5 | H88: =G88/$J$7*1000 -> 0 | I88: =H88+H88*$I$77 -> 0 | J88: =I88+I88*$J$77 -> 0
D89: Korean educational tour encompassing university campuses, future technologies, media, and theme parks | E89: 1018.5 | H89: =G89/$J$7*1000 -> 0 | I89: =H89+H89*$I$77 -> 0 | J89: =I89+I89*$J$77 -> 0
D90: Experience K-POP, Traditional Culture, Theme Parks, and Future Industries All at Once | E90: 1178 | H90: =G90/$J$7*1000 -> 0 | I90: =H90+H90*$I$77 -> 0 | J90: =I90+I90*$J$77 -> 0
C91: It experience | D91: AI-X Career Exploration Experience Program | E91: 400 | H91: =G91/$J$7*1000 -> 0 | I91: =H91+H91*$I$77 -> 0 | J91: =I91+I91*$J$77 -> 0
D92: Galaxy AI Class - DigitalCity | E92: free | H92: =G92/$J$7*1000 -> 0 | I92: =H92+H92*$I$77 -> 0 | J92: =I92+I92*$J$77 -> 0
D93: Galaxy AI Class - Samsong Store | E93: free | H93: =G93/$J$7*1000 -> 0 | I93: =H93+H93*$I$77 -> 0 | J93: =I93+I93*$J$77 -> 0
C94: Korean University Visit | E94: free | H94: =G94/$J$7*1000 -> 0 | I94: =H94+H94*$I$77 -> 0 | J94: =I94+I94*$J$77 -> 0
C95: Major Coporation Factory Tour | D95: Hyundai Ulsan factory | E95: free | H95: =G95/$J$7*1000 -> 0 | I95: =H95+H95*$I$77 -> 0 | J95: =I95+I95*$J$77 -> 0
D96: Amorepacific factory | E96: free | H96: =G96/$J$7*1000 -> 0 | I96: =H96+H96*$I$77 -> 0 | J96: =I96+I96*$J$77 -> 0
D97: Nongshim Busan factory | E97: free | H97: =G97/$J$7*1000 -> 0 | I97: =H97+H97*$I$77 -> 0 | J97: =I97+I97*$J$77 -> 0
C98: Korean Cultural Experience | D98: Hanji Fan-Making | F98: 42 | H98: =G98/$J$7*1000 -> 0 | I98: =H98+H98*$I$77 -> 0 | J98: =I98+I98*$J$77 -> 0
D99: Taekwondo | E99: 160 | H99: =G99/$J$7*1000 -> 0 | I99: =H99+H99*$I$77 -> 0 | J99: =I99+I99*$J$77 -> 0
D100: harmony with history and modernity | E100: 138 | H100: =G100/$J$7*1000 -> 0 | I100: =H100+H100*$I$77 -> 0 | J100: =I100+I100*$J$77 -> 0
D101: Mother-of-Pearl Craft Experience | E101: 30 - 150 | H101: =G101/$J$7*1000 -> 0 | I101: =H101+H101*$I$77 -> 0 | J101: =I101+I101*$J$77 -> 0
C102: Korean Heritage Tour | D102: Korean Heritage Passport Tour | E102: free | H102: =G102/$J$7*1000 -> 0 | I102: =H102+H102*$I$77 -> 0 | J102: =I102+I102*$J$77 -> 0
C103: Museum Tour | D103: National Museum of Korea | E103: free | H103: =G103/$J$7*1000 -> 0 | I103: =H103+H103*$I$77 -> 0 | J103: =I103+I103*$J$77 -> 0
D104: National Gugak Center | E104: free | H104: =G104/$J$7*1000 -> 0 | I104: =H104+H104*$I$77 -> 0 | J104: =I104+I104*$J$77 -> 0
D105: Seodaemun Prision History Hall | E105: 3 | H105: =G105/$J$7*1000 -> 0 | I105: =H105+H105*$I$77 -> 0 | J105: =I105+I105*$J$77 -> 0
A108: Premium Package Category
A109: Package | E109: Estimation | G109: Partners Quotation (Cost) | I109: Margin Rate | J109: Agent Fee (Customer Submit)
...

Sheet Total Price Sheet
A1: Muslim VIP K-BMW Premium Tour ToTal Price Sheet for Schedule
A3: Name (M or F) : | B3: =Cover!$D$69 -> : Michael Hong | C3: Passport No. : | D3: =Cover!$D$73 -> : DMC 0000000000
A4: Birth Date : | B4: =Cover!$D$71 -> : Feb. OO, 197X(Age: 5X) | C4: Arrival Flight Schedule (Local Time): | D4: =Cover!$D$58 -> : Departure - Mar. 10. 2026. 03:30 (Dubai) / Arrival - Mar. 10. 2026. 16:50 (Incheon)
A5: VIPs Contact. : | B5: =_xlfn.TEXTJOIN(" / ", TRUE, Cover!$D$76:$D$77) -> : +971-00-00-000 / : example@example.com | C5: Departure Flight Schedule (Local Time) : | D5: =Cover!$D$59 -> : Departure - Mar. 19. 2026. 23:40 (Incheon) / Arrival - Mar. 20. 2026. 05:05 (Dubai)
C7: Exchange Rate (KRW/USD) | D7: 1500
A9: Premium Package Category
A10: Package | D10: Agent Fee (VIPs Customer Submit Price)
D11: USD
A12: K-Medical | B12: Dimond (Premium) | D12: =SUM('Total Quotation Price'!J13:J15) -> 12535
A13: K-Beauty (Medical) | B13: A Clinic | D13: =SUM('Total Quotation Price'!J23:J26) -> 11500
B14: B Clinic | D14: =SUM('Total Quotation Price'!J26:J28) -> 0
B15: C Clinic | D15: =SUM('Total Quotation Price'!J27:J29) -> 17250
A16: K-Beauty (Non-Medical) | B16: Body Therapy | D16: =SUM('Total Quotation Price'!J30:J32) -> 1725
B17: Signature treatments | D17: =SUM('Total Quotation Price'!J33:J35) -> 609.5
B18: Facial collection | D18: =SUM('Total Quotation Price'!J36:J38) -> 644
B19: Henna | D19: =SUM('Total Quotation Price'!J39) -> 0
B20: Scalp treatment | D20: =SUM('Total Quotation Price'!J40) -> 287.5
A21: K-Wellness | B21: Free Time
B22: Shopping
B23: K-Pop | C23: Tour | D23: =SUM('Total Quotation Price'!J51:J56) -> 494.5
C24: Experience | D24: =SUM('Total Quotation Price'!J57) -> 0
C25: Dance | D25: =SUM('Total Quotation Price'!J58) -> 0
C26: Beauty | D26: =SUM('Total Quotation Price'!J59:J62) -> 10364.95
B27: Tour | C27: Seoul Tour | D27: =SUM('Total Quotation Price'!J63:J65) -> 103.5
C28: Local Tour | D28: =SUM('Total Quotation Price'!J66:J70) -> 644
C29: Busan Cruise Tour | D29: =SUM('Total Quotation Price'!J71) -> 0
C30: Grand Tour of Korea by Train | D30: =SUM('Total Quotation Price'!J72) -> 0
B31: Leisure | C31: Snow park | D31: =SUM('Total Quotation Price'!J79:J81) -> 0
C32: Water Park | D32: =SUM('Total Quotation Price'!J82) -> 0
C33: Barge | D33: =SUM('Total Quotation Price'!J83) -> 0
C34: Sprorts | D34: =SUM('Total Quotation Price'!J84:J85) -> 0
C35: Theme Park | D35: =SUM('Total Quotation Price'!J86) -> 402.5
B36: KTX Experience | D36: =SUM('Total Quotation Price'!J87) -> 0
B37: Education | C37: Package tour | D37: =SUM('Total Quotation Price'!J88:J90) -> 0
C38: It experience | D38: =SUM('Total Quotation Price'!J91:J93) -> 0
C39: Korean University Visit | D39: =SUM('Total Quotation Price'!J94) -> 0
C40: Major Coporation Factory Tour | D40: =SUM('Total Quotation Price'!J95:J97) -> 0
C41: Korean Cultural Experience | D41: =SUM('Total Quotation Price'!J98:J101) -> 0
C42: Korean Heritage Tour | D42: =SUM('Total Quotation Price'!J102) -> 0
C43: Museum Tour | D43: =SUM('Total Quotation Price'!J103:J105) -> 0
A44: Luxury Hotel | B44: ★5 Hotel | D44: =SUM('Total Quotation Price'!J112:J115) -> 29333.453
B45: Hanok | D45: =SUM('Total Quotation Price'!J116) -> 0
A46: Private Vehicle | B46: Luxury Sedan | D46: =SUM('Total Quotation Price'!J117) -> 7084
B47: Premium SUV | D47: =SUM('Total Quotation Price'!J118) -> 0
B48: Benz Sprinter | D48: =SUM('Total Quotation Price'!J119) -> 0
B49: Limousine Bus | D49: =SUM('Total Quotation Price'!J120) -> 0
B50: Chauffeur | D50: =SUM('Total Quotation Price'!J121) -> 0
A51: Interpreter | D51: =SUM('Total Quotation Price'!J121:J122) -> 5750
A52: Concierge | D52: =SUM('Total Quotation Price'!J123) -> 6900
A53: Restaurant | D53: =SUM('Total Quotation Price'!J124:J126) -> 0
A54: Insurance | D54: =SUM('Total Quotation Price'!J127) -> 230
A55: VIP Security | B55: VIP Security | D55: =SUM('Total Quotation Price'!J128) -> 5750
D57: Total Agent Fee
D58: =SUM(D12:D55) -> 111607.9

Sheet INVOICE_to Agent
A1: Commercial Invioce (Example)
B3: To | C3: : OOOO | E3: Ref.NO. | F3: : INTERVIEW-OO-2603-OO
B4: Attention | C4: : | E4: Issue Date | F4: : Feb OO, 2026
B5: C.C | C5: :
B6: From | C6: : Interview Co., Ltd
B8: Subject : K-Beauty & Medical Premium Tour Package for Muslim VIP Clients
G10: Currency: United States Dollars
B11: No | C11: Descriptions | E11: Q'ty | F11: Unit Price | G11: Amount | H11: Remarks
B12: 1 | C12: K-Beauty & Medical Premium Tour Package for Muslim VIP Clients | E12: 1 | F12: ='Total Quotation Price'!I131 -> 112051.85 | G12: =E12*F12 -> 112051.85
B13: Total Amount(USD) | G13: =SUM(G12) -> 112051.85
B15: We are pleased to submit an invoice for the Maharba K-Medi & Beauty and K-Entertainment Tour Package for your VIP clients.
B17: Bank Account Details
A19: 1. | B19: Name of Bank | C19: : SHINHAN BANK
A20: 2. | B20: Account No. | C20: : 180 039 209697
A21: 3. | B21: Address | C21: : 20, SEJONG-DAERO 9-GIL, JUNG-GU, SOUTH KOREA
A22: 4. | B22: Swift Code | C22: : SHBKKRSE
A23: 5. | B23: Beneficiary | C23: : INTERVIEW CO LTD
B24: Beneficiary No. | C24: : +82 10 2396 0469
B26: Yours Faithfully,
B28: Interview Co.,Ltd.
B38: 805ho, 8F, 229 Seokjeong-ro, Michuhol-gu, | D38: Tel: +82-32-715-7899
B39: Incheon, Republic of Korea | D39: Fax: +82-32-715-7946 | G39: www.interviewcorp.co.kr
D40: Email: info@interviewcorp.co.kr

Sheet Travel schedule_cover
B2: Premium Experience
B4: 10-DAY VIP
B5: K-Beauty & Medical Tour
B7: K-Medical · K-Beauty · K-Wellness
E9: DXB | I9: ICN | N9: DXB
B11: March 10-19, 2026
B12: Secoul & Incheon, South Korea
B15: 10-DAY VIP Tour Overview
B17: K-Medical · K-Beauty · K-Wellness
D20: Arrival & Welcome | K20: Precision Health Assessment — Part I
D21: ● | E21: Incheon arrival | K21: ● | L21: Comprehensive health screening
D22: ● | E22: Oackwood Premier Incheon check-in | K22: ● | L22: VIP hospital stay
D27: Precision Health Assessment — Part II | K27: Precision Health Assessment — Part III
D28: ● | E28: Health screening & Colonoscopy | K28: ● | L28: PET-CT imaging
K29: ● | L29: Signiel Seoul check-in
D34: Style Consulting & Shopping Experience | K34: Comprehensive Skin Rejuvenation
D35: ● | E35: Hair, Makeup, fashion styling | K35: ● | L35: Personalized aesthetic program
D36: ● | E36: Stylist-accompanied shopping tour
D37: ● | E37: glasses, cosmetic shopping
D41: Leisure & Recovery | K41: Heritage & History
D42: ● | E42: Signature spa therapy | K42: ● | L42: DMZ & NLL guided tour
D43: ● | E43: Thema Park experience
D48: Stem Cell Lifting Treatment | K48: Final Wellness & Farewell
D49: ● | E49: Advanced Stem Cell Treatment | K49: ● | L49: Luxury spa
K50: ● | L50: Departure from Incheon

Sheet Day1(Mar.10)_VIP
B1: Day 1. March 10 Arrival & Welcome Incheon International Airport -> Oakwood Premier Incheon
C3: Afternoon
C4: 12:00 - 12:30 | D4: Arrival & Immigration Clearance(Incheon International Airport)
C5: 12:30 - 12:45 | D5: Luggage Assistance & VIP vehicle(Incheon International Airport)
C7: Evening
C8: 18:00 - 18:15 | D8: Maghrib Pray(In-Vehicle)
C9: 18:15 - 18:30 | D9: Incheon International Airport -> Oakwook Premier Incheon
D10: Hotel Check-in (Oakwood Premier Incheon)
C11: 19:30 - 19:45 | D11: Isha Pray(In-Vehicle)
C12: 20:00 - 22:00 | D12: Dinner (Hotel Restaurant)
C13: 22:30 - | D13: Evening rest

Sheet Day2(Mar.11)_VIP
B1: Day 2. March 11 Precision Health Assessment — Part I Hospital VIP Medical Center ※ Examination schedules and prayer times will be arranged flexibly
C3: Morning - Afternoon
C4: 06:00 - 06:15 | D4: Fajr Pray(Hotel)
C5: 06:15 - 08:00 | D5: Rest before Hospital Visit
C6: 08:00 - 09:00 | D6: Oakwood Premier Incheon -> Gil Medical Center
C7: 09:00 - 18:00 | D7: Health Screening (Gil Medical Center)
D8: Dhuhr Pray / Asr Pray (Gil Medical Center)
D9: Dinner
D10: VIP Ward Assignment & Room Preparation (Gil Medical Center – VIP Ward)
C12: Evening
C13: 18:00 - 18:15 | D13: Maghrib Pray(In-Vehicle)
C14: 18:15 - 19:30 | D14: Dinner (Gil Medical Center – VIP Ward)
C15: 19:30 - 19:45 | D15: Isha Pray(In-Vehicle)
C16: 19:45 - | D16: Evening rest

Sheet Day3(Mar.12)_VIP
B1: Day 3. March 12 Precision Health Assessment — Part II Hospital VIP Medical Center ※ Examination schedules and prayer times will be arranged flexibly
C3: Morning - Afternoon
C7: Evening

Sheet Day4(Mar.13)_VIP
B1: Day 4. March 13 Precision Health Assessment — Part III Hospital → Signiel Seoul ※ Examination schedules and prayer times will be arranged flexibly
C3: Morning - Afternoon
C7: Evening

Sheet Day5(Mar.14)_VIP
B1: Day 5. March 14 Style Consulting & Shopping Experience Personal Styling & Curated Shopping Tour
C3: Morning
C4: 06:00 - 06:15 | D4: Fajr Pray(Hotel)
C5: 06:15 - 08:00 | D5: Breakfast(Hotel Restaurant)
C6: 08:00 - 10:00 | D6: Hotel -> Styling Venue
C7: 10:00 - 12:00 | D7: Personal Styling Consultation(Styling Venue) Premium image consulting (hair, makeup, fashion)
C9: Afternoon
C10: 12:00 - 12:30 | D10: Styling Venue -> Restaurant
C11: 12:30 - 12:45 | D11: Dhuhr Pray(In-Vehicle)
C12: 12:45 - 14:00 | D12: Lunch(Restaurant)
C13: 14:00 - 14:30 | D13: Restaurant -> Shopping Venue
C14: 14:30 - 16:00 | D14: Stylist-accompanied Shopping Tour(Shopping Venue) Outfit recommendations at selected stores
C15: 16:00 - 16:15 | D15: Asr Pray(In-Vehicle)
C16: 16:15 - 16:45 | D16: Shopping Venue -> KUMKANG Optical
C17: 16:45 - 18:00 | D17: Eye Examination & Luxury Eyewear Fitting(KUMKANG Optical) Premium optical store
C19: Evening
C20: 18:00 - 18:15 | D20: Maghrib Pray(In-Vehicle)
C21: 18:15 - 18:30 | D21: KUMKANG Optical ->Olive Young
C22: 18:30 - 19:30 | D22: K-Beauty Shopping Experience(Olive Young) Curated selection of cosmetics and beauty products
C23: 19:30 - 19:45 | D23: Isha Pray(In-Vehicle)
C24: 19:45 - 20:00 | D24: Olive Young ->Restaurant
C25: 20:00 - 22:00 | D25: Dinner(Restaurant)
C26: 22:00 - 22:30 | D26: Restaurant -> Hotel
C27: 22:30 - | D27: Evening rest

Sheet Day6(Mar.15)_VIP
B1: Day 6. March 15 Comprehensive Skin Rejuvenation Premium Aesthetics Clinic in Seoul ※ Treatment schedules and prayer times will be arranged flexibly
C3: Morning - Afternoon
C7: Evening

Sheet Day7(Mar.16)_VIP
B1: Day 7. March 16 Leisure & Recovery Signiel Spa & Lotte World
C3: Morning
C9: Afternoon
C17: Evening

Sheet Day8(Mar.17)_VIP
B1: Day 8. March 17 Heritage & History DMZ(Demilitarized Zone) & NLL(Northern Limit Line) ※ Conducted by professional tour operator with English-speaking guide ※ Prayer times arranged flexibly during tour
C3: Morning
C9: Afternoon
C17: Evening

Sheet Day9(Mar.18)_VIP
B1: Day 9. March 18 Stem Cell Lifting Treatment Premium Aesthetics Clinic in Seoul ※ Treatment schedules and prayer times will be arranged flexibly
C3: Morning
C9: Afternoon
C17: Evening

Sheet Day10(Mar.19)_VIP
B1: Day 10. March 19 Final Wellness & Farewell Spa -> Incheon International Airport
C3: Morning
C9: Afternoon
C17: Evening

Sheet Day1(Mar.10)_Internal
A1: Day 1. March 10 Arrival & Welcome Incheon International Airport -> Oakwood Premier Incheon
A4: Date | B4: Category | C4: Time | D4: Activity | E4: Partner Company | F4: Transport | G4: Status | H4: Notes
A5: Day 1 March 10, 2026 | C5: Afternoon
B6: Arrival | C6: 12:00 - 12:30 | D6: Arrival & Immigration Clearance(Incheon International Airport)
B7: Arrival | C7: 12:30 - 12:45 | D7: Luggage Assistance & VIP vehicle(Incheon International Airport) | E7: NOBLE KLASSE 070-5210-7678 vipriding@kcmotors.co.kr | G7: Planned | H7: 픽업, 하차 위치 사전 확인
C9: Evening
B10: Pray | C10: 18:00 - 18:15 | D10: Maghrib Pray(In-Vehicle) | H10: 정확한 기도 시간 확인
B11: Transfer | C11: 18:15 - 18:30 | D11: Incheon International Airport -> Oakwook Premier Incheon | E11: NOBLE KLASSE | F11: SOLATI S11 (할랄 인증 리무진) | H11: 차량 대기 및 이동 동선 확인 교통 상황 사전 체크
B12: Check-in | D12: Hotel Check-in (Oakwood Premier Incheon) | E12: Oak Wood Premier Incehon 032-726-2000 reservations.incheon@oakwoodpremier.co.kr | G12: Planned | H12: VIP 이동 중 사전 체크인 진행 (자사 직원/컨시어지) 객실 배정 및 기도 편의 사항 사전 준비
B13: Pray | C13: 19:30 - 19:45 | D13: Isha Pray(In-Vehicle) | H13: 정확한 기도 시간 확인
B14: Dining | C14: 20:00 - 22:00 | D14: Dinner (Hotel Restaurant) | E14: OAK Restaurant & Bar 032.726.2301 | G14: Planned | H14: 소고기 스테이크 & 랍스터 메뉴 예약 가능 여부 확인 고객 선호 음식 확인
B15: Rest | C15: 22:30 - | D15: Evening rest

Sheet Day2(Mar.11)_Internal
A1: Day 2. March 11 Precision Health Assessment — Part I Hospital VIP Medical Center ※ Examination schedules and prayer times will be arranged flexibly
A4: Date | B4: Category | C4: Time | D4: Activity | E4: Partner Company | F4: Transport | G4: Status | H4: Notes
A5: Day 2 March 11, 2026 | C5: Morning - Afternoon
B6: Pray | C6: 06:00 - 06:15 | D6: Fajr Pray(Hotel)
B7: Rest | C7: 06:15 - 08:00 | D7: Rest before Hospital Visit | H7: 검진 전 식음료 섭취 금지 사항 사전 안내 필요
B8: Transfer | C8: 08:00 - 09:00 | D8: Oakwood Premier Incheon -> Gil Medical Center | E8: Gil Hospital International Healthcare Center 032-460-3213 010-6272-9567 | F8: Hospital-arranged vehicle | G8: Planned | H8: 길병원 – 오크우드호텔 협력으로 차량 지원 제공 별도 차량 예약 불필요 픽업 시간 병원 측 사전 조율 필요
B9: Examination | C9: 09:00 - 18:00 | D9: Health Screening (Gil Medical Center) | E9: Gil Hospital International Healthcare Center | G9: Planned | H9: 전체 건강검진 일정 확인 필요 검사 사이 대기 시간 및 휴식 가능 여부 확인
B10: Pray | D10: Dhuhr Pray / Asr Pray (Gil Medical Center) | H10: 기도 시간 확보 가능 여부 기도실 또는 대체 공간 사용 가능 여부 확인 필요
B11: Dining | D11: Dinner | H11: 중식 섭취 가능 여부 확인 필요
B12: Admission | D12: VIP Ward Assignment & Room Preparation (Gil Medical Center – VIP Ward) | E12: Gil Hospital International Healthcare Center | G12: Planned | H12: 병실 내 기도 가능 공간 확보 여부 사전 확인 및 필요 시 요청 진행 VIP 병동 배정 관련 병원 측 사전 협의 진행 병원 담당 코디네이터 전담 연락 창구 확보 및 일정 공유
C14: Evening
B15: Pray | C15: 18:00 - 18:15 | D15: Maghrib Pray(In-Vehicle)
B16: Dining | C16: 18:15 - 19:30 | D16: Dinner (Gil Medical Center – VIP Ward) | H16: 식사 가능 여부 확인 필요 병원식 vs 외부식 선호 조사 필요
B17: Pray | C17: 19:30 - 19:45 | D17: Isha Pray(In-Vehicle)
B18: Rest | C18: 19:45 - | D18: Evening rest | H18: 다음날 대장내시경 관련 준비 안내 필요

Sheet Day3(Mar.12)_Internal
A1: Day 3. March 12 Precision Health Assessment — Part II Hospital VIP Medical Center ※ Examination schedules and prayer times will be arranged flexibly
A4: Date | B4: Category | C4: Time | D4: Activity | E4: Partner Company | F4: Transport | G4: Status | H4: Notes
A5: Day 3 March 12, 2026 | C5: Morning - Afternoon
C9: Evening

Sheet Day4(Mar.13)_Internal
A1: Day 4. March 13 Precision Health Assessment — Part III Hospital → Signiel Seoul ※ Examination schedules and prayer times will be arranged flexibly
A4: Date | B4: Category | C4: Time | D4: Activity | E4: Partner Company | F4: Transport | G4: Status | H4: Notes
A5: Day 4 March 13, 2026 | C5: Morning - Afternoon
C9: Evening

Sheet Day5(Mar.14)_Internal
A1: Day 5. March 14 Style Consulting & Shopping Experience Personal Styling & Curated Shopping Tour
A4: Date | B4: Category | C4: Time | D4: Activity | E4: Partner Company | F4: Transport | G4: Status | H4: Notes
A5: Day 5 March 14, 2026 | C5: Morning
B6: Pray | C6: 06:00 - 06:15 | D6: Fajr Pray(Hotel) | H6: 정확한 기도 시간 확인 기도 방향(Qibla) 파악 기도 매트 준비
B7: Dining | C7: 06:15 - 08:00 | D7: Breakfast(Hotel Restaurant) | H7: 조식 이용 여부 사전 파악 필요 호텔 레스토랑 메뉴 적합 여부 사전 확인
B8: Transfer | C8: 08:00 - 10:00 | D8: Hotel -> Styling Venue | E8: NOBLE KLASSE 070-5210-7678 vipriding@kcmotors.co.kr | F8: SOLATI S11 (할랄 인증 리무진) | G8: Planned | H8: 차량 대기 및 이동 동선 확인 픽업, 하차 위치 사전 확인 교통 상황 사전 체크
B9: Style Consulting | C9: 10:00 - 12:00 | D9: Personal Styling Consultation(Styling Venue) Premium image consulting (hair, makeup, fashion) | E9: Rarelee 070-8019-3318 contact@rarelee.co.kr | G9: Planned | H9: 상담 범위 및 소요 시간 재확인
C11: Afternoon
B12: Transfer | C12: 12:00 - 12:30 | D12: Styling Venue -> Restaurant | E12: NOBLE KLASSE | F12: SOLATI S11 (할랄 인증 리무진) | H12: 차량 대기 및 이동 동선 확인 픽업, 하차 위치 사전 확인 교통 상황 사전 체크
B13: Pray | C13: 12:30 - 12:45 | D13: Dhuhr Pray(In-Vehicle) | H13: 정확한 기도 시간 확인
B14: Dining | C14: 12:45 - 14:00 | D14: Lunch(Restaurant) | G14: TBD | H14: 식당 예약 확인 핳랄/식단 적합성 최종 확인 혼잡 시간대 체크
B15: Transfer | C15: 14:00 - 14:30 | D15: Restaurant -> Shopping Venue | E15: NOBLE KLASSE | F15: SOLATI S11 (할랄 인증 리무진)
B16: Shopping Tour | C16: 14:30 - 16:00 | D16: Stylist-accompanied Shopping Tour(Shopping Venue) Outfit recommendations at selected stores | E16: K Look 02-3478-4131 | G16: Planned | H16: 쇼핑 투어 일정 재확인
B17: Pray | C17: 16:00 - 16:15 | D17: Asr Pray(In-Vehicle) | H17: 정확한 기도 시간 확인
B18: Transfer | C18: 16:15 - 16:45 | D18: Shopping Venue -> KUMKANG Optical | E18: NOBLE KLASSE | F18: SOLATI S11 (할랄 인증 리무진) | H18: 차량 대기 및 이동 동선 확인 / 교통 상황 사전 체크
B19: Shopping | C19: 16:45 - 18:00 | D19: Eye Examination & Luxury Eyewear Fitting(KUMKANG Optical) Premium optical store | E19: KUMKANG Optical | G19: Planned
A22: Date | B22: Category | C22: Time | D22: Activity | E22: Partner Company | F22: Transport | G22: Status | H22: Notes
A23: Day 5 March 14, 2026 | C23: Evening
B24: Pray | C24: 18:00 - 18:15 | D24: Maghrib Pray(In-Vehicle) | H24: 정확한 기도 시간 확인
B25: Transfer | C25: 18:15 - 18:30 | D25: KUMKANG Optical ->Olive Young | E25: NOBLE KLASSE | F25: SOLATI S11 (할랄 인증 리무진) | H25: 차량 대기 및 이동 동선 확인 픽업, 하차 위치 사전 확인 교통 상황 사전 체크
B26: Shopping | C26: 18:30 - 19:30 | D26: K-Beauty Shopping Experience(Olive Young) Curated selection of cosmetics and beauty products | F26: Olive Young | H26: 매장 혼잡도 확인
B27: Pray | C27: 19:30 - 19:45 | D27: Isha Pray(In-Vehicle) | H27: 정확한 기도 시간 확인
B28: Transfer | C28: 19:45 - 20:00 | D28: Olive Young ->Restaurant | E28: NOBLE KLASSE | F28: SOLATI S11 (할랄 인증 리무진) | H28: 차량 대기 및 이동 동선 확인 픽업, 하차 위치 사전 확인 교통 상황 사전 체크
B29: Dining | C29: 20:00 - 22:00 | D29: Dinner(Restaurant) | G29: TBD | H29: 식당 예약 확인
B30: Transfer | C30: 22:00 - 22:30 | D30: Restaurant -> Hotel | E30: NOBLE KLASSE | F30: SOLATI S11 (할랄 인증 리무진) | H30: 차량 대기 및 이동 동선 확인 픽업, 하차 위치 사전 확인 교통 상황 사전 체크
B31: Rest | C31: 22:30 - | D31: Evening rest

Sheet Day6(Mar.15)_Internal
A1: Day 6. March 15 Comprehensive Skin Rejuvenation Premium Aesthetics Clinic in Seoul ※ Treatment schedules and prayer times will be arranged flexibly
A4: Date | B4: Category | C4: Time | D4: Activity | E4: Partner Company | F4: Transport | G4: Status | H4: Notes
A5: Day 6 March 15, 2026 | C5: Morning - Afternoon
C9: Evening

Sheet Day7(Mar.16)_Internal
A1: Day 7. March 16 Leisure & Recovery Signiel Spa & Lotte World
A4: Date | B4: Category | C4: Time | D4: Activity | E4: Partner Company | F4: Transport | G4: Status | H4: Notes
A5: Day 7 March 16, 2026 | C5: Morning
C11: Afternoon
C19: Evening

Sheet Day8(Mar.17)_Internal
A1: Day 8. March 17 Heritage & History DMZ(Demilitarized Zone) & NLL(Northern Limit Line) ※ Conducted by professional tour operator with English-speaking guide ※ Prayer times arranged flexibly during tour
A4: Date | B4: Category | C4: Time | D4: Activity | E4: Partner Company | F4: Transport | G4: Status | H4: Notes
A5: Day 8 March 17, 2026 | C5: Morning
C11: Afternoon
C19: Evening

Sheet Day9(Mar.18)_Internal
A1: Day 9. March 18 Stem Cell Lifting Treatment Premium Aesthetics Clinic in Seoul ※ Treatment schedules and prayer times will be arranged flexibly
A4: Date | B4: Category | C4: Time | D4: Activity | E4: Partner Company | F4: Transport | G4: Status | H4: Notes
A5: Day 9 March 18, 2026 | C5: Morning
C11: Afternoon
C19: Evening

Sheet Day10(Mar.19)_Internal
A1: Day 10. March 19 Final Wellness & Farewell Spa -> Incheon International Airport
A4: Date | B4: Category | C4: Time | D4: Activity | E4: Partner Company | F4: Transport | G4: Status | H4: Notes
A5: Day 10 March 19, 2026 | C5: Morning
C11: Afternoon
C19: Evening

Sheet 1. K-Medical
A1: K-Medical for Muslim VIP K-BMW Premium Tour
A4: Premium Check-up Package | I4: Information
A5: Package | B5: Partners | C5: Grade | D5: Selection Sheet Grade | E5: Quotation | G5: Time Taken | H5: Check-up Detail
E6: 1,000 KRW | F6: USD
A7: K-Medical Check-up | B7: Gil Hospital International Healthcare Center 032-460-3213 010-6272-9567 Incheon Namdon-gu | C7: Premium | D7: Gold | E7: M : 7,800 F : 8,100 | G7: 1 day | H7: * Heart & Brain Premium + Additional Tests * An advanced program developed for early detection of cancer and cardio-cerebrovascular diseases, carefully tailored to each individual's medical history and needs * Recommended for ages 50+ | I7: https://www.gilhospital.com/en_US/web/foreigner/medical-health-check-up
C8: VIP Premium | D8: Diamond | E8: M : 10,600 F : 10,900 | G8: 1 day | H8: * Heart & Brain Premium + Additional Tests * A premium all-in-one screening program offering a comprehensive health evaluation * Recommended for ages 50+
B9: SNUH healthcare System Gangnam Center's International Clnic 02-2112-5601 Seoul Seocho-gu | C9: Standard | D9: Silver | F9: M : 990 F : 1,110 | G9: 1 day | H9: Common : Fundus Photography ❖Age ≥50: including Audiometry, excluding Hepatitis A M : Prostate Tumor Marker F : Gynecologic Examination & Consultation, Ovarian Tumor Marker, Cervical Cytologic Test(PAP Smear), Mammography | I9: http://en-healthcare.snuh.org
C10: Premium | D10: Gold | F10: M : 5,870 F : 6,383 | G10: 1 day | H10: Standard Program + Premium Medical Consultation, Nutrition Guidance, Dental Exam/X-ray, Audiometry, Thyroid Ultrasonography, Urine(Microalbuminuria), Blood[Rheumatoid Factor, Allergy(108kinds), Detailed Lipid Panel, Serum Pepsinogen, Vit. D, Blood Coagulation], Cardiovascular(Treadmill Test, Echocardiography, Arterial Stiffness, Carotid Ultrasonography), Pulmonary(Low Dose Chest CT, Otorhinolaryngoscopy), Gastrointestinal(Abdominal-pelvic CT, Sedative Colonoscopy), Brain MRI/MRA(Including Carotid Artery)
B11: The Catholic University of Korea Seoul St. MARY'S Hospital 02-1588-8668 Seoul Seocho-gu | C11: Basic Intensive | D11: Gold | E11: M : 2,210 F : 2,600 | G11: 1 day | H11: Includes International Basic + Thyroid Ultrasonography / Pelvic Ultrasonography Breast Ultrasonography / Low dose Chest CT HPV(Human Papilloma Virus) / Bone densitometry / Vitamin D Female hormones(LH, FSH, Estradiol, Prolactin) Detailed blood test for anemia / Tumor marker(Breast) | I11: https://healthcare.cmcseoul.or.kr/en/personal/sub01_01.do
C12: Premium S | D12: Gold | E12: M : 5,910 F : 6,510 | G12: 1 day | H12: Includes International Basic + Pre-medical consultation / Brain MRI·MRA, Colonoscopy under conscious sedation Thyroid Ultrasonography / Carotid Ultrasonography Echocardiography / Coronary artery 3D CT / Low dose Chest CT Abdomen & Pelvic CT / Pulse wave velocity measurement Bone densitometry / Vitamin D Tumor marker(Lung, Bladder, Peripheral blood smear) Detailed Blood test, Allergy test, Physical fitness assessmen
C13: Premium P | D13: Diamond | E13: M : 7,260 F : 7,890 | G13: 1 day | H13: Includes International Marian S + Optical CT(Retina / Glaucoma) Detailed Blood test(Parathyroid hormone, Factor of Arteriosclerosis) Tumor marker(Thyroid) Detailed Urine exam(Microalbumin, Creatinine, Total protein)
A17: Premium Check-up Package | I17: Information
A18: Package | B18: Partners | C18: Grade | D18: Selection Sheet Grade | E18: Quotation | G18: Time Taken | H18: Check-up Detail
E19: 1,000 KRW | F19: USD
A20: K-Medical Check-up | B20: Asan Medical Center 02-3010-5005 Seoul Songpa-gu | C20: Essential | D20: Silver | E20: M : 1,800 F : 2,600 | G20: 1 day | H20: •Gastroscopy Under Conscious Sedation •Abdominal Ultrasonography •Blood Pressure •Electrocardiogram •Chest X-ray (Front/Lateral) •Ophthalmic Exam •Urine Test •Audiometry Test •Body Measurement •Dental Assessment •Result Consultation with a Specialist • Blood Sampling (Diabetes, Hypercholesteremia, Liver Function, Hepatitis A/B/C, Kidney Function, Electrolyte, Uric Acid, Complete Blood Count, Blood Coagulation Test, Blood Type, Inflammation, Thyroid Function, Helicobacter Pylori, Infection(AIDS), Syphilis, Rheumatoid Factor) •Cancer Marker(Liver, Lung, Digestive Organ) | I20: https://eng.amc.seoul.kr/gb/lang/specialities/centers.do?hpCd=D053
C21: Platinum | D21: Gold | E21: M : 7,300 F : 7,720 | G21: 1 day | H21: Extensive and Detailed Check-up Program Including Cancer & Heart Program and Brain MR Male Essential + •Brain MRA & MRI •Abdominal & Pelvic CT •Coronary CT •Echocardiography •Treadmill Test •Arterial Stiffness and Peripheral Artery Stenosis •Dental X-ray •Blood Test(Heart function, 3 types of Allergy, 3 types of Osteoporosis, 3 types of Anemia) •Prostate Ultrasonography & Digital Rectal Examination •Thyroid Ultrasonography, Female : •Chest CT •Carotid Ultrasonography
C22: Premium | D22: Diamond | E22: M : 8,430 F : 8,990 (2월 단가 조정 예정) 10-30% 인상 예정 | G22: 1 day | H22: The Most Comprehensive and Intensive Check-up Program, Performed Over 2 Days and 1 Night While Staying in a Comfortable Room, Includes Platinum Program and Brain MR with Care by Specialized Medical Staffs. • Assessment by a Specialist •Escorted by a Nurse •Provided Meals •Brain MRI+MRA • Gastroscopy with Conscious sedation •Colonoscopy with Conscious sedation • Abdominal Ultrasonography • Carotid Ultrasonography •Abdominal & Pelvic CT •Chest CT •Coronary CT •Thyroid Ultrasonography •Echocardiography •Treadmill Test • Arterial Stiffness and Peripheral Artery Stenosis •Electrocardiogram •Blood Pressure •Chest X-ray (Front/Lateral) •Bone Densitometry •T-L Spine X-ray •Body Measurement •Dental X-ray •Dental Assessment •Ophthalmic Exam •Urine Test •Urine Cytology •Audiometry Test •Blood Sampling (Diabetes, Hypercholesteremia, Liver Function, Heart Function, 3 Types of Allergy, 3 Types of Osteoporosis, Hepatitis A/B/C, Kidney Function, Electrolyte, Uric Acid, Complete Blood Count, Blood Coagulation Test, Blood Type, Inflammation, Thyroid Function, 3 Types of Anemia, AIDS, Syphilis, Helicobacter Pylori) •Cancer Marker(Liver, Lung, Digestive Organ) •Result Consultation with a Specialist Male :•Prostate Ultrasonography & Digital Rectal Examination •Testosterone •Cancer Marker(Prostate) Female : •Pelvic Ultrasonography •Pap Smear •Breast Ultrasonography •Mammography •HPV(Human Papilloma Virus) •Cancer Marker(Ovary)

Sheet 2. K-Beauty
A1: K-Beauty for Muslim VIP K-BMW Premium Tour
A4: Premium K-beauty Package | J4: Information
A5: Package | B5: Partners | C5: Program Course & Grade | E5: Selection Sheet Grade | F5: Quotation | H5: Time Taken | I5: Clinic Detail
F6: 1,000 KRW | G6: USD
A7: K-Beauty (Medical) Private Wellness Experience | B7: Salon de Dr.Tune's Clinic | C7: Signiture Program | D7: Salon de Juvénile | I7: Salon de Juvénile is the VVIP stem cell center at Salon de Dr.Tune’s, offering an exclusive private regenerative program that rejuvenates not only the skin but your entire body. Moving beyond simple treatments, our program is built on precise stem-cell-based solutions that address the root causes of aging, helping you preserve firm, radiant skin and enhance your overall wellness.
D8: Salon de All-Layer | I8: Salon de All-Layer is our specialized lifting and tightening center, dedicated to refining your natural beauty by precisely treating every layer of the skin — from the surface to the deep muscle tissue. Beyond superficial improvements, we perform a comprehensive, multi-layer analysis of your skin’s structure to deliver a fully personalized solution. This approach restores harmonious balance to your facial volume, elasticity, and texture.
D9: Salon de Sportif | I9: Salon de Sportif is a specialized total body conditioning center for professional athletes needing pre/post-game care, and for individuals seeking recovery after physical activities such as tennis and golf. We provide personalized care designed to maximize athletic performance, including rapid post-workout recovery, muscle fatigue relief, and body contour refinement. Our tailored solutions encompass everything from pre- and post-competition care for athletes, diet management, postpartum recovery, to body contouring.
C10: Package | D10: Glow Package | G10: 6666.67 | H10: 120m | I10: Ultherapy 400 shots + Sofwave 300 pulses + Eye Thermage 450 shots + Premium Rejuran Glow Toxin + Premium Skin Care Treatment
D11: Premium Anti-Aging Package | G11: 13333.33 | H11: 180m | I11: Stem Cell IV Therapy + Ultherapy 400 shots + Sofwave 300 pulses + Eye Thermage 450 shots + Titanium or BBL Hero + Premium Rejuran Glow Toxin + Premium Skin Care Treatment
D12: Premium Stem Cell Anti-Aging Package | G12: 20000 | H12: 180m | I12: Activated Stem Cell IV Therapy + Stem Cell Facial Treatment + Ultherapy 600 shots + Sofwave 300 pulses + Titanium or BBL Hero + Premium Skin Care Treatment
D13: Premiun Body Package | G13: 33333.33 | H13: 480m | I13: Ultherapy Prime 3,000 shots (Abdomen, Arms, Thighs) + Sofwave 1,500 pulses (Abdomen, Arms, Thighs) + Full Body BBL HERO + Manual Body Treatment + Hyperbaric Oxygen Therapy + Stem Cell IV Therapy + Premium Skin Care Treatment
A16: Premium K-beauty Package | J16: Information
A17: Package | B17: Partners | C17: Program Course & Grade | E17: Selection Sheet Grade | F17: Quotation | H17: Time Taken | I17: Clinic Detail
F18: 1,000 KRW | G18: USD
A19: K-Beauty (Medical) Private Wellness Experience | B19: Nest Clinic GangNam (=A Clinic) 02-532-2867 Seoul Seocho-gu | C19: stem cell program | D19: Special - 1 | F19: - | H19: 60m | I19: Blood Stem Cell Full Face + Premium SkinCeuticals Antioxidant Care | J19: https://nest-clinic.com/ The entire clinic can be rented depending on the number of VIP customers and schedule.
D20: Special - 2 | F20: - | H20: 120m | I20: Blood Stem Cell Full Face + Stem cell intravenous injection + Premium SkinCeuticals Antioxidant Care
D21: Basic | F21: 5,000 / 10,000 / 15,000 | H21: 120m | I21: S-1 or S-2 + Basic : 1 vial Sculptra or Juvederm Filler 3cc (No restrictions on body part) + Premium SkinCeuticals Antioxidant Care
D22: Gold | F22: 10,000 / 15,000 / 20,000 | H22: 120m | I22: S-1 or S-2 + Gold : Rejuran HB 4cc + Full Face Skin Botox + Thermage FLX 900 Shot(Face+Neck) + 1 vial Sculptra (No restrictions on body part) + Premium SkinCeuticals Antioxidant Care
D23: Platinum | F23: 15,000 / 20,000 / 25,000 | H23: 180m | I23: S-1 or S-2 + Platinum : Rejuran HB 4cc + Full Face Skin Botox + Ultherapy HIFU Prime 600 shot + Thermage FLX 900 Shot(Face+Neck) + Premium SkinCeuticals Antioxidant Care + Premium SkinCeuticals(55ml) Ampoule giveaway
C24: Dermatological procedures | F24: 4000 | H24: 150m | I24: 울쎄라피프라임 300샷+써마지FLX 600샷+프리미엄 스킨수티컬즈 항산화 관리
F25: 6000 | H25: 180m | I25: 써마지FLX 600샷 + 아이써마지 450샷+아이리쥬란 2cc+ 풀페이스 리쥬란힐러 4cc+항산화 스킨수티컬즈 관리
F26: 8000 | H26: 240m | I26: 울쎄라피프라임 600샷 + 써마지FLX 600샷 +풀페이스 리쥬란 HB 4cc+항산화 스킨수티컬즈 관리
C27: Full Body Package | F27: 5000 | H27: 180m | I27: [Antiaging+Collagen Volumizing] 바디써마지 FLX 600샷+바디 스컬트라 2vial+프리미엄 메디컬 케어
F28: 8000 | H28: 150m | I28: [Slimming, Antiaging] 바디써마지FLX 1200샷(총 2부위까지 선택 가능)+ 바디슬리밍 브이올렛 2vial+프리미엄 메디컬 케어
F29: 15000 | H29: 270m | I29: [Slimming, Total Antiaging] 바디써마지FLX 3000샷(총 5부위까지 선택 가능)+바디슬리밍 브이올렛 6vial+손등주름 래디어스 2syringe+프리미엄 메디컬 케어
B30: SELENA Clinic Hongdae (=B Clinic) 50713108808 Seoul Mapo-gu | C30: Dermatological procedures | D30: Royal Refresh Day (Face only, no injection) | F30: 5000 | H30: 180m | I30: Ultherapy Prime 600 shots, Thermage 600 shots, Eye Thermage 225 shots, LDM therapy (12 minutes), Radio-Frequency facial care, 24K Gold Therapy, Regenerative LED treatment | J30: https://selenaskin.com/en
D31: Royal Signature Lifting (Including neck & fatigue recovery) | F31: 10000 | H31: 240m | I31: Ultherapy Prime 600 shots, Ultherapy Prime 200 shots (Neck), Eye Ultherapy Prime 200 shots Thermage 600 shots, Volumer 200 shots (Neck), Eye Thermage 225 shots, Titanium 100 kJ Pico Toning, Rejuran Healer 4cc, Rejuran Eye 2cc, Juvelook Skin 4cc, Mega Complex Vitamin IV Therapy, Premium Nutrition IV Therapy, RejuDM Premium Care(24K Gold therapy+Cryo therapy+LDM Rejuran Skin Booster(2 vials)+LED light therapy+Modeling pack) Radio-Frequency facial & neck care
D32: Royal Face & Body Refinement (Royal Hospital Takeover) | F32: 15000 | H32: 540m | I32: Ultherapy Prime 600 shots, Ultherapy Prime 200 shots (Neck), Eye Ultherapy Prime 200 shots Thermage 600 shots, Volumer 200 shots (Neck), Eye Thermage 225 shots, Titanium 100 kJ Pico Dual Toning, Rejuran Healer 4cc, Rejuran Eye 2cc, Juvelook Skin 4cc Mega Complex Vitamin IV Therapy, Premium Nutrition IV Therapy RejuDM Premium Care(24K Gold therapy+Cryo therapy+ LDM Rejuran Skin Booster(2 vials)+LED light therapy+Modeling pack) Radio-Frequency facial & neck care, Ultrasound facial & neck care
A35: Premium K-beauty Package | J35: Information
A36: Package | B36: Partners | C36: Program Course & Grade | E36: Selection Sheet Grade | F36: Quotation | H36: Time Taken | I36: Clinic Detail
F37: 1,000 KRW | G37: USD
A38: K-Beauty (Non-Medical) Private Wellness Experience | B38: SPA the belec (Primium Skincure & Spa) Incheon Songdo | C38: Body therapy | D38: Mix | E38: Silver | F38: 297 | H38: 100m | I38: Basci Face + Body efficient care | J38: instagram : @_thebelec
D39: Spa | E39: Silver | F39: 363 | H39: 120m | I39: Head to Foot Full Line (Body Care managed with spa-specific technology)
D40: Medi Course | E40: Diamond (Premium) | F40: 425 | H40: 120m | I40: Belec Line 2 or 3-Body Care (Restore your body's balance by controlling the device's temperature and pressure)
E41: Diamond (Premium) | F41: 473 | H41: 120m | I41: Medi Slimming 2 or 3-Body Care(Body Slimming Care that selectively breaks down only the fat layer using ultrasound)
D42: Special Course | E42: Gold | F42: 393 | H42: 120m | I42: Elimination of active oxygen and waste products from the skin, A treatment that helps to organize lymph and body lines and relieve swelling
B43: Retreat SIGNIEL SPA 02-3213-1383 Gangnam Songpa-gu | C43: Body therapy | D43: Contour Whole Body Program | E43: Gold | F43: 670 | H43: 150m | I43: Full-body detox combined with a V-line facial | J43: https://www.lottehotel.com/seoul-signiel/en/facilities/retreat-signiel
D44: Diamond Détente | E44: Gold | F44: 680 | H44: 150m | I44: Luxurious full-body treatment with diamond powder and pearl extract
D45: Timeless Away Journey | E45: Diamond (Premium) | F45: 750 | H45: 180m | I45: Restorative body ritual with coffee scrub and baobab oil
D46: Chocolate Whole Body | E46: Diamond (Premium) | F46: 1500 | H46: 240m | I46: The world's first premuim full-body chocolate therapy
B47: Four Seasons Hotel SPA 02- 6388-5000 Seoul Jongru-gu | C47: Body therapy | D47: Serenity with Thermo-Stones | E47: Gold | F47: 340 | H47: 90m | I47: A divinely healing treatment, aches and body tension dissipate as stones are warmed and moved along the body. This is a medium to deep-pressure treatment, ideal for general fatigue or following a long-haul flight. Feel your energy levels return like magic. | J47: https://www.fourseasons.com/seoul/spa/
D48: Bespoke Therapeutic | E48: Silver | F48: 320 | H48: 90m | I48: levate your relaxation with a luxurious Aromatherapy experience, enriched with Zents' mindful oils. Immerse yourself in the healing scents of mandarin, oolong, ore, or sun oils and experience a profound sense of restorative calm.
D49: Revitalize with K-Wellness | E49: Silver | F49: 260 | H49: 60m | I49: Experience the rejuvenating power of our Korean-inspired therapy, combining deep tissue, reflexology, and stretching to release tension, promote energy flow, and leave you feeling revitalized. Perfect for relieving tightness and fatigue.
D50: Mandarin Deep Tissue | E50: Gold | F50: 330 | H50: 90m | I50: For areas that need some remedial attention, this medium to strong treatment uses deep tissue techniques to reach deeper into problem areas and help disperse tension, leaving your body feeling more at ease than ever.
C51: Signature treatments | D51: Seoul’s Luxurious Renewal Journey | E51: Diamond (Premium) | F51: 530 | H51: 150m | I51: Experience a modern take on Korea’s historic treatment. Begin with a scrub blending traditional and modern techniques, followed by a seaweed detox and herbal wash. Finish with restorative body therapy and a rejuvenating collagen mask, leaving you refreshed and revitalized. | J51: https://www.fourseasons.com/seoul/spa/
D52: Romantic Retreat | E52: Gold | F52: 530 | H52: 150m | I52: Step into a light-filled spa suite and unwind in a warm couples’ bath with epsom salt and arnica. A Zents scrub and body therapy melt away tension, followed by a Sodashi mini-facial for fragrant hydration. A beautifully restorative escape for two.
D53: Wellness Balancing Treatment (Premium Upgrade) | E53: Silver | F53: 530 | H53: 120m | I53: Target weariness with our warm volcanic stone treatment, followed by a calming therapy to ease tension and help your body recover from travel or a busy day. Finish with a soothing facial to calm the effects of sun, wind, and stress on your skin.
C54: Facial collection | D54: Revolutionize with Second Skin | E54: Diamond (Premium) | F54: 560 | H54: 75m | I54: Experience the revolutionary facial treatment Second Skin, brought to you by Biologique Recherche. The non-invasive treatment utilizes five electrospun masks, each infused with 80% hyaluronic acid and a regenerating serum, to target damaged skin instantly, with no downtime. | J54: https://www.fourseasons.com/seoul/spa/
D55: Bespoke Bliss for Radiant Skin | E55: Gold | F55: 450 | H55: 90m | I55: Using the Biologique Recherche Methodology to analyze and diagnose your skin, this revitalizing facial includes a reshaping treatment to promote firmer, more contoured skin. Our active skincare products restore your natural pH, increase hydration and improve texture, leaving you radiant and energized.
D56: MediSpa Pro | E56: Silver | F56: 410 | H56: 90m | I56: Experience a transformative 90-minute facial with the Ceragem MediSpa Pro. Combining advanced technology, it rejuvenates, deeply cleanses, and hydrates the skin. Using high-frequency vibration, thermal therapy, and infrared light, it enhances circulation, boosts collagen, and reduces fine lines for a youthful glow.
A59: Premium K-beauty Package | J59: Information
A60: Package | B60: Partners | C60: Program Course & Grade | E60: Selection Sheet Grade | F60: Quotation | H60: Time Taken | I60: Clinic Detail
F61: 1,000 KRW | G61: USD
A62: K-Beauty (Non-Medical) Private Wellness Experience | B62: SONAEGRIM Contact via Instagram Seoul Dongdaemun-gu | C62: Henna | I62: Traditional Indian henna art created using natural henna dye. The design remains on the skin temporarily and fades naturally over time. | J62: https://www.instagram.com/p/DCasO3iT-0H/?img_index=1
B63: MEHNDIHENNA 0507-1368-1058 Busan | I63: Traditional Indian henna art created using natural henna dye. The design remains on the skin temporarily and fades naturally over time. 출장가능 | J63: https://blog.naver.com/people_d https://www.instagram.com/mehndihenna.studio/
B64: ECO JARDIN 010-2947-1144 k.official@ecojardin.co.kr Seoul Songpa-gu / Mapo-gu | C64: scalp treatment | F64: 250 | I64: A premium scalp care program at Eco Jardin, providing deep cleansing and revitalization of the scalp through delicate care by experienced professionals. The program includes consultation, diagnosis, scalp treatment, and styling. | J64: https://ecojardin.co.kr/kr/spa

Sheet 3-1. K-Wellness_Shopping
A1: K-Wellness_Shopping for Muslim VIP K-BMW Premium Tour
A4: K-Wellness Package | I4: Information
A5: Package | B5: Sub Package | C5: Partners | D5: Course Program & Grade | E5: Quotation | G5: Time Taken | H5: Package Detail
E6: 1,000 KRW | F6: USD
A7: K-Wellness (Shopping) | B7: festival | C7: Korea Grand Sale 070-8789-5600 070-8789-5700 kgs2026.info@gmail.com Seoul Jongru-gu | D7: nations's premier festival for shopping, culture, tourism | E7: No fixed Price | H7: 25.12.17 ~ 26.02.22 진행 웰컴 쿠폰북 제공, K-테마존 체험, 포토존&럭키드로우 A 감정 분석을 통한 쇼핑 추천, K 쇼핑카트 채우기 항공·교통, 쇼핑, 숙박, 식·음료, 뷰티, 건강, 체험, 편의서비스 등 | I7: https://www.koreagrandsale.co.kr/main
B8: K-GLASSES | C8: KUMKANG OPTICAL 도곡 점 : 02-6243-1001 삼성병원 점 : 02-2226-7007 압구정 점 : 02-549-6006 킨텍스 점 : 031-822-2959 판교 점 : 031-5170-3812 천호 점 : 02-2225-7476 고속터미널 점 : 02-3479-1619 압구정로데오 점 : 02-543-1634 광교 점 : 031-5174-7210 여의도 점 : 02-3277-0317 명동 점 : 02-310-1547 잠실 점 : 02-3213-2319 아루네띠(명동) : 02-310-1573 | E8: No Fixed Price | H8: 국내 최대 규모의 린드버그 딜러. 해외 명품 브랜드 안경을 취급하는 프리미엄 안경원. 최첨단 검안 시스템과 초정밀 3D 검사 장비 자체적인 교육 시스템으로 수준 높은 검안 기술과 피팅 시스템을 갖춘 전문 안경사 | I8: https://kumkangoptical.com/
B9: Cosmetics & Beauty Products | C9: OLIVE YOUNG 올리브영N 성수: 02-497-6589 올리브영 강남 타운: 02-532-7444 올리브영 명동타운: 02-736-5290 | E9: No Fixed Price | H9: 국내 최초의 헬스&뷰티 스토어 | I9: https://corp.oliveyoung.com/ko
B10: Stationery | C10: ART BOX 부천역점: 0507-1483-6015 성신여대점: 0507-1483-6015 명동길점: 0507-1445-0819 | E10: No Fixed Price | H10: 단순한 학용품의 생산/판매에 머물러 있던 문구산업을 디자인 중심의 팬시사업으로 전환시킨 국내 최초의 문구 팬시 전문 브랜드 | I10: https://recruit.artbox.kr/m/

Sheet 3-2. K-Wellness_K-Content
A1: K-Wellness_K-Content for Muslim VIP K-BMW Premium Tour
A4: K-Wellness Package | J4: Information
A5: Package | B5: Sub Package | C5: Partners | D5: Course Program & Grade | F5: Quotation | H5: Time Taken | I5: Package Detail
F6: 1,000 KRW | G6: USD
A7: K-Wellness (K-CONTENT) | B7: Tour | C7: Life World tour 010 7711 0774 02 1688 5632 bulgom@lifeworldtour.com | D7: K-POP demon Hunters Tour | F7: 860 / 1T | H7: 1 day | I7: 최소 인원: 2인(최대 인원 6-7인) 경복궁 → 북촌/서촌 → 명동 → 점심식사 → N서울타워 → VAN 엔터테인먼트(DIY 워크숍) → 낙산공원 → 기념품 쇼핑 # 서울도심 #K-POP콘텐츠 #K-POP Demon Hunters #몰입형체험 #미션형투어 #XR/AR #식사개인부담 #활동량중상 #기본투어패키지(밴1대) + 영어가이드 + 전문사진작가 + 점심식사 | J7: https://lifeworldtour.co.kr/18/?idx=34
C8: Korea Trevel Easy 010-7574-6474 info@koreatraveleasy.com | D8: K-POP Concert Tour | E8: SBS Inkigayo KPOP Show Ticket Package (Every Sunday) | G8: 240 / 1P | H8: 1 day | I8: * Entrance Ticket to Live Taping of SBS Inkigayo at SBS Public Hall * Walking Tour (Different itinerary every month) * Transportation to the SBS Public Hall from the walking tour Place #서울도심 #K-POP방송체험 #워킹투어 #하이커그라운드 #SBSInkigayo #외국인전용 #식사개인부담 #활동량중 | J8: https://www.koreatraveleasy.com/product /sbs-inkigayo-k-pop-concert-music-show-ticket-package/
C9: eTour 02-323-6850 | D9: K-Drama Tour Incheon, Seoul | E9: Descendants of the Sun / Guardian / My Love From the Star Filming Locations | G9: 103-233 / 1P | H9: 1 day | I9: Songdo Dalkomm coffee(Descendants of the Sun, Guardian) -> Songdo Central park -> lunch(BBQ / Guardian) -> Deoksugung(Guardian) -> hakrim coffee(My Love From the Star) -> N- seoul tower(My Love From the Star) #서울·송도 #K-드라마촬영지(태양의 후예, 도깨비 별에서 온 그대) #카페·먹거리체험 #포토미션 #가이드동행 #중식포함 #활동량중 | J9: https://fi.koreaetour.com/tuote/Korean-draaman-yksityinen-kiertue/
D10: K-Drama Tour Jeju | E10: Welcome to Samdal-ri / Woo young Woo / When life gives you tangerines Filming Locations | G10: 402 / 1T | H10: 1 day | I10: A: Gwaneumsa Temple, Secret Forest Andol-oreum, Micheon Cave, Gwangchigi Beach, Seongsan ilchulbong, Ojo pogu, Seongiwpean Bakery B: Dodubong Peak, Rainbow coastal Road, Iho tewoo horese lighthouses, Myeongwol Elementary School, Shinchang Windmill Coastal Road, Yeongrak-ri Coastal Road+Sindo Part, Changwido Natural Preserve #제주도 #K-드라마촬영지(웰컴투 삼달리, 런닝맨, 이상한 변호사 우영우) #자연·섬여행 #차량이동중심 #가이드동행 #식사개인부담 #활동량중 | J10: https://www.kkday.com/en-au/product/164626
C11: GET YOUR GUIDE | D11: K-Film Tour Incheon | E11: Incheon: Squid Game Tour | F11: 231 / 1P | H11: 1 day | I11: * Visit Gyodong Elementary, a real Squid Game filming site * Play on-screen challenges: dalgona carving & punch machine * Taste the retro “lunchbox” meal seen on screen * Sea-view monorail loop and Archery café target session with coastal Wolmi vibes * Songdo Central Park mission game + hotel pickup/drop-off #인천·송도 #오징어게임촬영지 #콘텐츠체험형 #미션게임 #레트로체험 #차량이동중심 #중식포함 #활동량중 | J11: https://www.getyourguide.com/ko-kr/incheon-l90654/squid-game-in-incheon-t1093485/?ranking_uuid=d4da7648-edd3-48d7-a0f5-d0063ab5ffaf
C12: K-Content AWARD CEREMONY
B13: Experience | C13: Korea Tour Tip master@koreatourtip.co.kr | D13: K-POP Experience | E13: K-POP Idol VIP Performance Experience Private One-Day Class | F13: 539 / 1P | H13: 1 day | I13: 하루 4명만 참여 가능 K-POP 아이돌 댄스 체험 + 보컬 체험 -> 점심식사(현지식) -> 아이돌 메이크업 -> 아이돌 컨셉 사진 촬영 #서울 #K-POP퍼포먼스체험 #아이돌트레이닝 #프라이빗클래스 #VIP소수정예 #사진촬영포함 #중식포함 #활동량상 | J13: https://www.koreatourtip.com/master/54126
B14: Dance | C14: DANCEJOA 010-6478-7022 https://dancejoa.com/28 | D14: K-POP Dance Lessons | E14: K-POP OneDay | F14: 200 / 2P, 1hour | H14: 120 m | I14: Lesson counseling --> Resevation --> Instructor assigment --> Lesson start Special group dance lessons tailored to your group and purpose, available in small groups #서울 #K-댄스클래스 #프라이빗레슨 #댄스조아 #원데이클래 #안무완성 #활동량상 | J14: https://dancejoa.com/34
A17: K-Wellness Package | J17: Information
A18: Package | B18: Sub Package | C18: Partners | D18: Course Program & Grade | F18: Quotation | H18: Time Taken | I18: Package Detail
F19: 1,000 KRW | G19: USD
A20: K-Wellness (K-CONTENT) | B20: Beauty | C20: K Look 02-3478-4131 | D20: K-POP Fashion Tour | E20: Personal Shopping Tour with Professional K-fashion Stylist in Seoul | F20: 213 / 1P 400 / 2P | H20: 120 m | I20: One korean stylist works with One customer to help style with a popular korean fashion brand. We recommend about 6 to 7 outfits per 1 hour the final purchase is your choice. #서울도심 #K-스타일링 #퍼스널쇼핑 #스타일리스트동행 #소그룹체험 #활동량하 | J20: https://www.klook.com/ko/activity/91909-seoul-shopping-tour/
C21: Korea Trevel Easy 010-7574-6474 info@koreatraveleasy.com | D21: K-POP Styling | E21: Makeup + Hair Styling + Photoshoot | G21: 450 / 1P | H21: 240 m | I21: Experience the professional styling of K-Beauty ! Where Korean stars come to get ready for the shows! A must-visit course for travelers to Korea! The hair and makeup of K-pop stars are located in Seoul, Gangnam-gu, Cheongdam-dong, and Dosan Park! A Place close to famous luxury brands such as Supreme, Louis Vuitton, Noted, and Stussy. #서울강남·청담 #K-뷰티스타일링 #헤어·메이크업체험 #살롱체험 #사진옵션 #활동량하 | J21: https://www.koreatraveleasy.com/product/ k-beauty-makeup-hairstyling-in-gangnam-seoul/
C22: REHANNAIMAGE 031-983-3704 rehannaimagecompany@naver.com | D22: STYLE CONSULTING | E22: Master Style Consulting (I Style Consulting + Fit Style Consulting) | F22: 600 / 1P | H22: 300m | I22: I Style Consulting: Professional personal image consulting to define your ideal style, including hair, makeup, personal color, and body type analysis Fit Style Consulting: Advanced body-type fit style consulting based on data from 15,000 measurements, including in-person analysis and practical shopping guidance #서울 #스타일컨설팅 #퍼스널스타일진단 #체형분석 #스타일메뉴얼제공 #활동량하 | J22: https://www.rehannaimagecompany.co.kr/stylecounsulting
C23: Rarelee 070-8019-3318 contact@rarelee.co.kr | E23: Private Consulting | F23: ~ 8,,800 / 1P | I23: VIP Offline Service Inquiries via Email #VIP오프라인컨설팅 #프리미엄스타일컨설팅 #헤어메이크업 #패션컨설팅 #1:1맞춤분석 #시그니처스타일제안 #활동량하 #메일문의 | J23: https://rarelee.co.kr/category/9/premium-consulting
C24: Merizzbeauty merizzbeauty@gmail.com | E24: VIP Offline Consulting | F24: 2,200 / 1P | I24: Inquiries via KakaoTalk Channel * Beauty Consultant * Fashion Consultant * Hair Consultant * Makeup consultant #VIP오프라인컨설팅 #프라이빗컨설팅 #스타일리스트팀#뷰티컨설팅 #패션컨설팅 #헤어컨설팅 #메이크업컨설팅 #활동량하 #카톡문의 | J24: https://merizzbeauty.com/shop_view/?idx=194
C25: COLOR PLACE 02-3443-5461 colorplace@colorplace.co.kr | D25: Personal Color Diagnosis | E25: Master Premium | F25: 400 / 1P | H25: 150 m | I25: 컬러 드레이핑 세부톤 총 25type 진단 + 색조 메이크업 제품 추천 + 패션 스타일 체크&패션 스타일링 추천 + 악세서리, 향수 추천, 안경, 렌즈, 네일 디자인&컬러 추천 + 골격 및 체형 진단에 맞는 전략적 패션 코칭 + 시그니처 이미지 컨설팅 #퍼스널컬러진단 #사계절톤분석 #메이크업컬러추천 #헤어컬러가이드 #이미지분석 #맞춤추천 #활동량하 | J25: https://colorplace.co.kr/consulting8.html
C26: NEUF COULEUR 0507-1351-0014 contact@neufcouleur.com | E26: Palette Premium | F26: 250 / 1P | H26: 150 m | I26: 신체색 분석 후 퍼스널컬러진단 + 헤어, 주얼리, 렌즈컬러 추천 + 페이스존 간이 분석, 패션 코칭 + 향수 추천 + 목걸이, 귀걸이, 반지, 시계 디자인 추천 #퍼스널컬러심화진단 #컬러배색가이드 #페이스존분석 #이미지분석 #메이크업활용 #맞춤추천 #활동량하 | J26: https://neufcouleur.com/Home

Sheet 3-3. K-Wellness_TOUR
A1: K-Wellness_Tour for Muslim VIP K-BMW Premium Tour
A4: K-Wellness Package | J4: Information
A5: Package | B5: Sub Package | C5: Partners | D5: Course Program & Grade | F5: Quotation | H5: Time Taken | I5: Package Detail
F6: 1,000 KRW | G6: USD
A7: K-WELLNESS (TOUR) | B7: KTX EXPERIENCE
B8: CITY TOUR | C8: COSMOJIN 1644-8230 master@koreatourtip.co.kr | D8: SEOUL CITY TOUR | E8: VIP Special Tour Full-Day | F8: 220 / 1P | H8: 1 day | I8: 최소 인원 4명 / 09:00 ~ 17:30 호텔 → 드라이빙(시청/광화문광장/청계천) → 수문장교대의식 → 경복궁 (월요일: 덕수궁 대체) → 국립민속박물관 → 청와대 경유 → 자수정 혹은 인삼센터 → N서울타워 → 중식 → 창덕궁 (월요일: 북촌한옥마을 대체) → 인사동 → 한강크루즈 → 호텔 #외국인전용여행사 #서울VIP시티투어 #역사문화체험 #프라이빗차량 #픽업서비스 #중식포함 #활동량중상 | J8: https://home.cosmojin.com/korea-package/detail.php?idx=41
C9: Gold Sky Tour 02 2039 5882 hi@goldskytour.com | D9: SEOUL CITY NIGHT TOUR | E9: SEOUL CITY NIGHT TOUR (BAMDOKKAEBI TOUR) | F9: 90 / 1P | H9: 4 hr | I9: 광화문광장 → 청계천을 따라 드라이빙 → 동대문 DDP → N서울타워 → 한강공원→ 반포대교 달빛무지개분수 → 이태원 #야간드라이빙투어 #서울야경 #외국인전용 #영어가이드 #활동량중 | J9: https://www.goldskytour.com/night-tour
C10: KOREA TOUR NET 070-7792-3001 phc@koreatournet.kr | D10: ISLAMIC SEOUL TOUR | E10: Tour & Halal Food are available for Muslim Travelers | F10: 85 / 1P | H10: 4 hr | I10: Hotel-Hanbok-Changing Guard Ceremony (Folk Museum on Tue)-Gyeongbokgung Palace-N Seoul Tower-Itaewon Mosque -Lunch-Prayer's time-Bukchon Village-Dongdaemun Market-Gwangjang Market-Myeongdong (Include : Private Car, Lunch, Entrance Fees, Guide) #무슬림프라이빗투어 #할랄식사제공 #기도시간보장 #서울시티투어 #아랍어가이드 #영어가이드 #중식포함 #활동량중상 | J10: http://www.koreatournet.kr/islamic2type.php
B11: LOCAL TOUR | C11: COSMOJIN 1644-8232 master@koreatourtip.co.kr | D11: DMZ TOUR | E11: DMZ + NLL TOUR | F11: 160 / 1P | H11: 1 day | I11: 최소 인원 4명 / 07:00 ~ 17:30 호텔 → 임진각 → 통일대교 → 여권 및 신분증 검사 → DMZ 영상관 및 전시관 → 제3터널 → 도라전망대 → 통일촌 → 중식 → 강화도 연미정 → 여권 및 신분증 체크 → 해안경계철책선 → 강화 평화전망대 → 호텔 #외국인VIP전용 #DMZNLL투어 #전문가이드동행 #중식포함 #활동량중 | J11: https://home.cosmojin.com/korea-package/detail.php?idx=65
C12: KOREA TOUR NET 070-7792-3001 phc@koreatournet.kr | D12: ISLAMIC NAMI ISLAND TOUR | E12: The Garden of Morning Calm + Nami Island | F12: 120 / 1P | H12: 4 hr | I12: 호텔 → 남이섬 → 중식 → 기도 시간 → 아침고요수목원 → 호텔 또는 명동 → 투어 종료 #무슬림프라이빗투어 #할랄식사제공 #기도시간보장 #남이섬투어 #아랍어가이드 #영어가이드 #중식포함 #활동량중상 | J12: http://www.koreatournet.kr/
C13: LOTTE TOUR 1577-3000 | D13: JEJU TOUR | E13: Private trip, 3 days of Jeju Island | F13: 686 - 1,165 / 1P | H13: 3 day | I13: Inclusions: Round-trip airfare, accommodations at the Grand Hyatt Jeju, private vehicle and driver (Solati for 4-10 people, Combi Bus for 11 or more people), meals as per itinerary (breakfast, lunch, and one dinner per day), admission fees to tourist attractions as per itinerary (Pacific Marina Yacht, Hwansang Forest Gotjawal Park + foot bath, full-body massage, etc.), travel insurance #프라이빗제주 #그랜드하얏트 #전용차량 #퍼시픽마리나요트 #전신마사지 #동백동산 #맞춤일정가능 #중식포함 #활동량중 | J13: https://www.lottetour.com/evtList/851/938/943/944?godId=65289
E14: 3 rounds of 18 holes at Blackstone Villa + Blackstone CC + Elysian CC | F14: 887 - 1,245 / 1P | H14: 3 day | I14: Inclusions: 2 nights' accommodation, 3 rounds of 18-hole green fees (1 round at Elysian, 2 rounds at Blackstone) #제주골프 #프라이빗빌라 #블랙스톤CC #엘리시안CC #아시아100대골프코스 #전용차량 #식사불포함 #활동량상 | J14: https://www.lottetour.com/evtList/851/2750/2751/2752?godId=57906
C15: Gyeongsangbuk-do Cultural Tourism 1522-2089 070-4263-7790 | D15: GYEONGJU CITY | E15: Gyeongbuk Tourpass | F15: 17 / 1P | H15: 1 day | I15: An affordable and convenient free-pass ticket to access major paid tourist attractions in Gyeongsangbuk-do for 24 hours with a single barcode. #경북투어패스 #자유이용권 #경상북도 #관광패스 #24/48/72시간 #다양한추천코스 | J15: https://www.gbtourpass.kr/Tourpass/view?seq=iBb2419
B16: CRUISE Tour | C16: NATOUR 051-714-3133 info@natour.co.kr | D16: BUSAN CITY | E16: Busan Fanstar One Night Cruise | F16: 600 - 650 / 1P | H16: 2 day | I16: Inclusions: Panstar Bridge Tour, Onboard Dinner Buffet, Performances and various events, fireworks #부산팬스타 #원나잇크루즈 #주말여행 #국내크루즈 #선상불꽃놀이 #부산출발 #선상뷔페 #석식포함 #조식포함 #럭셔리선상라이프 #활동량하 | J16: https://www.natour.co.kr/shop_view/?idx=186
B17: RAIL CRUISE TOUR | C17: HAERANG 1544-7755 haerang@korailtravel.com | D17: GRAND TOUR OF KOREA Suncheon, Busan, Gyeongju, Jeongdongjin, Donghae | E17: Three Days journey | F17: 3,540 - 3,710 / 2P | H17: 3 day | I17: This travel package, AURA, aims at introducing ‘the beautiful nature of Korea’ in ‘an aloof atmosphere that cannot be imitated’ with Rail Cruise Haerang. This high quality travel package offers customers the opportunity to enjoy Korea’s beautiful landscape along with delicious local food while traveling throughout the country. #전국일주 #숙박형기차여행 #순천 #여수 #부산 #경주 #동해 #맛집체험 #관광지포함 #식사포함 #활동량중 | J17: https://www.railcruise.co.kr/website/rc_course_info.asp?1

Sheet 3-4. K-Wellness_Leisure
A1: K-Wellness_Leisure for Muslim VIP K-BMW Premium Tour
A4: K-Wellness Package | J4: Information
A5: Package | B5: Sub Package | C5: Partners | D5: Course Program & Grade | F5: Quotation | H5: Time Taken | I5: Package Detail
F6: 1,000 KRW | G6: USD
A7: K-Wellness (LEISURE) | B7: SNOW TOUR | C7: TATATA RENTAL SHOP 010-4994-5060 kyc1120@naver.com | D7: MONA YONG PYONG RESORT Gangwon-do Pyeongchang | E7: Ski & Board rental + lesson | F7: rental+lift: 111 / 1P lesson: 200 - 400 / 1T | H7: 1~2 day | I7: #국내최대스키장 #국제스키연맹공인슬로프13개 #슬로프수28면 #리프트수14기 #스키렌탈 #보드렌탈 #장비렌탈 #의류렌탈 #리프트 #강습 | J7: https://www.tatataski.com/
C8: SERENO SKISHOP 010-5716/5691-1369 | D8: High 1 RESORT Gangwon-do Jeongseon | E8: Skiing & Boarding &Sleigh | F8: rental+lift: 120 / 1P lesson: 150 - 360 / 1T | H8: 1~2 day | I8: #국제스키연맹공인슬로프15개 #슬로프수15면 #리프트수5기 #곤돌라수3기#스키렌탈 #보드렌탈 #장비렌탈 #의류렌탈 #리프트 #강습 | J8: https://serenoskishop.com/
C9: NUMBER.1 RENTALSHOP 010-2312-9202 gudwns2695@naver.com | D9: VIVALDI PARK RESORT Gangwon-do Hongcheon | E9: Skiing & Boarding &Sleigh | F9: rental+lift: 150 / 1P lesson: 140 - 240 / 1T | H9: 1~2 day | I9: #슬로프수13면 #리프트수10기 #스키렌탈 #보드렌탈 #장비렌탈 #의류렌탈 #리프트 #강습 | J9: https://smartstore.naver.com/number1rentalshop
C10: V SKI 031-769-9997 yachacom@naver.com | D10: KONJIAM RESORT Gyeonggi-do Gwangju | E10: Skiing & Boarding &Sleigh | F10: rental+lift: 159 / 1P lesson: 150 - 360 / 1T | H10: 1~2 day | I10: #슬로프수9면 #리프트5기 #스키렌탈 #보드렌탈 #장비렌탈 #의류렌탈 #리프트 #강습 | J10: https://smartstore.naver.com/vski
B11: WATER PARK | C11: Caribbean Bay 031-320-5000 Gyeonggi-do Yongin | E11: 1 Day Pass | F11: Middle Seasons: 55 / 1P High Seasons: 65 / 1P Gold Seasons: 79 / 1P | H11: 1~2 day | I11: #에버랜드리조트산하의워터파크 #카리브해테마 #파도풀 #다이빙풀 #서핑라이드 #슬라이드 | J11: https://www.everland.com/caribbeanbay/home/main
C12: Ocean World 1588-4888 webmaster@daemyungsono.com Gangwon-do Hongcheon | E12: 1 Day Pass | F12: Mid Summer: 74 / 1P Hot Summer1: 79 / 1P Hot Summer2: 89 / 1P | H12: 1~2 day | I12: #비발디파크리조트의초대형워터파크 #고대이집트테마 #파도풀 #슬라이드 | J12: https://www.sonohotelsresorts.com/oceanWorld
C13: Cimer 1833-8855 p-city@paradian.com Incheon Jung-gu | E13: 6 hours | F13: Normal season: 50 / 1P Peak season: 60 / 1P | H13: 1~2 day | I13: #파라다이스시티의스파워터파크 #유럽식아트스파+풀파티+감성찜질방 #슬라이드 #인피티니풀 | J13: https://www.p-city.com/front/cimer/overview
B14: WATER LEISURE | C14: Le Point Water Leisure 010-8233-1426 Gyenggi-do Gapyeong | E14: 1 Day Pass + 1-time Jet Boat | F14: 75 / 1P | H14: 1~2 day | I14: #워터파크 #제트보트 #수상스키/웨이크보드 #놀이기구 #무제한바베큐 | J14: https://lepoint.qrsvc.kr/
C15: RIVER LAND 010-5337-5534 Gyenggi-do Gapyeong | E15: Afternoon Pass + 1-time Jet Boat | F15: 59 / 1P | H15: 1~2 day | I15: #워터파크 #제트보트 #수상스키/웨이크보드 #놀이기구 #무제한바베큐 | J15: http://www.riverland.co.kr/
B16: SPORTS | C16: 키움히어로즈(GOCHUCK) Seoul Guro-gu | D16: BASEBALL | E16: SKY BOX | F16: 20P: 2,400 / 1T 9P: 1,080 / 1T | I16: 제공 서비스 / 이벤트 1) 전용 출입구 이용(고척 스카이돔 중앙 C게이트) 2) 전용 주차장 이용 3) 마스코트 포토 서비스 | J16: https://heroesbaseball.co.kr/index.do
C17: SSG Landers (Incheon SSG Landers Field) Incheon Michuhol-gu | E17: SKY BOX | F17: weekdays: 71 /1P weekends: 77 / 1P | J17: https://www.ssglanders.com/main
C18: FC Seoul (Seoul World Cup Stadium) Seoul Mapo-gu | D18: Soccer | E18: SKY BOX | F18: 2,970 / 1T
B19: THEME PARK | C19: LOTTE WORLD 1661-2000 Seoul Songpa-gu | E19: 1 Day Pass + Magic Pass Premium | F19: 5-time pass: 54 / 1P 7-time pass: 75 / 1P | H19: 1 day
C20: EVER LAND 031-325-0000 Gyeonggi-do Yongin | E20: Dream Tour | F20: 350 / 1P | H20: 1 day | I20: * 드림투어 지정 주차공간 제공 * 에버랜드 정문 게이트 우선 입장 * 투어 가이드 파크 동행 서비스 * 인기 어트랙션 우선 탑승 * 에버랜드 기념 촬영 * 레스토랑 식사 * 사파리 스페셜 투어(26.02.19부터 리뉴얼로 휴장)
C21: SEOUL LAND 02-509-6000 Gyeonggi-do Gwachon | E21: 1 Day Pass | F21: 52 / 1P | H21: 1 day

Sheet 3-5. K-Wellness_Education
A1: K-Wellness_K-Education for Muslim VIP K-BMW Premium Tour
A4: K-Wellness Package | J4: Information
A5: Package | B5: Sub Package | C5: Partners | D5: Course Program & Grade | F5: Quatation | H5: Time Taken | I5: Package Detail
F6: 1,000 KRW | G6: USD
A7: K-Wellness (EDUCATION) | B7: CITY PACKAGE TOUR | C7: Korea tour tip 1644-8230 master@koreatourtip.co.kr | D7: SEOUL TOUR | E7: Experience Future-Oriented Korean Education Spanning School Exchange, AI, Media, and K-POP | F7: 1,100.5 / 1P (estimated price) | G7: 815 | H7: 5 day | I7: 최소 인원: 30인, 최대 인원: 40인 Day 1: Incheon Airport → G Valley Industrial Experience Center → Hiker Ground Day 2: School Exchange (AM) → School Exchange (PM) → Namsan Cable Car → N Seoul Tower Day 3: Seoul Robotics & AI Science Center → MMCA Seoul → KBS Station → National Assembly Museum → Han River Cruise Day 4: National Museum of Korea → Myeongdong → Real K-POP Dance Experience → Hongdae Street Day 5: Gyeongbokgung Palace → National Palace Museum → Incheon Airport #외국인학생수학여행 #서울교육체험 #학교교류 #로봇AI체험 #KPOP체험 #박물관탐방 #식사포함 #활동량중 | J7: https://www.koreatourtip.com/master/29173
B8: CITY + LOCAL PACKAGE TOUR | D8: SEOUL, GYEONGGI TOUR | E8: Korean educational tour encompassing university campuses, future technologies, media, and theme parks | F8: 1,018.5 / 1P (estimated price) | G8: 775 / 1P (estimated price) | H8: 5 day | I8: 최소 30인, 최대 40인 Day 1: Incheon Airport → Seodaemun Prison History Museum → War Memorial of Korea Day 2: University Campus Tour → Hongdae Street → MBC World Theme Park → Han River Cruise Day 3: LG Discovery Lab → Seoul Future Lab → National Museum of Korea → Insadong Day 4: Wolmi Sea Train → Wolmi Theme Park → Songdo Central Park → National Museum of World Letters → G-Tower Observatory Day 5: Gimbap Making Experience → National Aviation Museum → Incheon Airport #외국인학생수학여행 #서울경기권교육체험 #대학캠퍼스투어 #미래기술투어 #미디어투어 #테마파크 #식사포함 #활동량중상 | J8: https://www.koreatourtip.com/master/28983
E9: Experience K-POP, Traditional Culture, Theme Parks, and Future Industries All at Once | F9: 1,178.5 / 1P (estimated price) | G9: 873 / 1P (estimated price) | H9: 5 day | I9: 최소 30인, 최대 40인 Day 1: Incheon Airport → Gwangjang Market / Dongdaemun Market Day 2: University Campus Tour → K-POP Dance Experience → Apgujeong K-Star Road Day 3: Korean Folk Village → Everland Day 4: Gyeongbokgung Palace → Hiker Ground → Namsan Cable Car & Seoul Tower → Myeongdong → Painters Show / Musical Chef Day 5: Hyundai Motorstudio Goyang → Heiri Art Village → Incheon Airport #외국인학생수학여행 #서울경기권교육체험 #K-POP투어 #한국전통투어 #테마파크 #미래산업투어 #식사포함 #활동량중상 | J9: https://www.koreatourtip.com/master/18057
B10: IT experience | C10: SAMWOO immersion 070-4711-0991 swim118@samwooim.com Busan Dong-gu | D10: IX 청소년 체험센터 | E10: AI-X 진로 탐험관 체험 프로그램 | F10: 400 / 1T | H10: 150m | I10: * Program 01: AI 이론 및 실습 프로그램 * Program 02: 다양한 직업군 VR 체험 * Progame 03: 수료증 발급 #청소년체험센터 #AI-X진로탐험관 #AI교육 #XR직업체험 #활동량중하 | J10: https://www.samwooim.com/AIX_dream
C11: SAMSUNG aiclass@samsung.com Gyeonggi-do Suwon | D11: 갤럭시 AI 클래스 | E11: 디지털시티 | H11: 150m | I11: 신청대상: 초등(5~6학년) Program: 삼성이노베이션뮤지엄 투어, eX·Home, 사업장 투어 및 점심식사, 갤럭시 AI 체험 공휴일, 방학기간 미운영 #초등체험학습 #디지털시티 #삼성전자 #AI교육 #XR직업체험 #식사포함 #활동량중하 | J11: https://www.samsung.com/sec/ai-class/digitalcity/
C12: SAMSUNG STORE 홍대 02-333-8788 대치 02-3454-1103 강남 02-3482-8388 노원 02-2091-1447 강서 02-2658-3033 | E12: 삼성스토어 | I12: 신청대상: 유치/초등 Program: 내 꿈 티셔츠 만들기, 키링 만들기, 내 셀피로 스티커 만들기, 가족여행 텀블러 만들기 #유치/초등체험 #AI체험 #체험학습 #활동량하 | J12: https://www.samsung.com/sec/ai-class/samsungstore/
A15: K-Wellness Package | J15: Information
A16: Package | B16: Sub Package | C16: Partners | D16: Course Program & Grade | F16: Quatation | H16: Time Taken | I16: Package Detail
F17: 1,000 KRW | G17: USD
A18: K-Wellness (EDUCATION) | B18: KOREAN UNIVERSITY VISIT | C18: SEOUL UNIVERSITY 국제협력본부(ahnsihun@snu.ac.kr) Seoul Gwanak-gu | D18: CAMPUS TOUR | E18: Group Tour & Self-Guided Campus Tour | F18: free | H18: 120m | I18: Number of tours per week: TBD, Mon-Friday (9:00 a.m. to 4:00 p.m. KST / GMT+9) Only visitors from high schools, universities, or institutes may apply. Office of International Affairs - College of Business Administration - College of Music / College of Fine Arts - Jaha Pond / Cultural Center - Administration Building - Student Center (Souvenir Shop) - Seoul National University Library - College of Humanities - School of Law - Kyujanggak Institute for Korean Studies - College of Social Sciences - Main Stadium | J18: http://oia.snu.ac.kr/campus-tours-overview
C19: KOREA UNIVERSITY 02-3290-2675 Seoul seongbuk-gu | D19: CAMPUS TOUR | E19: Individual & Flexible Tours (Crimson Tour) | F19: free | H19: 90m | I19: * Registration by phone (02-3290-2675) or on-site (first 25 participants; registration closes 5 minutes before the tour starts) * Operates three times daily for approximately 30 minutes each (11:00–11:30, 14:00–14:30, 17:00–17:30) * Available in Korean or English * If applicants are not from the same group, multiple groups may join the tour during each time slot. | J19: https://tour.korea.ac.kr/tour/index.do
C20: YONSEI UNIVERSITY 1599-1885 Seoul Seodaemun-gu | D20: CAMPUS TOUR | E20: Group Tour | F20: free | H20: 90m | I20: Groups must consist of at least 4 and no more than 100 people Sinchon Campus: Tours operate Monday to Friday, 10:00 AM or 4:00 PM (excluding periods when campus tours are not available) International Campus: Tours operate on Friday at 2:00 PM (excluding periods when campus tours are not available) | J20: https://www.yonsei.ac.kr/en_sc/1826/subview.do
C21: Incheon Global Campus 032-626-0114 yjlee@igc.or.kr Incheon Yeonsu-gu | D21: IGC PR Center | E21: Free Tours or Docent-Guided Tour | F21: free | H21: 90m | I21: How to Visit : Advance reservation required ※ for both free and docent-guided tours Free Tours : Monday-Friday, 10:00 a.m.-7:00 p.m. ※ closed during lunch hour, 12:00-1:00 p.m. Docent-Guided Tour : Tuesdays and Thursdays at 2:30 p.m. ※ approximately 30 minutes / available for group visitors, high school level and older | J21: https://en.journal.igc.or.kr/65
B22: MAJOR COPORATION MANUFACTURING TOUR | C22: HYUNDAI 052)215-2323 / 2234 Ulsan Bok-gu | D22: Ulsan Manufacturing Plant | E22: Dreams ever dreamt | F22: free | H22: 120m | I22: time: weekdays 09:00 ~ 17:00(Excluding lunch break 11:30 – 12:30, weekends, and public holidays) 현대자동차그룹 홍보영상 관란 -> 현대자동차 및 울산공장 역사 설명 / 올드카 전시 관람 -> 의장 라인 관람 및 자동차 생산 공정 설명 -> 대한민국 유일 공장 내 자동차 전용부두 설명 #울산 #산업견학 #공장견학 #자동차산업체험 #초등4학년이상 #식사불포함 #활동량중 | J22: https://www.hyundai.com/kr/ko/brand/factory-reservation/reservation
C23: AMOREPACIFIC amorefactory@amorepacific.com Gyeonggi-do Osan | D23: Amorepacific factory tour | E23: Group tour | F23: free | H23: 120m | I23: The first floor introduces key historical production sites and original equipment, highlighting the expansion and advancement of Amorepacific’s manufacturing capabilities. The second floor displays the development of technologies and manufacturing equipment accumulated since the company’s founding through a storage-based exhibition. The third floor offers a view into the skincare packaging process and the intelligent production and logistics system of the Amore Beauty Park. #경기 #산업견학 #공장견학 #화장품산업체험 #초등학생이상 #식사불포함 #활동량중 | J23: https://tour.amorepacific.com/
C24: NONGSHIM 051-366-5326 | D24: Busan Factory | F24: free | H24: 120m | I24: 수출 제품 전문 생산공장 매월 1일~4일 다음달 견학 예약, 매월 10일 추첨 #부산 #산업견학 #공장견학 #식품산업체험 #고등학생이상 #식사불포함 #활동량중 | J24: https://www.nongshim.com/customer/factory_trip/registration_busan
A27: K-Wellness Package | J27: Information
A28: Package | B28: Sub Package | C28: Partners | D28: Course Program & Grade | F28: Quatation | H28: Time Taken | I28: Package Detail
F29: 1,000 KRW | G29: USD
A30: K-Wellness (EDUCATION) | B30: KOREAN CULTURAL EXPERIENCE | C30: Life World tour 010 7711 0774 02 1688 5632 bulgom@lifeworldtour.com | D30: Korean Traditional Paper Culture Tour | E30: Hanji Fan-Making Experience Program | G30: 42 / 1P | H30: 150 m | I30: 최소 인원: 2인(최대 인원 15인) 웰컴 드링킹&소개 → 부채 만들기 워크숍 → 전통 문양 채색 → 마무리&사진 촬영 | J30: https://lifeworldtour.com/tour/hanji-fan
C31: COSMOJIN 1644-8230 master@koreatourtip.co.kr | D31: CULTURAL EXPERIENCE | E31: Taekwondo | F31: 160 / 1P | H31: 240m | I31: 태권도 예절 교육 → 태권도 사범 시범 → 기본 동작 및 품새 체험 → 격파 체험 → 수료식 (수료증 수여) | J31: https://home.cosmojin.com/korea-package/detail.php?idx=45
C32: Gold Sky Tour 02-2039-5882 hi@goldskytour.com | D32: Korean Traditional Culture Experience Tour | E32: A Harmony of History and Modernity A Korean Cultural Experience | F32: 138 / 1P | H32: 4 hr | I32: 경복궁(한복체험) → 국립민속박물관 → 한식문화전시관 → 점심식사(비빔밥) → 한식문화관 참관&한식 디저트 만들기 체험 → 고려인삼박물관 → 페인터즈쇼 | J32: https://www.goldskytour.com/b
C33: JinJooShell 02-2253-7585 ymspace@jinjooshell.com | D33: mother-of-pearl craft experience | F33: 30 - 150 / 1P | H33: 180m | I33: A premium mother-of-pearl craft experience held at Jinju Shell in Bukchon Hanok Village, featuring heritage works prepared by Master Artisan Lee Young-ok. This one-day program allows participants to work with a variety of materials, including hand-cut mother-of-pearl, engraved and stamped inlay, and lacquered wooden objects. | J33: https://jinjooshell.com/class
B34: KOREAN CULTURAL HERITAGE TOURS | C34: Korea Heritage Agency 1670-8904 | D34: Visit Korean Heritage Campaign | E34: Korean Heritage Passport Tour | I34: Along with the Korean Heritage Visitor's Passport, you will go through 10 roads and 76 national heritages. It is a program where you can feel the special beauty of Korea. 10 Routes Gaya Culture Route / Gwandong Pungryu Era Route(Gangwon-do) / Baekje Antiquity Route(Gongju, Buyeo, Iksan) / Korean Temple Monasteries (Sansa) Route / Korean Confucian Academy Route / Prehistoric Landscape Route(Yeoncheon) / Mythic Landscape Route(Jeju) / Folk Music Route Royalty Route(Seoul, Suwon, Hwaseong) / Golden Era Route(Gyeongju) | J34: https://www.kh.or.kr/visit/kor/index.do
B35: MUSEUM TOUR | C35: National Museum of Korea 02-2077-9000 Seoul Yongsan-gu | D35: Exhibitions | E35: Permanent Exhibitions | F35: free | I35: Operating Hours MON, TUE, THU, FRI, SUN: 10:00 ~ 18:00(final entrance at 17:30) WED, SAT: 10:00 ~ 21:00(final entrance at 20:30) 15인 이상일 경우 해설 예약 가능 | J35: https://www.museum.go.kr/MUSEUM/main/index.do
C36: National Gugak Center 02-580-3130 Seoul Seocho-gu | D36: Exhibitions | F36: free | I36: Operating Hours: 10:00 ~ 18:00(final admission 17:00) Closed on Mondays and January 1st | J36: https://www.gugak.go.kr/site/main/index001
C37: Seodaemun Prision History Hall 02-360-8590 Seoul Seodaemun-gu | D37: Exhibitions | F37: 3 / 1p | I37: Operating Hours Summer season (March o October): 09:30 ~ 18:00 Winter season(November to February): 09:30 ~ 17:00 | J37: https://sphh.sscmc.or.kr/

Sheet 4. K-Starcation
A1: K-Starcation for Muslim VIP K-BMW Premium Tour
A4: K-Wellness Package | I4: Information
A5: Package | B5: Partners | C5: Course Program & Grade | E5: Quotation | G5: Time Taken | H5: Package Detail
E6: 1,000 KRW | F6: USD
A7: K-Starcation | B7: World K-POP Center w-kpop@naver.com | C7: K-POP CAMP | D7: Basic (2박 3일 K-POP 캠프) | E7: 3000 | G7: 3day | H7: 그룹 K-POP 베이직 트레이닝 (보컬 & 댄스 기초) + K-POP 아이돌 헤어 & 메이크업 스타일링 + 프리미엄 스튜디오 프로필 촬영 + 숏폼(Reels/Shorts) 챌린지 영상 제작 + 공식 수료증 발급 | I7: 프리미엄 레지던스 숙박 및 소수정예 K-POP 체험 전문 영상팀 트렌디 숏폼 챌린지 영상 촬영 및 제작 할랄/비건 다과 및 식사 케이터링 ISO 국제자격증 과정 제공 (댄스, 보컬 부분) 전담 강사 및 직원, 통시 통역 가이드 배치
D8: Gold (4박 5일 프로 클래스) | E8: 4000 | G8: 5day | H8: 소수정예 K-POP 심화 트레이닝 (보컬, 댄스, 무대 퍼포먼스) + 프리미엄 아이돌 스타일링 (무대 의상 피팅 요청 시 추가 진행 가능) + 개인 콘셉트 화보 촬영 + 전문 스튜디오 음원 녹음 + 하이라이트 뮤직비디오(MV) 촬영 + 공연장 쇼케이스 진행 + 수료증 발급
D9: Platinum (4박 5일 VVIP Class) | E9: 5500 | G9: 5day | H9: 1:1 마스터 트레이닝 (전담 보컬/댄스 디렉팅) + VVIP 전담 스타일링 및 맞춤형 무대 + 단독 음원 제작 및 녹음 + 스케일업 단독 풀버전 뮤직비디오(MV) 촬영 + 쇼케이스 + 전담 의전 및 VIP 케어(기도실/할랄 식단 등 맞춤 지원) +기획사 내방오디션

Sheet 5. Hotel
A1: Hotel for Muslim VIP K-BMW Premium Tour
A4: Premium Package | H4: Information
A5: Package | B5: Category | C5: Partners | D5: Selection Sheet Grade | E5: Room | F5: Quotation (KRW) | G5: Check-up-Detail
A6: Hotel | B6: ★5 Hotel | C6: THE SHILLA SEOUL 02-2230-3310 Seoul Jung-gu | D6: Deluxe | E6: Executive Grand Deluxe | F6: 786,500 ~ 1,760,000 / 1박, 2인 기준 1인당 추가 금액 242,000 / 1박 | G6: 룸구성(53m2): 침실1, 욕실1, 화장실1 기준 인원: 성인 2인(최대 인원: 성인 3인 또는 소인 동반 시 최대 4인) | H6: https://www.shillahotels.com/index.do
D7: Suite | E7: Premier Suite | F7: 1,430,000 ~ 3,630,000 / 1박, 2인 기준 1인당 추가 금액 308,000 / 1박 | G7: 룸구성(84m2): 침실1, 욕실1, 화장실2, 응접실1 기준 인원: 성인 2인(최대 인원: 성인 4인 또는 소인 동반 시 최대 5인)
D8: Special Suite | E8: Shilla Suite | F8: ~ 13,000,000(세금 별도) / 1박, 2인 기준 1인당 추가 금액 308,000 / 1박 | G8: 전화 예약만 가능 룸구성(159m2): 침실1, 욕실1, 사우나1, 화장실2, 응접실1, 집무실1, 다이닝룸1 기준 인원: 성인 2인(최대 인원: 성인 4인 또는 소인 동반 시 최대 5인)
C9: SIGNIEL SEOUL 02-3213-1111 rsv.signiel.seoul@lotte.net Seul Songpa-gu | D9: Deluxe | E9: Premier Double River view | F9: 665,500 ~ 1,319,500 / 1박, 2인 기준 1인당 추가 금액 60,500 / 1박 | G9: 면적: 59-73m2 투숙 인원: 2인, 전망: 리버(전망욕실) | H9: https://www.lottehotel.com/global/ko
D10: Suite | E10: Primier Suite Doblue River view | F10: 1,270,500 ~ 2,359,500 /1박, 2인 기준 1인당 추가 금액 60,500 / 1박 | G10: 면적: 70-86m2 투숙 인원: 2인, 전망: 리버(전망욕실)
D11: Special Suite | E11: Presidential Suite | F11: 12,100,000 / 1박 | G11: 면적:143m2 투숙 인원: 2인, 전망: 시티(전망욕실)
C12: FOUR SEASONS 02-6388-5000 Seoul Jongro-gu | D12: Deluxe | E12: Premier Family Room | F12: 847,000 ~ 1,319,500 / 1박, 2인 기준 1인당 추가 금액: 106,000 / 1박 | G12: 면적:48m2 기준인원: 성인2(최대 인원" 성인 3인 또는 성인 1인과 유아 2인). 전망: 도심 또는 산 전망 | H12: https://www.fourseasons.com/kr/seoul/
D13: Suite | E13: Palace-View Executive Suite | F13: 1,593,000 ~ 2,200,000 /1박, 2인 기준 1인당 추가 금액: 297,000 / 1박 | G13: 면적: 143m2 기준 인원: 성인 2인(최대 인원: 성인 3명 또는 성인 2명과 어린이 2명), 전망: 경복궁 전망
C14: PARK HYATT SEOUL 02-2016-1234 Seoul Gangnam-gu | D14: Deluxe | E14: 2 twin bed premium | F14: 847,000 ~ 1,319,500 / 1박, 2인 기준 1인당 추가 금액: 106,000 / 1박 | G14: 면적: 52m2 | H14: https://www.hyatt.com/park-hyatt/ko-KR/selph-park-hyatt-seoul
D15: Suite | E15: Park coner Suite | F15: 935,000 ~ 1,298,000 /1박 1인당 추가 금액 99,000 / 1박 | G15: 면적: 70m2
C16: InterContinental Grand Seoul Parnas 00 798 142 03 0212 Seoul Gangnam-gu | D16: Deluxe | E16: 2 double premiun room | F16: 590,480 ~ 1,362,460 / 1박, 2인 기준 1인당 추가 금액 70,000 | G16: 면적: 50m2 기준 인원: 성인 2명(최대 인원: 성인 4인) | H16: https://www.ihg.com/intercontinental/hotels/kr/ko/seoul/seoha/hoteldetail
D17: Suite | E17: Coner Suite | F17: 1,114,410 ~ 1,943,260 /1박, 2인 기준 1인당 추가 금액 70,000 | G17: 면적: 85m2 기준 인원: 성인 2명(최대 인원: 성인 3인)
D18: Special Suite | E18: Ambassador Suite | F18: 7,704,675 ~ 8,385,300 / 1박, 2인 기준 1인당 추가 금액 70,000 | G18: 면적: 120m2 기준 인원: 성인 2명(최대 인원: 성인 3인)
C19: PARADISE HOTEL 032-729-2000 1833-8855 p-city@paradian.com Incheon Jung-gu | D19: Deluxe | E19: Grand Deluxe Suite | F19: 979,000 ~1,258,000 / 1박, 2인 기준 1인당 추가 금액 55,000 | G19: 면적: 135m2 기준 인원: 성인 2명(최대 인원: 성인 3인) | H19: https://www.p-city.com/front/hotel/overview
D20: Suite | E20: Royal Suite | F20: 3,300,000 ~ 4,180,000 / 1박, 4인 기준 1인당 추가 금액 50,000 | G20: 면적: 84m2 기준 인원: 성인 2명(최대 인원: 성인 ?인)
D21: Special Suite | E21: Grand Deluxe Poll Villa | F21: 13,200,000 / 1박, 4인 기준 1인당 추가 금액 50,000 | G21: 면적: 942m2 기준 인원: 성인 4명(최대 인원: 성인 5인)
C22: INSPIRE 032-580-9000 contact@inspireresorts.com Incheon Jung-gu | D22: Minagi Omakase Set | E22: Sun Suite | F22: 869,000 ~ 1,122,000 / 1박, 2인 기준 | G22: 미나기 오마카세 세트 + 웰니스 클럽 실내 수영장 및 피트니스 센터 무료 이용 면적: 131m2 기준 인원: 성인 2명, 전망: 호수 전망 | H22: https://www.inspireresorts.com/ko
E23: Sun Tower Inspire Suite | F23: 1,694,000 ~ 1,947,000 / 1박, 2인 기준
D24: Premier Suite Journey | E24: Sun Suite | F24: 869,000 ~ 1,188,000 / 1박, 2인 기준 | G24: 레이트 체크아웃 + 스플래시 베이 오후 이용권 + 스플래시 베이 카바나 + 세프스 키친 디너 뷔페 + 웰니스 클럽 실내 수영장 및 피트니스 센터 무료 이용 면적: 131m2 기준 인원: 성인 2명, 전망: 호수 전망
E25: Sun Tower Inspire Suite | F25: 1,639,000 ~ 1,958,000 / 1박, 2인 기준
C26: PARK HYATT INCHEON 032-745-1234 Incheon Jung-gu | D26: Deluxe | E26: 2 Twin Beds with Club Access West Tower | F26: 646,800 ~775,500 / 1박, 2인 기준 1인당 추가 금액: 168,300 | G26: 면적: 38m2 | H26: https://www.hyatt.com/grand-hyatt/ko-KR/inche-grand-hyatt-incheon
D27: Suite | E27: Ambassador Suite | F27: 1,137,074 ~ 1,329,900 / 1박, 2인 기준 1인당 추가 금액: 242,200 | G27: 면적: 108m2
D28: Special Suite | E28: Presidential Suite | F28: 2,719,200 ~ 2,759,900 / 1박, 2인 기준 1인당 추가 금액: 242,200 | G28: 면적: 252m2
C29: Oak Wood Premier Incehon 032-726-2000 reservations.incheon@oakwoodpremier.co.kr Incheon Yeonsu-gu | D29: Deluxe | E29: 2 bedroom premier suite | F29: 538,450 ~ 895,400 / 1박, 4인 기준 1인당 추가 금액 36,300 | G29: 룸구성(112.5m2 ~ 128m2): 침실2, 화장실1, 다이닝룸1, 주방1 기준 인원: 성인 4명(최대 인원: 성인 5인) | H29: https://www.homehmc.com/ko/oakwood-incheon-songdo/
D30: Suite | E30: 4 beadroom suite | F30: 2,250,600 ~ 2,831,400 / 1박, 8인 기준 1인당 추가 금액 36,300 | G30: 룸구성(234.2m2): 침실3, 가족룸1, 화장실3, 다이닝룸1, 주방1, 집무실1, 다용도실1 기준 인원: 성인 8명(최대 인원: 성인 9인)
D31: Special Suite | E31: Penthouse | F31: 3,079,450 ~4,726,260 / 1박, 4인 기준 1인당 추가 금액 36,300 | G31: 룸구성(371.6): 침실2, 가족룸1, 화장실2, 다이닝룸1, 주방2, 옷방1, 다용도실1 기준 인원: 성인 4명(최대 인원: 성인 5인)
C32: Sheraton 032-835-1000 Incheon Yeonsu-gu | D32: Deluxe | E32: Ambassador Suite | F32: 883,300 ~ 1,000,000 / 1박, 2인 기준 1인당 추가 금액 36,300 | G32: 클럽 라운지 이용 가능 + 무료 음식(조식, 간식, 오르되브르) + 무료 비즈니스 서비스 면적: 120m2 기준 인원: 성인 2명(최대 인원: 성인 3인), 전망: 시티뷰 | H32: https://www.marriott.com/ko/hotels/selgi-sheraton-grand-incheon-hotel/overview/
A35: Premium Package | H35: Information
A36: Package | B36: Category | C36: Partners | D36: Selection Sheet Grade | E36: Room | F36: Quotation (KRW) | G36: Check-up-Detail
A37: Hotel | B37: Hanok | C37: THE SHILLA SEOUL 02-2230-3310 Seoul Jung-gu | E37: Korean Suite | F37: ~2,200,000(세금 별도) / 1박 1인당 추가 금액 308,000 | G37: 전화 예약만 가능 룸구성(66m2): 침실1, 욕실1, 화장실2 기준 인원: 성인 2인(최대 인원: 성인 4인 또는 소인 동반 시 최대 5인) | H37: https://www.shilla.net/seoul/accommodation/index.do
C38: SIGNIEL SEOUL 02-3213-1111 Seoul Songpa-gu | E38: Korean Suite | F38: 3,630,000 / 1박 | G38: 면적: 84m2 투숙 인원: 4인, 전망: 리버뷰 | H38: https://www.lottehotel.com/global/ko
C39: Rakkojae Hahoe Hanok Hotel 02-742-3410 rakkojae@roonet.ai Seoul Jongro-gu | E39: 락고재 서울 본관 - 별채(독채) | F39: 510,000 ~ 900,000 / 1박, 4인 기준 1인당 추가 금액 80,000 | G39: 조식 포함 룸구성(50m2): 침실2, 화장실2 / 온돌 기준 인원: 성인 4명(최대 인원: 성인 5인) | H39: http://rkj.co.kr/ko-seoul/
E40: 북촌빈관 by 락고재 - 사랑방 | F40: 459,000 ~790,000 / 1박, 3인 기준 1인당 추가 금액 80,000 | G40: 조식 포함 룸구성(60m2): 침실2, 화장실3 / 온돌 기준 인원: 성인 3명(최대 인원: 성인 4인)
C41: Hanok Essay Hahoe https://gahoe.hanokessay.com/reservation Seoul Jongro-gu | E41: Gahoe | F41: 1,200,000 ~ 1,300,000 / 1박, 4인 기준 1인당 추가 금액 100,000 | G41: 다도세트와 찻잎, 드립 커피 셋트와 원두 기준 인원: 성인 4명(최대 인원: 성인 6인) | H41: https://gahoe.hanokessay.com/
C42: GYEONGWONJAE 032-729-1101 gwj@gwjbywalkerhill.com Incheon Yeonsu-gu | D42: Stay & Dine | E42: Rotal suite | F42: 876,000 ~ 896,000 / 1박, 4인 기준 1인당 추가 금액 33,000(현장 결제) | G42: 면적: 132m2 기준 인원: 성인 4명(최대 인원: 성인 6인) | H42: https://www.gwjbywalkerhill.com/
D43: A Taste of Morning Calm | E43: Rotal suite | F43: 1,195,000 ~ 1,215,000 / 1박, 4인 기준 1인당 추가 금액 33,000(현장 결제) | G43: 면적: 132m2 기준 인원: 성인 2명(최대 인원: 성인 3인)

Sheet 6. Vehicle
A1: Vehicle for Muslim VIP K-BMW Premium Tour
A6: Premium Package | H6: Information
A7: Package | B7: Partners | C7: Vehicle Category | D7: Vehicle Model | E7: Quotation (KRW) | F7: Check-up-Detail | G7: Check-up-Detail
A8: Vehicle | B8: NOBLE KLASSE 070.5210.7678 vipriding@kcmotors.co.kr | C8: NOBLE KLASSE SOLATI | D8: NOBLE KLASSE SOLATI S11 | E8: 별도 상담 | F8: 별도 상담 | G8: 세계최초 할랄인증 리무진으로 제공하는 무슬림 전용 라이딩 서비스로 차량 내 무슬림을 위한 기도 공간을 구성하여, 무슬림 고객들이 국내 관광시 시간과 공간의 제약없이 기도를 할수 있는 무슬림 관광에 최적화된 모빌리티 서비스
B9: 그랜드리무진코리아 (vehicle + driver) 1644-1065 baboo-1052@naver.com | C9: 럭셔리 세단 | D9: 제네시스 G90(신형) | E9: 450000 | F9: 8시간 초과 시 5만원 추가 시트수: 4 | G9: 8시간 기준 | H9: https://www.grandlimousine.co.kr/home
C10: 프리미엄 SUV | D10: 벤츠 S580(신형) | E10: 800000 | F10: 8시간 초과 시 7만원 추가 시트수: 6
C11: 벤츠 스프린터 | D11: 리무진(9인승) | E11: 800000 | F11: 8시간 초과 시 7만원 추가 시트수: 9
C12: 다인승 리무진 | D12: 리무진 버스(28인승 / 45인승) | E12: 별도 상담
B13: CK Company (vehicle + driver) 1688-2271 ckkoreacom@naver.com | C13: 럭셔리 세단 | D13: GENESIS G90 RS4 신형 | E13: 850000 | G13: 10시간 기준 | H13: http://ckkorea.net/
C14: 럭셔리 세단 | D14: BENZ S-Class | E14: 850000
C15: 벤츠 스프린터 | D15: BENZ SPRINTER VIP | E15: 850000
B16: VIP 리무진 코리아 (vehicle + driver) 1877-6411 010-7599-6411 limousines-korea@naver.com | C16: 럭셔리 세단 | D16: 최신형 제네시스 G90 리무진(롱휠) | E16: 800000 | G16: 이용 가능 고객: 외국인(바이어 등) / 국가 및 지방자치단체 / 일반 및 주 법인사업자 / 기업의전방문 주유비, 톨비, 주차비, 기사 숙식비 소요 경비 별도 Over Time 적용: 9시간 기준(09:00 -18:00), 18시 이후에는 시간당 O/T 발생 | H16: https://limousines-korea.com/
C17: 벤츠 스프린터 | D17: 최신형 벤츠 스프린터 리무진 519 최고급형 9인승,11인승,12인승 | E17: 800000
C18: 다인승 리무진 | D18: 리무진(20인승 / 28인승) | E18: 별도 상담
B19: 메리트리무진 (only vehicle / vehicle + driver) 010-5215-2467 ktw1358@hanmail.net | C19: 프리미엄 SUV | D19: 벤츠 S580L 4matic | E19: 880000 | F19: 기준 4인(최대 4인) | G19: 차량 + 기사님(8h): over time(시간 당) 132,000 유류, 톨비, 식사, 숙박 등 행사종류 후 별도 청구 영어 가능 인원 요청시 추가요금 발생 차량만(24h): 자차보험 55,000 | H19: https://meritlimo.kr/Reservation
C20: 벤츠 스프린터 | D20: 스프린터 R-VIP 크리스탈 | E20: 1320000 | F20: 기준 8인(최대 8인)
C21: 벤츠 스프린터 | D21: 스프린터 비즈니스 15 | E21: 660000 | F21: 기준 14인(최대 14인)

Sheet 7. Interpreter
A1: Interpreter for Muslim VIP K-BMW Premium Tour
A6: Premium Package | F6: Information
A7: Package | B7: Partners | C7: Service | D7: Quotation (1,000 KRW) | E7: Check-up-Detail
A8: Interpreter | B8: TRABIC 02-2652-2645 010-5805-5505 service@trabic.kr | C8: Arabic-Korean translation | D8: 1hour: 800 6 hour: 1,000 (초과 시 20 / 1h) | F8: https://trabic.kr/
B9: VERITAS service@veritasco.co.kr | C9: Arabic-Korean translation | D9: General Interpreter: 1,012 / 8h Professional Interpreter : 2,420 / 8h | F9: https://m.blog.naver.com/veritas614/224103518574

Sheet 8. Concierge
A1: Concierge for Muslim VIP K-BMW Premium Tour
A6: Premium Package | F6: Information
A7: Package | B7: Partners | C7: Service | D7: Quotation (KRW) | E7: Check-up-Detail
A8: CONCIERGE | B8: OK KOREA COMPANY 010-6661-4871 okkoreacompany@naver.com | C8: 인력 지원 비용 | D8: 의전 전문 매니저: 시간당 5-10만원 의전도우미: 시간당 3-5만원 수행기사: 시간당 4-7만원 동시통역사: 시간당 15-30만원 | F8: https://okkoreacompany.com/page/56
C9: 개인 의전 | D9: 개인 VIP 수행: 시간당 10-20만원
B10: AS CONCIERGE sy.lee@aysconcierge.kr | C10: CORPORATE CONCIERGE | D10: 가격 문의 필요 | E10: 행사 기획 및 운영: 전략 기획 / 세부 실행 / 브랜드 일관성 / 위기 관리 출장 및 미팅 어레인지: 일정 통합 관리 / 맞춤형 편의 / 효율성 향상 VIP 의전: 고품격 환대 / 세심한 일정 / 전문 통역 / 전담 컨시어지 | F10: https://aysconcierge.kr/?act=main
B11: COSMIJN 02-318-0345 | C11: VIP HOSPITALITY | D11: 가격 문의 필요 | E11: 입국전부터 출국까지 / 일정에 맞춘 수송, 통역, 가이드배치 / 항공 호텔 각종 수배 / 다양한 테마 럭셔리 투어 | F11: https://home.cosmojin.com/vip-hospitality/

Sheet 9. Restaurant
A1: Restaurant for Muslim VIP K-BMW Premium Tour https://www.google.com/maps/d/u/0/viewer?mid=10rZlYa6GN93AbUi3JVpfSpR7oWv2Xzc&ll=37.39450627579441%2C127.03297210349965&z=11
A2: https://www.google.com/maps/d/u/0/viewer?mid=10rZlYa6GN93AbUi3JVpfSpR7oWv2Xzc&ll=37.39450627579441%2C127.03297210349965&z=11
A6: Premium Package | G6: Information
A7: Package | B7: Category | C7: Partners | D7: location & Contact Point | F7: Check-up-Detail
A8: Restaurant | B8: 터키음식 | C8: 케르반 | D8: 서울특별시 용산구(케르반 레스토랑) 0507-1412-4767 서울특별시 서초구(케르반 파미에스테이션) 0507-1316-4767 서울특별시 강남구(케르반 코엑스몰점) 0507-1326-4767 | F8: 튀르키예 전통 케밥과 피데 그리고 디저트 까지, 튀르키예 문화와 음식을 다양하게 경험할 수 있는 레스토랑
C9: 케르반 베이커리 | D9: 서울특별시 용산구 0507-1387-5585 | F9: 튀르키예 전통 케밥과 피데 그리고 디저트 까지, 튀르키예 문화와 음식을 다양하게 경험할 수 있는 레스토랑
C10: 할랄가이즈 | D10: 서울특별시 용산구(할랄가이즈 이태원점) 02-794-8309 | F10: 뉴욕에서 시작된 세계적인 할랄 음식 프랜차이즈 | G10: https://thehalalguys.co.kr/
C11: 질할브로스 | D11: 서울특별시 마포구(질할브로스 연남점) 0507-1406-1422 서울특별시 송파구(질할브로스 송파점) 0507-1325-1422 서울특별시 종로구(질할브로스 광화문점) 0507-1411-8122 서울특별시 용산구(질할브로스 이태원점) 02-749-1422 서울특별시 영등포구(질할브로스 여의도점) 0507-1364-1422 서울특별시 강남구(질할브로스 청담점 / 역삼점) 0507-1446-1625 / 02-566-1422 | F11: 신선한 숙성 닭고기, 양고기 위에 바스마티 라이스, 특제 화이트 소스와 레드 소스로 완성된 뉴욕식 덮밥 | G11: https://jilhalbros.com/
B12: 중동 음식 | C12: 페트라 | D12: 서울특별시 용산구 02-790-4433 | F12: 한국 첫 중동 음식점
B13: 한국음식 | C13: 이드 | D13: 서울특별시 용산구(이드 한식) 0507-1404-8219 서울특별시 마포구(이드 할랄 바비큐) 0507-1428-8318 | F13: 대한민국 최초 할랄 한식 인증 레스토랑
C14: 발우공양 | D14: 서울특별시 종로구 02-733-2081 | F14: 대한 불교 조계종에서 운영하는 사찰음식 전문점 미쉐린 가이드 스타 레스토랑에 2017년부터 2년 연속 선정될 정도로 훌륭한 음식을 제공 계절에 따라 코스를 구성하는 요리가 달라지는데, 고기와 해산물 등 동물성 재료는 물론 파, 마늘, 부추 등을 사용하지 않아 자극적이지 않고 담백한 맛을 자랑 | G14: http://balwoo.or.kr/responsible_start.php

Sheet 10. Insurance
A1: Insurance for Muslim VIP K-BMW Premium Tour
A6: Premium Package | L6: Information
A7: Package | B7: Partners | C7: Service | D7: Medical Coverage (USD) | E7: Repatration | F7: High-Value Items Coverage | G7: Travel Delay / Cancellation | H7: 24/7 Arabic Support | I7: Concierge Service | J7: Recommended for Muslim VIP | K7: Notes
A8: INSURANCE | B8: Allianz Global Assistance | C8: OneTrip Prime VIP | D8: 500000 | E8: Included | G8: Included | H8: Yes | I8: Yes | J8: Highly Recommended | K8: Strong global medical network | L8: https://buly.kr/6Mt081U
B9: AXA Assistance | C9: Platinum Premium | D9: 300000 | E9: Included | G9: Included | H9: Yes | I9: Optional | J9: Recommended | K9: Flexible upgrade options
B10: IMG Global | C10: Platinum Traveler | D10: 500,000+ | E10: Included | G10: Optional | H10: English Only | I10: Yes | J10: Medical-Focused VIP | K10: Excellent evacuation coverage

Sheet 11. Security
A1: Security for Muslim VIP K-BMW Premium Tour
A6: Premium Package | G6: Information
A7: Package | B7: Partners | C7: Contact Point | D7: Service | E7: Quotation (KRW) | F7: Check-up-Detail
A8: Security | B8: KOREA SPECIAL SECURITY | C8: 1688-8596 pia707@naver.com | D8: VIP 의전수행 및 경호 | E8: 가격 문의 필요 | F8: 해외 VIP 수행경호 및 통역가이드 / 해외(기업인, 정치인, 연예인, 종교인) 국내 출장(여행) 수행 경호 | G8: http://kss007.com/
B9: TEAMGUARD COMPANY | C9: 1668-1028 tg.si@outlook.kr | D9: 신변보호 / VIP의전수행 | E9: 1,000 / 10h | F9: 국내/외 VIP 수행 경호 및 통역 | G9: https://teamguard.muv.kr/59
B10: TRIPLE SECURITY | C10: 1670-1780 triplesecu@triplesecu.co.kr | D10: 경호서비스 | E10: 가격 문의 필요 | F10: VIP 의전 업무: 국내/외 VIP 의전수행 및 통역가이드 개인신변보호업무: 개인경호 수행비서/기사 업무: VP 맞춤 서비스 / 의전 및 비서 업무 수행 / 경호운전 및 차량관리 서비스 | G10: http://xn--oy2ba961ev3n6zczj09j.com/bbs/content.php?co_id=0201
